Workbook

Sheet Income Statement
A1: Selvara Industrial Services, LLC | Detailed Income Statement
A2: Company-prepared monthly reporting package | USD, whole dollars (scale=1) | Unaudited | Source: Archive/<YYYY-MM>/monthly.xlsx 'Income Statement' tab (Jun 2026: June_2026_Monthly_Package.xlsx). Mar 2026 Revenue is RESTATED (sourced from consolidated-revised.xlsx) -- see Sources & Notes.
A6: Account | B6: Sep 2024 | C6: Oct 2024 | D6: Nov 2024 | E6: Dec 2024 | F6: Jan 2025 | G6: Feb 2025 | H6: Mar 2025 | I6: Apr 2025 | J6: May 2025 | K6: Jun 2025 | L6: Jul 2025 | M6: Aug 2025 | N6: Sep 2025 | O6: Oct 2025 | P6: Nov 2025 | Q6: Dec 2025 | R6: Jan 2026 | S6: Feb 2026 | T6: Mar 2026 | U6: Apr 2026 | V6: May 2026 | W6: Jun 2026 | X6: FY2024 (Sep-Dec, partial) | Y6: FY2025 | Z6: 2026 YTD (Jan-Jun)
A7: Revenue | B7: 12605500 | C7: 12789884 | D7: 13135791 | E7: 11437824 | F7: 12196317 | G7: 12295356 | H7: 12414623 | I7: 12502993 | J7: 12797821 | K7: 13593991 | L7: 13459064 | M7: 13155748 | N7: 13257192 | O7: 13979177 | P7: 14953029 | Q7: 12954797 | R7: 13016048 | S7: 13214769 | T7: 13729801 | U7: 13919077 | V7: 14115739 | W7: 14657475 | X7: =SUM(B7:E7) -> 49968998 | Y7: =SUM(F7:Q7) -> 1.5756011e+08 | Z7: =SUM(R7:W7) -> 82652910
A8: Reported EBITDA | B8: 2199513.6 | C8: 2301954.6 | D8: 2318831.9 | E8: 1660921.8 | F8: 1940600.6 | G8: 1912991 | H8: 2011459.6 | I8: 2055899 | J8: 2060893.1 | K8: 2392917 | L8: 2382134 | M8: 2492072.9 | N8: 2305563.4 | O8: 2495150.9 | P8: 2835136.1 | Q8: 2248759.6 | R8: 2332371.7 | S8: 2306219.1 | T8: 2618535.9 | U8: 2763848.1 | V8: 2588973.9 | W8: 2696995.1 | X8: =SUM(B8:E8) -> 8481221.9 | Y8: =SUM(F8:Q8) -> 27133577 | Z8: =SUM(R8:W8) -> 15306944
A9: EBITDA margin | B9: =IF(B7=0,"",B8/B7) -> 0.17448841 | C9: =IF(C7=0,"",C8/C7) -> 0.17998245 | D9: =IF(D7=0,"",D8/D7) -> 0.17652778 | E9: =IF(E7=0,"",E8/E7) -> 0.14521309 | F9: =IF(F7=0,"",F8/F7) -> 0.15911366 | G9: =IF(G7=0,"",G8/G7) -> 0.15558646 | H9: =IF(H7=0,"",H8/H7) -> 0.16202341 | I9: =IF(I7=0,"",I8/I7) -> 0.16443255 | ... Z9: =IF(Z7=0,"",Z8/Z7) -> 0.18519546

Sheet Balance Sheet
A1: Selvara Industrial Services, LLC | Balance Sheet (Working Capital detail -- no full Balance Sheet in borrower's monthly reporting; see Sources & Notes)
A2: Company-prepared monthly reporting package | USD, whole dollars (scale=1) | Unaudited | Source: Archive/<YYYY-MM>/monthly.xlsx 'Working Capital' and 'Debt Roll-Forward' tabs (Jun 2026: June_2026_Monthly_Package.xlsx). No Total Assets/Liabilities/Equity or Balance-Check row: this borrower's monthly package carries no full Balance Sheet -- see Sources & Notes.
A6: Account | B6: Sep 2024 | C6: Oct 2024 | D6: Nov 2024 | E6: Dec 2024 | F6: Jan 2025 | G6: Feb 2025 | H6: Mar 2025 | I6: Apr 2025 | J6: May 2025 | K6: Jun 2025 | L6: Jul 2025 | M6: Aug 2025 | N6: Sep 2025 | O6: Oct 2025 | P6: Nov 2025 | Q6: Dec 2025 | R6: Jan 2026 | S6: Feb 2026 | T6: Mar 2026 | U6: Apr 2026 | V6: May 2026 | W6: Jun 2026 | X6: FY2024 (Sep-Dec, spot) | Y6: FY2025 (spot) | Z6: 2026 YTD (Jun, spot)
A7: Accounts receivable | B7: 17530889 | C7: 17503382 | D7: 17891823 | E7: 15698032 | F7: 16936619 | G7: 16898737 | H7: 16822642 | I7: 16773182 | J7: 17133723 | K7: 18492359 | L7: 18407513 | M7: 18074244 | N7: 18032433 | O7: 19068529 | P7: 20708949 | Q7: 18035669 | R7: 17805086 | S7: 17955347 | T7: 18650562 | U7: 18777763 | V7: 18919796 | W7: 19744596 | X7: =E7 -> 15698032 | Y7: =Q7 -> 18035669 | Z7: =W7 -> 19744596
A8: Accounts payable | B8: 8239458.9 | C8: 8396814.4 | D8: 8688537.4 | E8: 7680727.5 | F8: 8217878.3 | G8: 8308218 | H8: 8268139.1 | I8: 8396009.8 | J8: 8649279.6 | K8: 9027497.3 | L8: 8991192.8 | M8: 8501244.6 | N8: 8784746 | O8: 9392329.2 | P8: 9944362.7 | Q8: 8540838.8 | R8: 8593715.5 | S8: 8785178.4 | T8: 8896911.2 | U8: 9007870.1 | V8: 9375674.2 | W8: 9760119.4 | X8: =E8 -> 7680727.5 | Y8: =Q8 -> 8540838.8 | Z8: =W8 -> 9760119.4
A9: Net working capital | B9: =B7-B8 -> 9291429.9 | C9: =C7-C8 -> 9106567.7 | D9: =D7-D8 -> 9203285.3 | E9: =E7-E8 -> 8017304.6 | F9: =F7-F8 -> 8718740.4 | G9: =G7-G8 -> 8590519.4 | H9: =H7-H8 -> 8554503.1 | I9: =I7-I8 -> 8377171.9 | ... W9: =W7-W8 -> 9984476.4 | X9: =E9 -> 8017304.6 | Y9: =Q9 -> 9494830.1 | Z9: =W9 -> 9984476.4
A11: DEBT ROLL-FORWARD (borrower-certified; source: monthly.xlsx / June_2026_Monthly_Package.xlsx 'Debt Roll-Forward' tab)
A12: Beginning debt | B12: 1.2380173e+08 | C12: 1.2355413e+08 | D12: 1.2330702e+08 | E12: 1.2306041e+08 | F12: 1.2281429e+08 | G12: 1.2256866e+08 | H12: 1.2232352e+08 | I12: 1.2207887e+08 | J12: 1.2183472e+08 | K12: 1.2159105e+08 | L12: 1.2134787e+08 | M12: 1.2110517e+08 | N12: 1.2086296e+08 | O12: 1.2062123e+08 | P12: 1.1820881e+08 | Q12: 1.1584463e+08 | R12: 1.1352774e+08 | S12: 1.1125718e+08 | T12: 1.0903204e+08 | U12: 1.068514e+08 | V12: 1.0471437e+08 | W12: 1.0262008e+08 | X12: =B12 -> 1.2380173e+08 | Y12: =F12 -> 1.2281429e+08 | Z12: =R12 -> 1.1352774e+08
A13: Required principal | B13: 247603.47 | C13: 247108.26 | D13: 246614.04 | E13: 246120.82 | F13: 245628.57 | G13: 245137.32 | H13: 244647.04 | I13: 244157.75 | J13: 243669.43 | K13: 243182.09 | L13: 242695.73 | M13: 242210.34 | N13: 241725.92 | O13: 2412424.7 | P13: 2364176.2 | Q13: 2316892.6 | R13: 2270554.8 | S13: 2225143.7 | T13: 2180640.8 | U13: 2137028 | V13: 2094287.4 | W13: 2052401.7 | X13: =SUM(B13:E13) -> 987446.59 | Y13: =SUM(F13:Q13) -> 9286547.7 | Z13: =SUM(R13:W13) -> 12960056
A14: Draws | B14: 0 | C14: 0 | D14: 0 | E14: 0 | F14: 0 | G14: 0 | H14: 0 | I14: 0 | J14: 0 | K14: 0 | L14: 0 | M14: 0 | N14: 0 | O14: 0 | P14: 0 | Q14: 0 | R14: 0 | S14: 0 | T14: 0 | U14: 0 | V14: 0 | W14: 0 | X14: =SUM(B14:E14) -> 0 | Y14: =SUM(F14:Q14) -> 0 | Z14: =SUM(R14:W14) -> 0
A15: PIK | B15: 0 | C15: 0 | D15: 0 | E15: 0 | F15: 0 | G15: 0 | H15: 0 | I15: 0 | J15: 0 | K15: 0 | L15: 0 | M15: 0 | N15: 0 | O15: 0 | P15: 0 | Q15: 0 | R15: 0 | S15: 0 | T15: 0 | U15: 0 | V15: 0 | W15: 0 | X15: =SUM(B15:E15) -> 0 | Y15: =SUM(F15:Q15) -> 0 | Z15: =SUM(R15:W15) -> 0
A16: Ending debt | B16: =B12-B13+B14+B15 -> 1.2355413e+08 | C16: =C12-C13+C14+C15 -> 1.2330702e+08 | D16: =D12-D13+D14+D15 -> 1.2306041e+08 | E16: =E12-E13+E14+E15 -> 1.2281429e+08 | F16: =F12-F13+F14+F15 -> 1.2256866e+08 | G16: =G12-G13+G14+G15 -> 1.2232352e+08 | H16: =H12-H13+H14+H15 -> 1.2207887e+08 | I16: =I12-I13+I14+I15 -> 1.2183472e+08 | ... W16: =W12-W13+W14+W15 -> 1.0056768e+08 | X16: =E16 -> 1.2281429e+08 | Y16: =Q16 -> 1.1352774e+08 | Z16: =W16 -> 1.0056768e+08
A18: COVENANT-SUPPORT ROWS (Fixed_Charges inputs; DEVIATION -- sourced from this borrower's native Cash-Flow-tab ledger lines, NOT debt-service-schedule.json, per covenant-spec.json step7_signoff 'fixed_charges_component_source' -- see Sources & Notes)
A19: Cash Interest Expense | B19: =-'Cash Flow Statement'!B12 -> 1058000.7 | C19: =-'Cash Flow Statement'!C12 -> 1055884.7 | D19: =-'Cash Flow Statement'!D12 -> 1053772.9 | E19: =-'Cash Flow Statement'!E12 -> 1051665.4 | F19: =-'Cash Flow Statement'!F12 -> 1049562.1 | G19: =-'Cash Flow Statement'!G12 -> 1047462.9 | H19: =-'Cash Flow Statement'!H12 -> 1045368 | I19: =-'Cash Flow Statement'!I12 -> 1043277.3 | ... W19: =-'Cash Flow Statement'!W12 -> 876983.86 | X19: =SUM(B19:E19) -> 4219323.7 | Y19: =SUM(F19:Q19) -> 12401866 | Z19: =SUM(R19:W19) -> 5537785.5
A20: Scheduled Debt Principal Payments | B20: =-'Cash Flow Statement'!B18 -> 247603.47 | C20: =-'Cash Flow Statement'!C18 -> 247108.26 | D20: =-'Cash Flow Statement'!D18 -> 246614.04 | E20: =-'Cash Flow Statement'!E18 -> 246120.82 | F20: =-'Cash Flow Statement'!F18 -> 245628.57 | G20: =-'Cash Flow Statement'!G18 -> 245137.32 | H20: =-'Cash Flow Statement'!H18 -> 244647.04 | I20: =-'Cash Flow Statement'!I18 -> 244157.75 | ... W20: =-'Cash Flow Statement'!W18 -> 2052401.7 | X20: =SUM(B20:E20) -> 987446.59 | Y20: =SUM(F20:Q20) -> 9286547.7 | Z20: =SUM(R20:W20) -> 12960056

Sheet Cash Flow Statement
A1: Selvara Industrial Services, LLC | Detailed Cash Flow Statement (as reported, single blended waterfall; two DERIVED Operating/Financing subtotal rows added below -- see Sources & Notes)
A2: Company-prepared monthly reporting package | USD, whole dollars (scale=1) | Unaudited | Source: Archive/<YYYY-MM>/monthly.xlsx 'Cash Flow' tab (Jun 2026: June_2026_Monthly_Package.xlsx). No native Operating/Investing/Financing split -- see derived rows and Sources & Notes.
A6: Account | B6: Sep 2024 | C6: Oct 2024 | D6: Nov 2024 | E6: Dec 2024 | F6: Jan 2025 | G6: Feb 2025 | H6: Mar 2025 | I6: Apr 2025 | J6: May 2025 | K6: Jun 2025 | L6: Jul 2025 | M6: Aug 2025 | N6: Sep 2025 | O6: Oct 2025 | P6: Nov 2025 | Q6: Dec 2025 | R6: Jan 2026 | S6: Feb 2026 | T6: Mar 2026 | U6: Apr 2026 | V6: May 2026 | W6: Jun 2026 | X6: FY2024 (Sep-Dec, partial) | Y6: FY2025 | Z6: 2026 YTD (Jan-Jun)
A7: Beginning cash | B7: 8421637.4 | C7: 8869981.8 | D7: 9440990.1 | E7: 9588282 | F7: 11902593 | G7: 18843648 | H7: 19089598 | I7: 19479483 | J7: 19868595 | K7: 19830996 | L7: 19072756 | M7: 19809761 | N7: 20960406 | O7: 21547628 | P7: 19014390 | Q7: 16246988 | R7: 17597497 | S7: 16470644 | T7: 14979786 | U7: 13295255 | V7: 12377153 | W7: 11304194 | X7: =B7 -> 8421637.4 | Y7: =F7 -> 11902593 | Z7: =R7 -> 17597497
A8: Reported EBITDA | B8: 2199513.6 | C8: 2301954.6 | D8: 2318831.9 | E8: 1660921.8 | F8: 1940600.6 | G8: 1912991 | H8: 2011459.6 | I8: 2055899 | J8: 2060893.1 | K8: 2392917 | L8: 2382134 | M8: 2492072.9 | N8: 2305563.4 | O8: 2495150.9 | P8: 2835136.1 | Q8: 2248759.6 | R8: 2332371.7 | S8: 2306219.1 | T8: 2618535.9 | U8: 2763848.1 | V8: 2588973.9 | W8: 2696995.1 | X8: =SUM(B8:E8) -> 8481221.9 | Y8: =SUM(F8:Q8) -> 27133577 | Z8: =SUM(R8:W8) -> 15306944
A9: Cash taxes | B9: -153965.95 | C9: -161136.82 | D9: -162318.24 | E9: -116264.53 | F9: -135842.04 | G9: -133909.37 | H9: -140802.17 | I9: -143912.93 | J9: -144262.52 | K9: -167504.19 | L9: -166749.38 | M9: -174445.1 | N9: -161389.43 | O9: -174660.57 | P9: -198459.53 | Q9: -157413.17 | R9: -163266.02 | S9: -161435.33 | T9: -183297.51 | U9: -193469.37 | V9: -181228.17 | W9: -188789.66 | X9: =SUM(B9:E9) -> -593685.54 | Y9: =SUM(F9:Q9) -> -1899350.4 | Z9: =SUM(R9:W9) -> -1071486.1
A10: Capital expenditures | B10: -252110 | C10: -255797.67 | D10: -262715.82 | E10: -228756.48 | F10: -243926.34 | G10: -245907.12 | H10: -248292.47 | I10: -250059.86 | J10: -255956.43 | K10: -271879.81 | L10: -269181.27 | M10: -263114.97 | N10: -265143.85 | O10: -279583.53 | P10: -299060.59 | Q10: -259095.95 | R10: -260320.96 | S10: -264295.38 | T10: -274596.03 | U10: -278381.55 | V10: -282314.79 | W10: -293149.5 | X10: =SUM(B10:E10) -> -999379.97 | Y10: =SUM(F10:Q10) -> -3151202.2 | Z10: =SUM(R10:W10) -> -1653058.2
A11: Working-capital increase | B11: -15918.97 | C11: 7837.23 | D11: -424905.94 | E11: 2319766.9 | F11: -1305730.5 | G11: 26588.88 | H11: 81105.15 | I11: 33476.68 | J11: -392200.41 | K11: -1405912.4 | L11: 89384.02 | M11: 394511.89 | N11: 6373.35 | O11: -1112043.7 | P11: -1709424 | Q11: 2848720.3 | R11: 223973.42 | S11: -174194.06 | T11: -709181.53 | U11: -141071.01 | V11: -188008.4 | W11: -872855.34 | X11: =SUM(B11:E11) -> 1886779.2 | Y11: =SUM(F11:Q11) -> -2445150.8 | Z11: =SUM(R11:W11) -> -1861336.9
A12: Cash interest | B12: -1058000.7 | C12: -1055884.7 | D12: -1053772.9 | E12: -1051665.4 | F12: -1049562.1 | G12: -1047462.9 | H12: -1045368 | I12: -1043277.3 | J12: -1041190.7 | K12: -1039108.3 | L12: -1037030.1 | M12: -1034956.1 | N12: -1032886.1 | O12: -1030820.4 | P12: -1010204 | Q12: -989999.89 | R12: -970199.89 | S12: -950795.89 | T12: -931779.97 | U12: -913144.37 | V12: -894881.49 | W12: -876983.86 | X12: =SUM(B12:E12) -> -4219323.7 | Y12: =SUM(F12:Q12) -> -12401866 | Z12: =SUM(R12:W12) -> -5537785.5
A13: Lease payments | B13: -23570.1 | C13: -18856.08 | D13: -21213.09 | E13: -23570.1 | F13: -18856.08 | G13: -21213.09 | H13: -23570.1 | I13: -18856.08 | J13: -21213.09 | K13: -23570.1 | L13: -18856.08 | M13: -21213.09 | N13: -23570.1 | O13: -18856.08 | P13: -21213.09 | Q13: -23570.1 | R13: -18856.08 | S13: -21213.09 | T13: -23570.1 | U13: -18856.08 | V13: -21213.09 | W13: -23570.1 | X13: =SUM(B13:E13) -> -87209.37 | Y13: =SUM(F13:Q13) -> -254557.08 | Z13: =SUM(R13:W13) -> -127278.54
A14: Legacy debt payoff | B14: 0 | C14: 0 | D14: 0 | E14: 0 | F14: -1.2281429e+08 | G14: 0 | H14: 0 | I14: 0 | J14: 0 | K14: 0 | L14: 0 | M14: 0 | N14: 0 | O14: 0 | P14: 0 | Q14: 0 | R14: 0 | S14: 0 | T14: 0 | U14: 0 | V14: 0 | W14: 0 | X14: =SUM(B14:E14) -> 0 | Y14: =SUM(F14:Q14) -> -1.2281429e+08 | Z14: =SUM(R14:W14) -> 0
A15: New facility funding | B15: 0 | C15: 0 | D15: 0 | E15: 0 | F15: 1.2281429e+08 | G15: 0 | H15: 0 | I15: 0 | J15: 0 | K15: 0 | L15: 0 | M15: 0 | N15: 0 | O15: 0 | P15: 0 | Q15: 0 | R15: 0 | S15: 0 | T15: 0 | U15: 0 | V15: 0 | W15: 0 | X15: =SUM(B15:E15) -> 0 | Y15: =SUM(F15:Q15) -> 1.2281429e+08 | Z15: =SUM(R15:W15) -> 0
A16: Sponsor equity | B16: 0 | C16: 0 | D16: 0 | E16: 0 | F16: 12000000 | G16: 0 | H16: 0 | I16: 0 | J16: 0 | K16: 0 | L16: 0 | M16: 0 | N16: 0 | O16: 0 | P16: 0 | Q16: 0 | R16: 0 | S16: 0 | T16: 0 | U16: 0 | V16: 0 | W16: 0 | X16: =SUM(B16:E16) -> 0 | Y16: =SUM(F16:Q16) -> 12000000 | Z16: =SUM(R16:W16) -> 0
A17: Closing fees | B17: 0 | C17: 0 | D17: 0 | E17: 0 | F17: -4000000 | G17: 0 | H17: 0 | I17: 0 | J17: 0 | K17: 0 | L17: 0 | M17: 0 | N17: 0 | O17: 0 | P17: 0 | Q17: 0 | R17: 0 | S17: 0 | T17: 0 | U17: 0 | V17: 0 | W17: 0 | X17: =SUM(B17:E17) -> 0 | Y17: =SUM(F17:Q17) -> -4000000 | Z17: =SUM(R17:W17) -> 0
A18: Required principal | B18: -247603.47 | C18: -247108.26 | D18: -246614.04 | E18: -246120.82 | F18: -245628.57 | G18: -245137.32 | H18: -244647.04 | I18: -244157.75 | J18: -243669.43 | K18: -243182.09 | L18: -242695.73 | M18: -242210.34 | N18: -241725.92 | O18: -2412424.7 | P18: -2364176.2 | Q18: -2316892.6 | R18: -2270554.8 | S18: -2225143.7 | T18: -2180640.8 | U18: -2137028 | V18: -2094287.4 | W18: -2052401.7 | X18: =SUM(B18:E18) -> -987446.59 | Y18: =SUM(F18:Q18) -> -9286547.7 | Z18: =SUM(R18:W18) -> -12960056
A19: Ending cash | B19: =SUM(B7:B18) -> 8869981.8 | C19: =SUM(C7:C18) -> 9440990.1 | D19: =SUM(D7:D18) -> 9588282 | E19: =SUM(E7:E18) -> 11902593 | F19: =SUM(F7:F18) -> 18843648 | G19: =SUM(G7:G18) -> 19089598 | H19: =SUM(H7:H18) -> 19479483 | I19: =SUM(I7:I18) -> 19868595 | ... W19: =SUM(W7:W18) -> 9693438.6 | X19: =E19 -> 11902593 | Y19: =Q19 -> 17597497 | Z19: =W19 -> 9693438.6
A21: Operating Cash Flow (derived) | B21: =B8+B9+B11+B12+B13 -> 948057.88 | C21: =C8+C9+C11+C12+C13 -> 1073914.2 | D21: =D8+D9+D11+D12+D13 -> 656621.73 | E21: =E8+E9+E11+E12+E13 -> 2789188.6 | F21: =F8+F9+F11+F12+F13 -> -569390.12 | G21: =G8+G9+G11+G12+G13 -> 736994.47 | H21: =H8+H9+H11+H12+H13 -> 882824.46 | I21: =I8+I9+I11+I12+I13 -> 883329.44 | ... W21: =W8+W9+W11+W12+W13 -> 734796.12 | X21: =SUM(B21:E21) -> 5467782.5 | Y21: =SUM(F21:Q21) -> 10132653 | Z21: =SUM(R21:W21) -> 6709056.7
A22: Financing Cash Flow (derived) | B22: =B14+B15+B16+B17+B18 -> -247603.47 | C22: =C14+C15+C16+C17+C18 -> -247108.26 | D22: =D14+D15+D16+D17+D18 -> -246614.04 | E22: =E14+E15+E16+E17+E18 -> -246120.82 | F22: =F14+F15+F16+F17+F18 -> 7754371.4 | G22: =G14+G15+G16+G17+G18 -> -245137.32 | H22: =H14+H15+H16+H17+H18 -> -244647.04 | I22: =I14+I15+I16+I17+I18 -> -244157.75 | ... W22: =W14+W15+W16+W17+W18 -> -2052401.7 | X22: =SUM(B22:E22) -> -987446.59 | Y22: =SUM(F22:Q22) -> -1286547.7 | Z22: =SUM(R22:W22) -> -12960056
A24: Memo: Net change in cash (derived: Operating + Investing[Capex] + Financing) | B24: =B21+B10+B22 -> 448344.41 | C24: =C21+C10+C22 -> 571008.3 | D24: =D21+D10+D22 -> 147291.87 | E24: =E21+E10+E22 -> 2314311.4 | F24: =F21+F10+F22 -> 6941055 | G24: =G21+G10+G22 -> 245950.03 | H24: =H21+H10+H22 -> 389884.95 | I24: =I21+I10+I22 -> 389111.83 | ... W24: =W21+W10+W22 -> -1610755.1 | X24: =SUM(B24:E24) -> 3480955.9 | Y24: =SUM(F24:Q24) -> 5694903.2 | Z24: =SUM(R24:W24) -> -7904057.9
A25: Memo: Net change in cash (native: Ending cash - Beginning cash) | B25: =B19-B7 -> 448344.41 | C25: =C19-C7 -> 571008.3 | D25: =D19-D7 -> 147291.87 | E25: =E19-E7 -> 2314311.4 | F25: =F19-F7 -> 6941055 | G25: =G19-G7 -> 245950.03 | H25: =H19-H7 -> 389884.95 | I25: =I19-I7 -> 389111.83 | ... W25: =W19-W7 -> -1610755.1 | X25: =SUM(B25:E25) -> 3480955.9 | Y25: =SUM(F25:Q25) -> 5694903.2 | Z25: =SUM(R25:W25) -> -7904057.9
A26: Memo: CF derivation tie (diff, should be 0) | B26: =B24-B25 -> 0 | C26: =C24-C25 -> 0 | D26: =D24-D25 -> 0 | E26: =E24-E25 -> 0 | F26: =F24-F25 -> 0 | G26: =G24-G25 -> -1.4551915e-09 | H26: =H24-H25 -> 0 | I26: =I24-I25 -> 1.8626451e-09 | ... W26: =W24-W25 -> 0 | X26: =SUM(B26:E26) -> 0 | Y26: =SUM(F26:Q26) -> -3.4924597e-10 | Z26: =SUM(R26:W26) -> 0
A28: Memo: Reported EBITDA per Income Statement | B28: ='Income Statement'!B8 -> 2199513.6 | C28: ='Income Statement'!C8 -> 2301954.6 | D28: ='Income Statement'!D8 -> 2318831.9 | E28: ='Income Statement'!E8 -> 1660921.8 | F28: ='Income Statement'!F8 -> 1940600.6 | G28: ='Income Statement'!G8 -> 1912991 | H28: ='Income Statement'!H8 -> 2011459.6 | I28: ='Income Statement'!I8 -> 2055899 | ... W28: ='Income Statement'!W8 -> 2696995.1 | X28: =SUM(B28:E28) -> 8481221.9 | Y28: =SUM(F28:Q28) -> 27133577 | Z28: =SUM(R28:W28) -> 15306944
A29: Memo: CF-vs-IS EBITDA tie (diff, should be 0) | B29: =B8-B28 -> 0 | C29: =C8-C28 -> 0 | D29: =D8-D28 -> 0 | E29: =E8-E28 -> 0 | F29: =F8-F28 -> 0 | G29: =G8-G28 -> 0 | H29: =H8-H28 -> 0 | I29: =I8-I28 -> 0 | ... W29: =W8-W28 -> 0 | X29: =SUM(B29:E29) -> 0 | Y29: =SUM(F29:Q29) -> 0 | Z29: =SUM(R29:W29) -> 0

Sheet Sources & Notes
A1: Entity | B1: Selvara Industrial Services, LLC (consolidated) -- per borrower-config model.entity='consolidated'. No separate divisional/standalone consolidation level is offered in the reporting package.
A2: Units | B2: USD, whole dollars (model.scale = 1). Verified against June 2026 revenue ($14,657,474.87), consistent with FY2024 annual revenue ($145,482,023.89, ~$12.1M/month average) and the H1 2026 Approved Budget's own June figure ($15,170,486.49), same unit. No '$ in thousands' caption anywhere.
A3: Basis | B3: Actuals only -- company-prepared monthly reporting packages, unaudited. No proforma/budget/forecast columns included.
A4: Coverage | B4: Sep 2024 through Jun 2026 (22 months), continuous, no gaps. Sep 2024-May 2026 from Monthly/Archive/<YYYY-MM>/monthly.xlsx (21 months); Jun 2026 from Monthly/Current/2026-06/June_2026_Monthly_Package.xlsx.
A5: Primary source files | B5: One monthly.xlsx package per Archive period (single-period snapshot, no hidden multi-month columns -- verified identical tab/row shape across 2024-09, 2025-05, 2026-03 and 2026-05). Jun 2026 uses June_2026_Monthly_Package.xlsx, the current-month analog of the same 3-file pattern (verified same tab shape as Archive; its own Revenue 14,657,474.87 and Reported EBITDA 2,696,995.08 tie exactly to consolidated-revised.xlsx's June row -- June's own package was never restated). See source-map.json for the exact file per statement per month.
A6: June 2026 package scope | B6: THE June 2026 monthly package is exactly: June_2026_Monthly_Package.xlsx (used here), June_2026_AR-AP_Detail.xlsx (ap-ar-aging module input, not a statement source), June_2026_Project_Service-Line_Detail.xlsx (sales-by-channel detail, not a statement source). Excluded as monthly-package inputs (restatement/compliance ephemera, read only for the restatement scan below): certificate.xlsx, PM_Update_2026-Q2.pdf, monthly-original.xlsx, consolidated-revised.xlsx (used ONLY for the March 2026 Revenue override below), March_Reporting_Correction_Notice_2026-07-23.pdf, and the Compliance/ subfolder.
A7: RESTATEMENT -- March 2026 Revenue (EPISODE B, financial reporting error) | B7: Monthly/Archive/2026-03/monthly.xlsx was NEVER updated after a 2026-07-22 correction and still shows STALE, UNDERSTATED March 2026 Revenue: $13,111,960.23. The AUTHORITATIVE March 2026 Revenue is $13,729,801.29, taken from consolidated-revised.xlsx ('Revised Authoritative March-June Package', tab 'Income Statement', March row) -- confirmed by direct read on this build date. This model's March 2026 Revenue cell is sourced from consolidated-revised.xlsx, NOT Archive/2026-03/monthly.xlsx. Reported EBITDA for March 2026 is UNCHANGED at $2,618,535.91 in both the stale Archive file and consolidated-revised.xlsx -- the restatement was a pure Revenue/Cost gross-up ($617,841.06 on each side), EBITDA-neutral (independently verified: Revenue - Costs - OpEx ties to 2,618,535.91 under both the original and corrected figures per consolidated-revised.xlsx's own Costs/Operating Expenses columns, which do not exist in the standard monthly Archive schema). April, May and June 2026 are NOT restated -- verified identical between consolidated-revised.xlsx and their respective Archive/June-package files (Revenue and Reported EBITDA match to the penny for all three months). Old->new logged in restatements.json: Mar 2026 Revenue $13,111,960.23 -> $13,729,801.29 (material: diff $617,841.06, 4.71% of the old value, well above the $25k/1% threshold).
A8: Restatement scan -- scope | B8: Full scan performed across all 22 months: each Archive month's own package compared against consolidated-revised.xlsx (the only file whose range overlaps any Archive month, covering Mar-Jun 2026) and against June_2026_Monthly_Package.xlsx for June. Result: only March 2026 Revenue differs (see above); April/May/June match exactly; no other month has a second source to compare against (each Archive month is a single-period snapshot with no other overlapping file). No prior canonical model existed for this borrower (first build) so no prior-snapshot diff applies.
A9: Income Statement -- thin monthly cadence (JUDGMENT CALL, per borrower-config.json model_lines._gap_note) | B9: The borrower's monthly Income Statement has ONLY three rows -- Revenue, Reported EBITDA, EBITDA margin -- with NO Gross Profit, COGS, Net Income, or D&A anywhere in the monthly cadence (not on the IS, not on the Cash Flow tab). model_lines.gross_profit / operating_cogs / net_income / depreciation_amortization are left BLANK/unmapped rather than derived or guessed -- three-statement-analysis will report them in lines_not_found with dependent ratios suppressed. opex_groups is intentionally EMPTY (no opex line at all exists). Both 'Revenue' and 'Reported EBITDA' are entered as hardcoded (blue) source lines -- there is no intermediate detail within this sheet to build EBITDA up from, so Reported EBITDA is NOT a computed subtotal here (unlike Asteron/Nemeris, where component cost lines exist).
A10: EBITDA bridge | B10: Per covenant-spec.json#/definitions/EBITDA, compute.ebitda_bridge = 'Reported EBITDA' -- the model's own single pinned EBITDA row, bound directly with NO addback. Verified at three independent points that 'Reported EBITDA' ties EXACTLY to the certified 'Covenant EBITDA': Mar 2026 both 2,618,535.91; Jun 2026 both 2,696,995.08; May 2026 both 2,588,973.90. This EBITDA bridge is NOT provisional -- it is the covenant-spec-directed definition, with a covenant-spec.json present.
A11: Interest / taxes -- cash basis only | B11: model_lines.interest_expense maps to the Cash Flow tab's 'Cash interest' line; model_lines.taxes maps to 'Cash taxes' -- both cash-basis, not accrual IS rows (there is no accrual IS interest/tax line at all in this borrower's monthly cadence).
A12: Balance Sheet -- NO native Balance Sheet exists (JUDGMENT CALL, per borrower-config.json analysis_lines._omitted_note) | B12: This borrower's monthly package carries NO Balance Sheet tab at all -- only a 'Working Capital' tab (Accounts receivable, Accounts payable, Net working capital) and a 'Cash Flow' tab. The 'Balance Sheet' sheet in this model therefore carries Working Capital detail ONLY (rows 7-9): there is no Total Assets/Total Liabilities/Total Equity, and consequently NO Balance-Check row -- inventing one from non-existent data would misstate the model. This is a disclosed, borrower-config-documented gap, not an omission. Supplementary detail below the Working Capital rows (rows 11-20) reproduces the borrower's own Debt Roll-Forward tab and the covenant-support rows -- see below. 'cash' (analysis_lines.cash) maps instead to the Cash Flow Statement sheet's 'Ending cash' row, the closest thing to a period-end cash balance this borrower reports. 'inventory' is also omitted (not part of pledged collateral per collateral-map.json, and no monthly row exists to track it against, even though FY2024 annual statements show a real $8,640,818.48 inventory balance -- annual-only, not part of the monthly cadence).
... A19: Build tool / recalc | B19: Built with openpyxl; formula cells recalculated (cached values populated) via headless LibreOffice as the LAST write, per assembling-rules.md. Gated with references/validate_model.py before becoming canonical.
