Workbook

Sheet Income Statement
A1: Orinth Vale Infrastructure, LLC | Detailed Income Statement
A2: Company-prepared monthly reporting package | USD (whole dollars) | Unaudited | Source: borrower Monthly Reporting Package ('a.xlsx'), 'Income Statement' tab
A6: Account | B6: Sep 2024 | C6: Oct 2024 | D6: Nov 2024 | E6: Dec 2024 | F6: Jan 2025 | G6: Feb 2025 | H6: Mar 2025 | I6: Apr 2025 | J6: May 2025 | K6: Jun 2025 | L6: Jul 2025 | M6: Aug 2025 | N6: Sep 2025 | O6: Oct 2025 | P6: Nov 2025 | Q6: Dec 2025 | R6: Jan 2026 | S6: Feb 2026 | T6: Mar 2026 | U6: Apr 2026 | V6: May 2026 | W6: Jun 2026 | X6: FY2024 (Sep-Dec, partial) | Y6: FY2025 | Z6: 2026 YTD (Jan-Jun)
A7: Revenue | B7: 10710057 | C7: 11113874 | D7: 11701769 | E7: 10057219 | F7: 10690856 | G7: 11205301 | H7: 11462285 | I7: 11958409 | J7: 12282541 | K7: 12398895 | L7: 12326249 | M7: 11512678 | N7: 12131435 | O7: 12640828 | P7: 12905597 | Q7: 10990544 | R7: 11420987 | S7: 11814062 | T7: 12062474 | U7: 12174839 | V7: 12402933 | W7: 13161734 | X7: =SUM(B7:E7) -> 43582919 | Y7: =SUM(F7:Q7) -> 1.4250562e+08 | Z7: =SUM(R7:W7) -> 73037028
A8: Costs | B8: 5908738.3 | C8: 6077066.3 | D8: 6221830.7 | E8: 5421846.8 | F8: 5789098.6 | G8: 6023969.9 | H8: 6242360.7 | I8: 6386986.1 | J8: 6604322.5 | K8: 6792114.5 | L8: 6864488 | M8: 6229509.9 | N8: 6634681.9 | O8: 6973944.6 | P8: 7086463.1 | Q8: 5849167.5 | R8: 6199311.6 | S8: 6417398.3 | T8: 6692260.8 | U8: 6828867 | V8: 6759598.3 | W8: 7253431.7 | X8: =SUM(B8:E8) -> 23629482 | Y8: =SUM(F8:Q8) -> 77477107 | Z8: =SUM(R8:W8) -> 40150868
A9: Operating Expenses | B9: 3274408.5 | C9: 3255942.4 | D9: 3375748 | E9: 3183011.2 | F9: 3196719.9 | G9: 3306242.4 | H9: 3379720.5 | I9: 3374177.2 | J9: 3457056.1 | K9: 3510845.8 | L9: 3425674.9 | M9: 3349275.1 | N9: 3473401.4 | O9: 3469715.9 | P9: 3544283.8 | Q9: 3313676.6 | R9: 3298938.1 | S9: 3391468.9 | T9: 3463746.9 | U9: 3404477.4 | V9: 3473910.8 | W9: 3617643.3 | X9: =SUM(B9:E9) -> 13089110 | Y9: =SUM(F9:Q9) -> 40800789 | Z9: =SUM(R9:W9) -> 20650185
A10: EBITDA | B10: =B7-B8-B9 -> 1526910 | C10: =C7-C8-C9 -> 1780865.4 | D10: =D7-D8-D9 -> 2104190.6 | E10: =E7-E8-E9 -> 1452361.1 | F10: =F7-F8-F9 -> 1705037.7 | G10: =G7-G8-G9 -> 1875088.8 | H10: =H7-H8-H9 -> 1840204.3 | I10: =I7-I8-I9 -> 2197245.4 | ... W10: =W7-W8-W9 -> 2290659.2 | X10: =SUM(B10:E10) -> 6864327.1 | Y10: =SUM(F10:Q10) -> 24227721 | Z10: =SUM(R10:W10) -> 12235975
A12: Gross Profit | B12: =B7-B8 -> 4801318.5 | C12: =C7-C8 -> 5036807.7 | D12: =D7-D8 -> 5479938.5 | E12: =E7-E8 -> 4635372.3 | F12: =F7-F8 -> 4901757.5 | G12: =G7-G8 -> 5181331.2 | H12: =H7-H8 -> 5219924.8 | I12: =I7-I8 -> 5571422.7 | ... W12: =W7-W8 -> 5908302.4 | X12: =SUM(B12:E12) -> 19953437 | Y12: =SUM(F12:Q12) -> 65028510 | Z12: =SUM(R12:W12) -> 32886161
A13: Depreciation and Amortization | B13: 128520.68 | C13: 133366.49 | D13: 140421.23 | E13: 120686.63 | F13: 128290.27 | G13: 134463.61 | H13: 137547.43 | I13: 143500.91 | J13: 147390.5 | K13: 148786.74 | L13: 147914.99 | M13: 138152.13 | N13: 145577.22 | O13: 151689.93 | P13: 154867.16 | Q13: 131886.53 | R13: 137051.84 | S13: 141768.74 | T13: 144749.69 | U13: 146098.06 | V13: 148835.19 | W13: 157940.81 | X13: =SUM(B13:E13) -> 522995.03 | Y13: =SUM(F13:Q13) -> 1710067.4 | Z13: =SUM(R13:W13) -> 876444.33
A14: Operating Income | B14: =B10-B13 -> 1398389.3 | C14: =C10-C13 -> 1647498.9 | D14: =D10-D13 -> 1963769.4 | E14: =E10-E13 -> 1331674.5 | F14: =F10-F13 -> 1576747.4 | G14: =G10-G13 -> 1740625.2 | H14: =H10-H13 -> 1702656.9 | I14: =I10-I13 -> 2053744.5 | ... W14: =W10-W13 -> 2132718.4 | X14: =SUM(B14:E14) -> 6341332 | Y14: =SUM(F14:Q14) -> 22517653 | Z14: =SUM(R14:W14) -> 11359531
A15: Cash Interest | B15: 607001.09 | C15: 603359.08 | D15: 599738.93 | E15: 596140.5 | F15: 592563.65 | G15: 589008.27 | H15: 585474.22 | I15: 581961.38 | J15: 578469.61 | K15: 574998.79 | L15: 571548.8 | M15: 568119.51 | N15: 564710.79 | O15: 561322.52 | P15: 557954.59 | Q15: 554606.86 | R15: 551279.22 | S15: 547971.54 | T15: 544683.72 | U15: 541415.61 | V15: 538167.12 | W15: 534938.12 | X15: =SUM(B15:E15) -> 2406239.6 | Y15: =SUM(F15:Q15) -> 6880739 | Z15: =SUM(R15:W15) -> 3258455.3
A16: Interest Expense | B16: =B15+B20 -> 607001.09 | C16: =C15+C20 -> 603359.08 | D16: =D15+D20 -> 599738.93 | E16: =E15+E20 -> 596140.5 | F16: =F15+F20 -> 642563.65 | G16: =G15+G20 -> 639008.27 | H16: =H15+H20 -> 635474.22 | I16: =I15+I20 -> 631961.38 | ... W16: =W15+W20 -> 584938.12 | X16: =SUM(B16:E16) -> 2406239.6 | Y16: =SUM(F16:Q16) -> 7480739 | Z16: =SUM(R16:W16) -> 3558455.3
A17: Income Before Taxes | B17: =B14-B16 -> 791388.25 | C17: =C14-C16 -> 1044139.8 | D17: =D14-D16 -> 1364030.4 | E17: =E14-E16 -> 735533.97 | F17: =F14-F16 -> 934183.76 | G17: =G14-G16 -> 1101616.9 | H17: =H14-H16 -> 1067182.7 | I17: =I14-I16 -> 1421783.1 | ... W17: =W14-W16 -> 1547780.2 | X17: =SUM(B17:E17) -> 3935092.4 | Y17: =SUM(F17:Q17) -> 15036914 | Z17: =SUM(R17:W17) -> 7801075.5
A18: Income Tax Expense | B18: 114518.25 | C18: 133564.9 | D18: 157814.3 | E18: 108927.08 | F18: 127877.83 | G18: 140631.66 | H18: 138015.32 | I18: 164793.41 | J18: 166587.22 | K18: 157195.08 | L18: 152706.45 | M18: 145041.95 | N18: 151751.39 | O18: 164787.54 | P18: 170613.73 | Q18: 137077.48 | R18: 144205.27 | S18: 150389.59 | T18: 142985 | U18: 145612.07 | V18: 162706.76 | W18: 171799.44 | X18: =SUM(B18:E18) -> 514824.53 | Y18: =SUM(F18:Q18) -> 1817079.1 | Z18: =SUM(R18:W18) -> 917698.13
A19: Net Income | B19: =B17-B18 -> 676870 | C19: =C17-C18 -> 910574.88 | D19: =D17-D18 -> 1206216.1 | E19: =E17-E18 -> 626606.89 | F19: =F17-F18 -> 806305.93 | G19: =G17-G18 -> 960985.28 | H19: =H17-H18 -> 929167.36 | I19: =I17-I18 -> 1256989.7 | ... W19: =W17-W18 -> 1375980.8 | X19: =SUM(B19:E19) -> 3420267.9 | Y19: =SUM(F19:Q19) -> 13219835 | Z19: =SUM(R19:W19) -> 6883377.3
A20: Deferred Financing Fee Amortization | B20: 0 | C20: 0 | D20: 0 | E20: 0 | F20: 50000 | G20: 50000 | H20: 50000 | I20: 50000 | J20: 50000 | K20: 50000 | L20: 50000 | M20: 50000 | N20: 50000 | O20: 50000 | P20: 50000 | Q20: 50000 | R20: 50000 | S20: 50000 | T20: 50000 | U20: 50000 | V20: 50000 | W20: 50000 | X20: =SUM(B20:E20) -> 0 | Y20: =SUM(F20:Q20) -> 600000 | Z20: =SUM(R20:W20) -> 300000

Sheet Balance Sheet
A1: Orinth Vale Infrastructure, LLC | Detailed Balance Sheet
A2: Company-prepared monthly reporting package | USD (whole dollars) | Unaudited | Source: borrower Monthly Reporting Package ('a.xlsx'), 'Balance Sheet' tab
A6: Account | B6: Sep 2024 | C6: Oct 2024 | D6: Nov 2024 | E6: Dec 2024 | F6: Jan 2025 | G6: Feb 2025 | H6: Mar 2025 | I6: Apr 2025 | J6: May 2025 | K6: Jun 2025 | L6: Jul 2025 | M6: Aug 2025 | N6: Sep 2025 | O6: Oct 2025 | P6: Nov 2025 | Q6: Dec 2025 | R6: Jan 2026 | S6: Feb 2026 | T6: Mar 2026 | U6: Apr 2026 | V6: May 2026 | W6: Jun 2026 | X6: FY2024 (Sep-Dec, partial) | Y6: FY2025 | Z6: 2026 YTD (Jan-Jun)
A7: Cash | B7: 16887933 | C7: 16819880 | D7: 16613480 | E7: 19110968 | F7: 27429982 | G7: 27086752 | H7: 27330132 | I7: 27338255 | J7: 27716473 | K7: 28420879 | L7: 29076744 | M7: 31213673 | N7: 30803186 | O7: 30952077 | P7: 31633296 | Q7: 35061625 | R7: 35074536 | S7: 35178947 | T7: 35565939 | U7: 36203497 | V7: 36850611 | W7: 36445186 | X7: =E7 -> 19110968 | Y7: =Q7 -> 35061625 | Z7: =W7 -> 36445186
A8: Accounts Receivable | B8: 14498561 | C8: 14985948 | D8: 15909726 | E8: 13703967 | F8: 14729862 | G8: 15591803 | H8: 15838586 | I8: 16658861 | J8: 17120225 | K8: 17147671 | L8: 17192652 | M8: 15788486 | N8: 16852990 | O8: 17525243 | P8: 17771867 | Q8: 15100275 | R8: 15691674 | S8: 16286078 | T8: 16499053 | U8: 16518009 | V8: 16770419 | W8: 18094752 | X8: =E8 -> 13703967 | Y8: =Q8 -> 15100275 | Z8: =W8 -> 18094752
A9: Inventory | B9: 7976796.8 | C9: 8204039.5 | D9: 8399471.5 | E9: 7319493.2 | F9: 7815283.1 | G9: 8132359.3 | H9: 8427186.9 | I9: 8622431.3 | J9: 8915835.4 | K9: 9169354.6 | L9: 9267058.8 | M9: 8409838.3 | N9: 8956820.6 | O9: 9414825.2 | P9: 9566725.2 | Q9: 7896376.1 | R9: 8369070.7 | S9: 8663487.8 | T9: 9034552.1 | U9: 9218970.4 | V9: 9125457.7 | W9: 9792132.7 | X9: =E9 -> 7319493.2 | Y9: =Q9 -> 7896376.1 | Z9: =W9 -> 9792132.7
A10: Net Property and Equipment | B10: =B15+B16 -> 51908507 | C10: =C15+C16 -> 51960520 | D10: =D15+D16 -> 52015285 | E10: =E15+E16 -> 52062352 | F10: =F15+F16 -> 52112386 | G10: =G15+G16 -> 52164827 | H10: =H15+H16 -> 52218470 | I10: =I15+I16 -> 52274435 | ... W10: =W15+W16 -> 53071092 | X10: =E10 -> 52062352 | Y10: =Q10 -> 52729279 | Z10: =W10 -> 53071092
A11: Deferred Financing Fees | B11: 0 | C11: 0 | D11: 0 | E11: 0 | F11: 2950000 | G11: 2900000 | H11: 2850000 | I11: 2800000 | J11: 2750000 | K11: 2700000 | L11: 2650000 | M11: 2600000 | N11: 2550000 | O11: 2500000 | P11: 2450000 | Q11: 2400000 | R11: 2350000 | S11: 2300000 | T11: 2250000 | U11: 2200000 | V11: 2150000 | W11: 2100000 | X11: =E11 -> 0 | Y11: =Q11 -> 2400000 | Z11: =W11 -> 2100000
A12: Other Assets | B12: 14640861 | C12: 14655531 | D12: 14670978 | E12: 14684253 | F12: 14698365 | G12: 14713156 | H12: 14728286 | I12: 14744072 | J12: 14760284 | K12: 14776651 | L12: 14792922 | M12: 14808118 | N12: 14824132 | O12: 14840818 | P12: 14857853 | Q12: 14872361 | R12: 14887436 | S12: 14903031 | T12: 14918953 | U12: 14935024 | V12: 14951396 | W12: 14968770 | X12: =E12 -> 14684253 | Y12: =Q12 -> 14872361 | Z12: =W12 -> 14968770
A13: Total Assets | B13: =B7+B8+B9+B10+B11+B12 -> 1.0591266e+08 | C13: =C7+C8+C9+C10+C11+C12 -> 1.0662592e+08 | D13: =D7+D8+D9+D10+D11+D12 -> 1.0760894e+08 | E13: =E7+E8+E9+E10+E11+E12 -> 1.0688103e+08 | F13: =F7+F8+F9+F10+F11+F12 -> 1.1973588e+08 | G13: =G7+G8+G9+G10+G11+G12 -> 1.205889e+08 | H13: =H7+H8+H9+H10+H11+H12 -> 1.2139266e+08 | I13: =I7+I8+I9+I10+I11+I12 -> 1.2243805e+08 | ... W13: =W7+W8+W9+W10+W11+W12 -> 1.3447193e+08 | X13: =E13 -> 1.0688103e+08 | Y13: =Q13 -> 1.2805991e+08 | Z13: =W13 -> 1.3447193e+08
A15: Gross Property and Equipment | B15: 64253031 | C15: 64438410 | D15: 64633595 | E15: 64801350 | F15: 64979673 | G15: 65166578 | H15: 65357769 | I15: 65557235 | J15: 65762108 | K15: 65968921 | L15: 66174523 | M15: 66366555 | N15: 66568907 | O15: 66779756 | P15: 66995021 | Q15: 67178344 | R15: 67368846 | S15: 67565904 | T15: 67767106 | U15: 67970183 | V15: 68177063 | W15: 68396601 | X15: =E15 -> 64801350 | Y15: =Q15 -> 67178344 | Z15: =W15 -> 68396601
A16: Accumulated Depreciation | B16: -12344523 | C16: -12477890 | D16: -12618311 | E16: -12738997 | F16: -12867288 | G16: -13001751 | H16: -13139299 | I16: -13282800 | J16: -13430190 | K16: -13578977 | L16: -13726892 | M16: -13865044 | N16: -14010621 | O16: -14162311 | P16: -14317178 | Q16: -14449065 | R16: -14586117 | S16: -14727885 | T16: -14872635 | U16: -15018733 | V16: -15167568 | W16: -15325509 | X16: =E16 -> -12738997 | Y16: =Q16 -> -14449065 | Z16: =W16 -> -15325509
A18: Trade Accounts Payable | B18: 4963340.2 | C18: 5104735.7 | D18: 5226337.8 | E18: 4554351.3 | F18: 4862842.8 | G18: 5060134.7 | H18: 5243583 | I18: 5365068.3 | J18: 5547631 | K18: 5705376.2 | L18: 5766169.9 | M18: 5232788.3 | N18: 5573132.8 | O18: 5858113.5 | P18: 5952629 | Q18: 4913300.7 | R18: 5207421.8 | S18: 5390614.6 | T18: 5621499.1 | U18: 5736248.2 | V18: 5678062.5 | W18: 6092882.6 | X18: =E18 -> 4554351.3 | Y18: =Q18 -> 4913300.7 | Z18: =W18 -> 6092882.6
A19: Accrued Expenses | B19: 1559906.9 | C19: 1604345.5 | D19: 1642563.3 | E19: 1431367.6 | F19: 1528322 | G19: 1590328 | H19: 1647983.2 | I19: 1686164.3 | J19: 1743541.1 | K19: 1793118.2 | L19: 1812224.8 | M19: 1644590.6 | N19: 1751556 | O19: 1841121.4 | P19: 1870826.2 | Q19: 1544180.2 | R19: 1636618.3 | S19: 1694193.2 | T19: 1766756.9 | U19: 1802820.9 | V19: 1784533.9 | W19: 1914906 | X19: =E19 -> 1431367.6 | Y19: =Q19 -> 1544180.2 | Z19: =W19 -> 1914906
A20: Other Current Liabilities | B20: 567238.88 | C20: 583398.37 | D20: 597295.75 | E20: 520497.29 | F20: 555753.47 | G20: 578301.11 | H20: 599266.62 | I20: 613150.67 | J20: 634014.96 | K20: 652043 | L20: 658990.85 | M20: 598032.95 | N20: 636929.46 | O20: 669498.68 | P20: 680300.46 | Q20: 561520.08 | R20: 595133.91 | S20: 616070.24 | T20: 642457.04 | U20: 655571.23 | V20: 648921.43 | W20: 696329.44 | X20: =E20 -> 520497.29 | Y20: =Q20 -> 561520.08 | Z20: =W20 -> 696329.44
A21: Accounts Payable and Accruals | B21: =B18+B19+B20 -> 7090486 | C21: =C18+C19+C20 -> 7292479.6 | D21: =D18+D19+D20 -> 7466196.9 | E21: =E18+E19+E20 -> 6506216.2 | F21: =F18+F19+F20 -> 6946918.3 | G21: =G18+G19+G20 -> 7228763.8 | H21: =H18+H19+H20 -> 7490832.8 | I21: =I18+I19+I20 -> 7664383.4 | ... W21: =W18+W19+W20 -> 8704118 | X21: =E21 -> 6506216.2 | Y21: =Q21 -> 7019001 | Z21: =W21 -> 8704118
A22: Funded Debt | B22: 66551477 | C22: 66152168 | D22: 65755255 | E22: 65360723 | F22: 64968559 | G22: 64578748 | H22: 64191275 | I22: 63806128 | J22: 63423291 | K22: 63042751 | L22: 62664495 | M22: 62288508 | N22: 61914777 | O22: 61543288 | P22: 61174028 | Q22: 60806984 | R22: 60442142 | S22: 60079489 | T22: 59719012 | U22: 59360698 | V22: 59004534 | W22: 58650507 | X22: =E22 -> 65360723 | Y22: =Q22 -> 60806984 | Z22: =W22 -> 58650507
A23: Total Liabilities | B23: =B21+B22 -> 73641963 | C23: =C21+C22 -> 73444648 | D23: =D21+D22 -> 73221452 | E23: =E21+E22 -> 71866940 | F23: =F21+F22 -> 71915477 | G23: =G21+G22 -> 71807512 | H23: =H21+H22 -> 71682108 | I23: =I21+I22 -> 71470511 | ... W23: =W21+W22 -> 67354625 | X23: =E23 -> 71866940 | Y23: =Q23 -> 67825985 | Z23: =W23 -> 67354625
A24: Equity | B24: 32270697 | C24: 33181271 | D24: 34387488 | E24: 35014094 | F24: 47820400 | G24: 48781386 | H24: 49710553 | I24: 50967543 | J24: 52246258 | K24: 53411212 | L24: 54525128 | M24: 55557707 | N24: 56669019 | O24: 57938387 | P24: 59279801 | Q24: 60233930 | R24: 61274130 | S24: 62389195 | T24: 63413243 | U24: 64471612 | V24: 65741326 | W24: 67117307 | X24: =E24 -> 35014094 | Y24: =Q24 -> 60233930 | Z24: =W24 -> 67117307
A25: Liabilities + Equity | B25: =B23+B24 -> 1.0591266e+08 | C25: =C23+C24 -> 1.0662592e+08 | D25: =D23+D24 -> 1.0760894e+08 | E25: =E23+E24 -> 1.0688103e+08 | F25: =F23+F24 -> 1.1973588e+08 | G25: =G23+G24 -> 1.205889e+08 | H25: =H23+H24 -> 1.2139266e+08 | I25: =I23+I24 -> 1.2243805e+08 | ... W25: =W23+W24 -> 1.3447193e+08 | X25: =E25 -> 1.0688103e+08 | Y25: =Q25 -> 1.2805991e+08 | Z25: =W25 -> 1.3447193e+08
A27: Balance Check (Total Assets - Liabilities + Equity) | B27: =B13-B25 -> 0 | C27: =C13-C25 -> 0 | D27: =D13-D25 -> 0 | E27: =E13-E25 -> 0 | F27: =F13-F25 -> 0 | G27: =G13-G25 -> 0 | H27: =H13-H25 -> 0 | I27: =I13-I25 -> 0 | ... W27: =W13-W25 -> 0 | X27: =E27 -> 0 | Y27: =Q27 -> 0 | Z27: =W27 -> 0
A29: DEBT & COVENANT (borrower-certified roll-forward; source: Debt & Covenant tab)
A30: Beginning Debt | B30: 66953196 | C30: =B34 -> 66551477 | D30: =C34 -> 66152168 | E30: =D34 -> 65755255 | F30: =E34 -> 65360723 | G30: =F34 -> 64968559 | H30: =G34 -> 64578748 | I30: =H34 -> 64191275 | J30: =I34 -> 63806128 | ... W30: =V34 -> 59004534 | X30: =B30 -> 66953196 | Y30: =F30 -> 65360723 | Z30: =R30 -> 60806984
A31: Draws | B31: 0 | C31: 0 | D31: 0 | E31: 0 | F31: 0 | G31: 0 | H31: 0 | I31: 0 | J31: 0 | K31: 0 | L31: 0 | M31: 0 | N31: 0 | O31: 0 | P31: 0 | Q31: 0 | R31: 0 | S31: 0 | T31: 0 | U31: 0 | V31: 0 | W31: 0 | X31: =SUM(B31:E31) -> 0 | Y31: =SUM(F31:Q31) -> 0 | Z31: =SUM(R31:W31) -> 0
A32: PIK | B32: 0 | C32: 0 | D32: 0 | E32: 0 | F32: 0 | G32: 0 | H32: 0 | I32: 0 | J32: 0 | K32: 0 | L32: 0 | M32: 0 | N32: 0 | O32: 0 | P32: 0 | Q32: 0 | R32: 0 | S32: 0 | T32: 0 | U32: 0 | V32: 0 | W32: 0 | X32: =SUM(B32:E32) -> 0 | Y32: =SUM(F32:Q32) -> 0 | Z32: =SUM(R32:W32) -> 0
A33: Repayments | B33: 401719.18 | C33: 399308.86 | D33: 396913.01 | E33: 394531.53 | F33: 392164.34 | G33: 389811.35 | H33: 387472.49 | I33: 385147.65 | J33: 382836.77 | K33: 380539.74 | L33: 378256.51 | M33: 375986.97 | N33: 373731.05 | O33: 371488.66 | P33: 369259.73 | Q33: 367044.17 | R33: 364841.9 | S33: 362652.85 | T33: 360476.94 | U33: 358314.07 | V33: 356164.19 | W33: 354027.2 | X33: =SUM(B33:E33) -> 1592472.6 | Y33: =SUM(F33:Q33) -> 4553739.4 | Z33: =SUM(R33:W33) -> 2156477.1
A34: Ending Debt | B34: =B30+B31+B32-B33 -> 66551477 | C34: =C30+C31+C32-C33 -> 66152168 | D34: =D30+D31+D32-D33 -> 65755255 | E34: =E30+E31+E32-E33 -> 65360723 | F34: =F30+F31+F32-F33 -> 64968559 | G34: =G30+G31+G32-G33 -> 64578748 | H34: =H30+H31+H32-H33 -> 64191275 | I34: =I30+I31+I32-I33 -> 63806128 | ... W34: =W30+W31+W32-W33 -> 58650507 | X34: =E34 -> 65360723 | Y34: =Q34 -> 60806984 | Z34: =W34 -> 58650507
A35: Cash Interest | B35: 607001.09 | C35: 603359.08 | D35: 599738.93 | E35: 596140.5 | F35: 592563.65 | G35: 589008.27 | H35: 585474.22 | I35: 581961.38 | J35: 578469.61 | K35: 574998.79 | L35: 571548.8 | M35: 568119.51 | N35: 564710.79 | O35: 561322.52 | P35: 557954.59 | Q35: 554606.86 | R35: 551279.22 | S35: 547971.54 | T35: 544683.72 | U35: 541415.61 | V35: 538167.12 | W35: 534938.12 | X35: =SUM(B35:E35) -> 2406239.6 | Y35: =SUM(F35:Q35) -> 6880739 | Z35: =SUM(R35:W35) -> 3258455.3
A36: Deferred Fee Amortization | B36: 0 | C36: 0 | D36: 0 | E36: 0 | F36: 50000 | G36: 50000 | H36: 50000 | I36: 50000 | J36: 50000 | K36: 50000 | L36: 50000 | M36: 50000 | N36: 50000 | O36: 50000 | P36: 50000 | Q36: 50000 | R36: 50000 | S36: 50000 | T36: 50000 | U36: 50000 | V36: 50000 | W36: 50000 | X36: =SUM(B36:E36) -> 0 | Y36: =SUM(F36:Q36) -> 600000 | Z36: =SUM(R36:W36) -> 300000
A37: TTM Covenant EBITDA | B37: 16923197 | C37: 16801862 | D37: 17107835 | E37: 17534490 | F37: 18064705 | G37: 18667224 | H37: 19274234 | I37: 20141911 | J37: 21021202 | K37: 21760157 | L37: 22292254 | M37: 22768979 | N37: 23265421 | O37: 23681723 | P37: 23852382 | Q37: 24227721 | R37: 24445420 | S37: 24575526 | T37: 24641788 | U37: 24386037 | V37: 24334298 | W37: 24529022 | X37: =E37 -> 17534490 | Y37: =Q37 -> 24227721 | Z37: =W37 -> 24529022
A38: Total Leverage Ratio | B38: =IFERROR(B34/B37,"") -> 3.9325594 | C38: =IFERROR(C34/C37,"") -> 3.9371926 | D38: =IFERROR(D34/D37,"") -> 3.8435754 | E38: =IFERROR(E34/E37,"") -> 3.727552 | F38: =IFERROR(F34/F37,"") -> 3.5964362 | G38: =IFERROR(G34/G37,"") -> 3.4594726 | H38: =IFERROR(H34/H37,"") -> 3.3304191 | I38: =IFERROR(I34/I37,"") -> 3.1678289 | ... W38: =IFERROR(W34/W37,"") -> 2.3910658 | X38: =E38 -> 3.727552 | Y38: =Q38 -> 2.5098103 | Z38: =W38 -> 2.3910658
A39: Maximum Covenant | B39: 5.5 | C39: 5.5 | D39: 5.5 | E39: 5.5 | F39: 5.5 | G39: 5.5 | H39: 5.5 | I39: 5.5 | J39: 5.5 | K39: 5.5 | L39: 5.5 | M39: 5.5 | N39: 5.5 | O39: 5.5 | P39: 5.5 | Q39: 5.5 | R39: 5.5 | S39: 5.5 | T39: 5.5 | U39: 5.5 | V39: 5.5 | W39: 5.5 | X39: =E39 -> 5.5 | Y39: =Q39 -> 5.5 | Z39: =W39 -> 5.5
A40: Monthly Principal Rate | B40: 0.006 | C40: 0.006 | D40: 0.006 | E40: 0.006 | F40: 0.006 | G40: 0.006 | H40: 0.006 | I40: 0.006 | J40: 0.006 | K40: 0.006 | L40: 0.006 | M40: 0.006 | N40: 0.006 | O40: 0.006 | P40: 0.006 | Q40: 0.006 | R40: 0.006 | S40: 0.006 | T40: 0.006 | U40: 0.006 | V40: 0.006 | W40: 0.006 | X40: =E40 -> 0.006 | Y40: =Q40 -> 0.006 | Z40: =W40 -> 0.006
A42: COVENANT-SUPPORT ROWS (facility Fixed-Charges inputs; source noted per row below)
A43: Cash Interest Expense | B43: 0 | C43: 0 | D43: 0 | E43: 0 | F43: =F35 -> 592563.65 | G43: =G35 -> 589008.27 | H43: =H35 -> 585474.22 | I43: =I35 -> 581961.38 | J43: =J35 -> 578469.61 | K43: =K35 -> 574998.79 | L43: =L35 -> 571548.8 | M43: =M35 -> 568119.51 | ... W43: =W35 -> 534938.12 | X43: =SUM(B43:E43) -> 0 | Y43: =SUM(F43:Q43) -> 6880739 | Z43: =SUM(R43:W43) -> 3258455.3
A44: Scheduled Debt Principal Payments | B44: 0 | C44: 0 | D44: 0 | E44: 0 | F44: =F33 -> 392164.34 | G44: =G33 -> 389811.35 | H44: =H33 -> 387472.49 | I44: =I33 -> 385147.65 | J44: =J33 -> 382836.77 | K44: =K33 -> 380539.74 | L44: =L33 -> 378256.51 | M44: =M33 -> 375986.97 | ... W44: =W33 -> 354027.2 | X44: =SUM(B44:E44) -> 0 | Y44: =SUM(F44:Q44) -> 4553739.4 | Z44: =SUM(R44:W44) -> 2156477.1

Sheet Cash Flow Statement
A1: Orinth Vale Infrastructure, LLC | Detailed Cash Flow Statement (as reported)
A2: Company-prepared monthly reporting package | USD (whole dollars) | Unaudited | Source: borrower Monthly Reporting Package ('a.xlsx'), 'Cash Flow' tab
A6: Account | B6: Sep 2024 | C6: Oct 2024 | D6: Nov 2024 | E6: Dec 2024 | F6: Jan 2025 | G6: Feb 2025 | H6: Mar 2025 | I6: Apr 2025 | J6: May 2025 | K6: Jun 2025 | L6: Jul 2025 | M6: Aug 2025 | N6: Sep 2025 | O6: Oct 2025 | P6: Nov 2025 | Q6: Dec 2025 | R6: Jan 2026 | S6: Feb 2026 | T6: Mar 2026 | U6: Apr 2026 | V6: May 2026 | W6: Jun 2026 | X6: FY2024 (Sep-Dec, partial) | Y6: FY2025 | Z6: 2026 YTD (Jan-Jun)
A7: Beginning Cash | B7: 16939298 | C7: =B9 -> 16887933 | D7: =C9 -> 16819880 | E7: =D9 -> 16613480 | F7: =E9 -> 19110968 | G7: =F9 -> 27429982 | H7: =G9 -> 27086752 | I7: =H9 -> 27330132 | J7: =I9 -> 27338255 | ... W7: =V9 -> 36850611 | X7: =B7 -> 16939298 | Y7: =F7 -> 19110968 | Z7: =R7 -> 35061625
A8: Cash Flow Change | B8: =B12+B18+B20 -> -51364.59 | C8: =C12+C18+C20 -> -68053.28 | D8: =D12+D18+D20 -> -206399.88 | E8: =E12+E18+E20 -> 2497488.4 | F8: =F12+F18+F20 -> 8319013.8 | G8: =G12+G18+G20 -> -343229.92 | H8: =H12+H18+H20 -> 243379.42 | I8: =I12+I18+I20 -> 8123.2 | ... W8: =W12+W18+W20 -> -405425.28 | X8: =SUM(B8:E8) -> 2171670.7 | Y8: =SUM(F8:Q8) -> 15950656 | Z8: =SUM(R8:W8) -> 1383560.9
A9: Ending Cash | B9: =B7+B8 -> 16887933 | C9: =C7+C8 -> 16819880 | D9: =D7+D8 -> 16613480 | E9: =E7+E8 -> 19110968 | F9: =F7+F8 -> 27429982 | G9: =G7+G8 -> 27086752 | H9: =H7+H8 -> 27330132 | I9: =I7+I8 -> 27338255 | ... W9: =W7+W8 -> 36445186 | X9: =E9 -> 19110968 | Y9: =Q9 -> 35061625 | Z9: =W9 -> 36445186
A11: EBITDA | B11: 1526910 | C11: 1780865.4 | D11: 2104190.6 | E11: 1452361.1 | F11: 1705037.7 | G11: 1875088.8 | H11: 1840204.3 | I11: 2197245.4 | J11: 2221162.9 | K11: 2095934.4 | L11: 2036086 | M11: 1933892.7 | N11: 2023351.9 | O11: 2197167.1 | P11: 2274849.7 | Q11: 1827699.8 | R11: 1922737 | S11: 2005194.5 | T11: 1906466.7 | U11: 1941494.2 | V11: 2169423.5 | W11: 2290659.2 | X11: =SUM(B11:E11) -> 6864327.1 | Y11: =SUM(F11:Q11) -> 24227721 | Z11: =SUM(R11:W11) -> 12235975
A12: Net Cash from Operating Activities | B12: =B11-B13-B14-B15 -> 543135.61 | C12: =C11-C13-C14-C15 -> 531305.31 | D12: =D11-D13-D14-D15 -> 401144.98 | E12: =E11-E13-E14-E15 -> 3073049.9 | F12: =F11-F13-F14-F15 -> -96386.44 | G12: =G11-G13-G14-G15 -> 248276.85 | H12: =H11-H13-H14-H15 -> 837173.05 | I12: =I11-I13-I14-I15 -> 608522.21 | ... W12: =W11-W13-W14-W15 -> 185513.13 | X12: =SUM(B12:E12) -> 4548635.8 | Y12: =SUM(F12:Q12) -> 14069497 | Z12: =SUM(R12:W12) -> 4854704.6
A13: Working Capital Investment | B13: 262255.07 | C13: 512636.06 | D13: 945492.39 | E13: -2325756.4 | F13: 1080982.6 | G13: 897172.04 | H13: 279541.74 | I13: 841968.42 | J13: 493964.95 | K13: 55615.1 | L13: 55836.54 | M13: -1499412.6 | N13: 1125279.4 | O13: 723143.03 | P13: 263501.27 | Q13: -2857186.6 | R13: 643921.39 | S13: 627116.59 | T13: 254203.99 | U13: 39447.69 | V13: 242018.93 | W13: 1398408.5 | X13: =SUM(B13:E13) -> -605372.85 | Y13: =SUM(F13:Q13) -> 1460406 | Z13: =SUM(R13:W13) -> 3205117.1
A14: Cash Taxes | B14: 114518.25 | C14: 133564.9 | D14: 157814.3 | E14: 108927.08 | F14: 127877.83 | G14: 140631.66 | H14: 138015.32 | I14: 164793.41 | J14: 166587.22 | K14: 157195.08 | L14: 152706.45 | M14: 145041.95 | N14: 151751.39 | O14: 164787.54 | P14: 170613.73 | Q14: 137077.48 | R14: 144205.27 | S14: 150389.59 | T14: 142985 | U14: 145612.07 | V14: 162706.76 | W14: 171799.44 | X14: =SUM(B14:E14) -> 514824.53 | Y14: =SUM(F14:Q14) -> 1817079.1 | Z14: =SUM(R14:W14) -> 917698.13
A15: Cash Interest | B15: 607001.09 | C15: 603359.08 | D15: 599738.93 | E15: 596140.5 | F15: 592563.65 | G15: 589008.27 | H15: 585474.22 | I15: 581961.38 | J15: 578469.61 | K15: 574998.79 | L15: 571548.8 | M15: 568119.51 | N15: 564710.79 | O15: 561322.52 | P15: 557954.59 | Q15: 554606.86 | R15: 551279.22 | S15: 547971.54 | T15: 544683.72 | U15: 541415.61 | V15: 538167.12 | W15: 534938.12 | X15: =SUM(B15:E15) -> 2406239.6 | Y15: =SUM(F15:Q15) -> 6880739 | Z15: =SUM(R15:W15) -> 3258455.3
A17: Capital Expenditures | B17: -192781.02 | C17: -200049.73 | D17: -210631.85 | E17: -181029.94 | F17: -192435.41 | G17: -201695.42 | H17: -206321.14 | I17: -215251.36 | J17: -221085.75 | K17: -223180.11 | L17: -221872.48 | M17: -207228.2 | N17: -218365.83 | O17: -227534.9 | P17: -232300.74 | Q17: -197829.79 | R17: -205577.76 | S17: -212653.11 | T17: -217124.54 | U17: -219147.09 | V17: -223252.79 | W17: -236911.21 | X17: =SUM(B17:E17) -> -784492.54 | Y17: =SUM(F17:Q17) -> -2565101.1 | Z17: =SUM(R17:W17) -> -1314666.5
A18: Net Cash from Investing Activities | B18: =B17 -> -192781.02 | C18: =C17 -> -200049.73 | D18: =D17 -> -210631.85 | E18: =E17 -> -181029.94 | F18: =F17 -> -192435.41 | G18: =G17 -> -201695.42 | H18: =H17 -> -206321.14 | I18: =I17 -> -215251.36 | ... W18: =W17 -> -236911.21 | X18: =SUM(B18:E18) -> -784492.54 | Y18: =SUM(F18:Q18) -> -2565101.1 | Z18: =SUM(R18:W18) -> -1314666.5
A20: Net Cash from Financing Activities | B20: -401719.18 | C20: -399308.86 | D20: -396913.01 | E20: -394531.53 | F20: 8607835.7 | G20: -389811.35 | H20: -387472.49 | I20: -385147.65 | J20: -382836.77 | K20: -380539.74 | L20: -378256.51 | M20: -375986.97 | N20: -373731.05 | O20: -371488.66 | P20: -369259.73 | Q20: -367044.17 | R20: -364841.9 | S20: -362652.85 | T20: -360476.94 | U20: -358314.07 | V20: -356164.19 | W20: -354027.2 | X20: =SUM(B20:E20) -> -1592472.6 | Y20: =SUM(F20:Q20) -> 4446260.6 | Z20: =SUM(R20:W20) -> -2156477.1
A22: Memo: Cash per Balance Sheet | B22: ='Balance Sheet'!B7 -> 16887933 | C22: ='Balance Sheet'!C7 -> 16819880 | D22: ='Balance Sheet'!D7 -> 16613480 | E22: ='Balance Sheet'!E7 -> 19110968 | F22: ='Balance Sheet'!F7 -> 27429982 | G22: ='Balance Sheet'!G7 -> 27086752 | H22: ='Balance Sheet'!H7 -> 27330132 | I22: ='Balance Sheet'!I7 -> 27338255 | ... W22: ='Balance Sheet'!W7 -> 36445186 | X22: =E22 -> 19110968 | Y22: =Q22 -> 35061625 | Z22: =W22 -> 36445186
A23: Memo: CF-vs-BS cash tie (diff, should be 0) | B23: =B9-B22 -> 0 | C23: =C9-C22 -> 0 | D23: =D9-D22 -> 0 | E23: =E9-E22 -> 0 | F23: =F9-F22 -> 0 | G23: =G9-G22 -> 0 | H23: =H9-H22 -> 0 | I23: =I9-I22 -> 0 | ... W23: =W9-W22 -> 0 | X23: =E23 -> 0 | Y23: =Q23 -> 0 | Z23: =W23 -> 0
A24: Memo: CF EBITDA vs IS EBITDA tie (diff, should be 0) | B24: =B11-'Income Statement'!B10 -> 0 | C24: =C11-'Income Statement'!C10 -> 0 | D24: =D11-'Income Statement'!D10 -> 0 | E24: =E11-'Income Statement'!E10 -> 0 | F24: =F11-'Income Statement'!F10 -> 0 | G24: =G11-'Income Statement'!G10 -> 0 | H24: =H11-'Income Statement'!H10 -> 0 | I24: =I11-'Income Statement'!I10 -> 0 | ... W24: =W11-'Income Statement'!W10 -> 0 | X24: =SUM(B24:E24) -> 0 | Y24: =SUM(F24:Q24) -> 0 | Z24: =SUM(R24:W24) -> 0

Sheet Sources & Notes
A1: Entity | B1: Orinth Vale Infrastructure, LLC (consolidated) -- borrower-config model.entity='consolidated'. No separate divisional/subsidiary consolidation levels are shown anywhere in the reporting package.
A2: Units | B2: USD, whole dollars (model.scale = 1). Borrower's own package states 'USD | internally titled source'; cross-checked against the executed Credit Agreement's pro forma leverage math and the FY2024 annual statements (borrower-config.json model._scale_verification) -- all consistent at whole-dollar scale.
A3: Basis | B3: Actuals only -- company-prepared monthly reporting package ('a.xlsx'), unaudited. No proforma/budget/forecast figures included. Each month's a.xlsx carries a single data column for that month (not a rolling multi-month window), so all 22 months were assembled from 22 separate monthly files.
A4: Coverage | B4: Sep 2024 through Jun 2026 (22 months), matching every monthly subfolder present in 04 Reporting/Period Archive, continuous, no gaps. The credit facility (Orinth Vale 2025 Senior Secured Facility) closed 2025-01-15, so Sep-Dec 2024 (4 months) predate it and carry a predecessor/legacy debt balance instead.
A5: Source files | B5: Every Income Statement / Balance Sheet / Cash Flow figure for month M is sourced from 04 Reporting/Period Archive/<YYYY>/<MM>/a.xlsx, which bundles Income Statement, Balance Sheet, Cash Flow and Debt & Covenant as four tabs in ONE workbook per month (confirmed non-generic despite the filename 'a.xlsx' -- re-verified independently across all 22 months, not just the 6 the prior monitor-setup/covenant-setup passes sampled: identical sheet set and identical row-label sequence in every month, zero letter-drift or schema drift found). 'b.xlsx' (AR/AP aging, bucketed) and 'c.xlsx' (Channel Detail, revenue by service line) are separate supplemental files consumed by other modules (ap-ar-aging) and are NOT part of this IS/BS/CF model, per borrower-config.json's own a/b/c mapping note.
A6: Restatement scan | B6: Full restatement scan performed: this is a from-scratch build (no prior canonical model existed). Each of the 22 monthly a.xlsx files is the ONLY package covering its own month within 04 Reporting/Period Archive -- no overlapping/consolidated by-month or YTD file exists there. The only other candidate source, 04 Reporting/2026/Q2/June Close/ (qtd-view.xls + monthly-detail.xlsx), was independently re-checked and its June 2026 Revenue/Costs/EBITDA/Debt figures tie EXACTLY to Period Archive/2026/06/a.xlsx -- confirming it is a convenience re-export of the same underlying data, not an independent or restated source; it was excluded (per borrower-config.json's own note) and contributes no restatement. Zero restatements found; restatements.json is an empty array.
A7: Independent tie-out sweep (this build) | B7: Beyond label/structure verification, every one of the following identities was checked and confirmed EXACT (no material variance) across all 22 months, not just June 2026: Revenue-Costs=Gross Profit; Revenue-Costs-OpEx=EBITDA; EBITDA-D&A=Operating Income; Cash Interest+Deferred Financing Fee Amortization=Interest Expense; Operating Income-Interest Expense=Income Before Taxes; Income Before Taxes-Income Tax Expense=Net Income; Net Income+Interest Expense+Income Tax Expense+D&A=EBITDA (the full bridge); Total Assets=sum of asset lines; Gross PP&E+Accumulated Depreciation=Net PP&E; Trade AP+Accrued Expenses+Other Current Liabilities=Accounts Payable and Accruals; Total Liabilities+Equity=Total Assets (balance check=0 every month); Cash Flow ties to both Balance Sheet cash (Ending Cash=BS Cash) and Income Statement EBITDA (CF EBITDA=IS EBITDA) every month; Beginning Debt(t)=Ending Debt(t-1) and Beginning Cash(t)=Ending Cash(t-1) hold continuously across the full 22-month run (i.e. no gap or restatement break at any month boundary); Repayments = 0.60% of that month's own Beginning Debt (the agreement's stated monthly amortization rate) every month. The single exception found: Jan 2025's 'Net Cash from Financing Activities' ($8,607,835.66) does NOT equal -Repayments -- expected, because Jan 2025 is the facility-closing/refinancing month (new $65,360,723.38 term loan proceeds settling the legacy debt payoff), a genuine one-time capital-structure event, not a data error; that row is carried as its own independently-reported figure (not derived by formula) for this reason.
A8: Cash Flow | B8: As-reported from the borrower's own 'Cash Flow' tab (not derived) -- the borrower delivers a full Operating/Investing/Financing cash flow every month. 'Net Cash from Operating Activities' is written as a live formula (EBITDA - Working Capital Investment - Cash Taxes - Cash Interest) which ties the reported figure exactly every month; 'Net Cash from Investing Activities' = Capital Expenditures (the only investing line); 'Net Cash from Financing Activities' is carried as its own reported figure (see the Jan 2025 exception above). Memo rows cross-check CF-vs-BS cash and CF-vs-IS EBITDA; both tie to 0 in every month.
A9: EBITDA bridge | B9: Per covenant-spec.json#/definitions/Covenant_EBITDA, compute.ebitda_bridge = 'EBITDA' -- the model's own single native monthly Income Statement row, bound via borrower-config.json model_lines.ebitda_bridge. Covenant-spec.json's own independent verification (5 non-adjacent months, 2025-01 through 2026-06) found the certified quarterly Covenant Calculation.xlsx TTM Detail's per-month 'Covenant EBITDA' figures tie EXACTLY to this model's monthly EBITDA row -- confirmed again here for June 2026 (2,290,659.16) as part of this build. No add-back gap; no deemed-EBITDA schedule (a full-text sweep of all 9 executed closing documents found zero 'deemed'/'stipulated'/'agreed EBITDA' hits -- this is a refinancing, not an LBO/acquisition financing with a pre-close target-EBITDA table). This is a NOT PROVISIONAL bridge (a validated covenant-spec.json exists and EBITDA ties exactly).
A10: Pre-archive TTM history gap | B10: covenant-spec.json flags that the certified TTM Detail for the 2025-03-31 and 2025-06-30 covenant tests needs monthly Covenant EBITDA back to 2024-04 and 2024-07 respectively, both of which predate this model's earliest month (2024-09) by 5 and 2 months. Those pre-archive months are genuine organic historical actuals the certifier sourced outside 04 Reporting/Period Archive, not a contractual override -- this model was built from 2024-09 forward as instructed; downstream TTM-based reads may show 'insufficient history' for test dates before 2025-09-30, which is expected and not a build defect. 'TTM Covenant EBITDA' on the Debt & Covenant roll-forward below is carried as the borrower's own certified figure for every month (not recomputed as a trailing-12 SUM of this model's own EBITDA row), because a from-model SUM would be wrong (understated) for any month before 2025-09 that lacks a full 12 months of in-model history; for months from 2025-09 onward, the certified figure was independently verified to equal the exact trailing-12-month SUM of this model's own EBITDA row (spot-checked June 2026: sum of Jul 2025-Jun 2026 EBITDA = $24,529,022.34 = the certified TTM figure, exact).
A11: Debt & Covenant roll-forward (Balance Sheet, below the balance-check row) | B11: Reproduces the borrower's own monthly 'Debt & Covenant' tab (Beginning Debt, Draws, PIK, Repayments, Ending Debt, Cash Interest, Deferred Fee Amortization, TTM Covenant EBITDA, Total Leverage Ratio, Maximum Covenant, Monthly Principal Rate) -- a self-consistent monthly roll-forward, present in EVERY month's a.xlsx (not just quarter-ends). Ending Debt ties exactly to the Balance Sheet's own 'Funded Debt' line every month, and Total Leverage Ratio / TTM Covenant EBITDA tie exactly to the certified quarterly Covenant Calculation.xlsx (06 Monitoring/Portfolio Management/<YYYY Qn>/) at all 6 quarters checked (2025 Q1 through 2026 Q2).
A12: Predecessor debt / refinancing | B12: The Balance Sheet's 'Funded Debt' / Debt & Covenant roll-forward shows a CONTINUOUS balance and 0.60%-of-beginning-balance monthly amortization from Sep 2024 (predecessor/legacy debt, $66,953,195.96 beginning balance) through the executed Credit Agreement's Jan 15, 2025 closing, at which point the new $65,360,723.38 facility funded at EXACTLY the legacy debt's Dec 2024 ending balance ($65,360,723.38) -- a dollar-for-dollar refinancing, consistent with the Credit Agreement's own statement that the term loan 'is fully funded at closing to refinance legacy debt.'
... A16: Build tool / recalc | B16: Built with openpyxl; formula cells recalculated (cached values populated) via headless LibreOffice as the LAST write, per assembling-rules.md. Gated with references/validate_model.py before becoming canonical.
