Workbook

Sheet Income Statement
A1: Veyrona Decision Systems, LLC | Detailed Income Statement
A2: Company-prepared monthly reporting package | USD, whole dollars (scale=1) | Unaudited | Source: Finance Reporting/<YYYY>/<MM>/<Month>_<Year>_Monthly_Package.xlsx, 'Income Statement' tab (Mar/Apr/May 2026: Quarterly_Package_2026-06-25_REVISED_MARCH-MAY.xlsx; Jun 2026: June_2026_Monthly_Package_2026-07-25.xlsx). Mar 2026 Revenue and Cost of Revenue are RESTATED -- see Sources & Notes and restatements.json.
A6: Account | B6: Sep 2024 | C6: Oct 2024 | D6: Nov 2024 | E6: Dec 2024 | F6: Jan 2025 | G6: Feb 2025 | H6: Mar 2025 | I6: Apr 2025 | J6: May 2025 | K6: Jun 2025 | L6: Jul 2025 | M6: Aug 2025 | N6: Sep 2025 | O6: Oct 2025 | P6: Nov 2025 | Q6: Dec 2025 | R6: Jan 2026 | S6: Feb 2026 | T6: Mar 2026 | U6: Apr 2026 | V6: May 2026 | W6: Jun 2026 | X6: FY2024 (Sep-Dec, partial) | Y6: FY2025 | Z6: 2026 YTD (Jan-Jun)
A7: Revenue | B7: 19209857 | C7: 16819871 | D7: 18853635 | E7: 20298744 | F7: 16165987 | G7: 16986903 | H7: 18295101 | I7: 15167051 | J7: 17000965 | K7: 18304070 | L7: 14561122 | M7: 15303090 | N7: 16484289 | O7: 16175355 | P7: 16993842 | Q7: 18299528 | R7: 16954731 | S7: 17818667 | T7: 14062564 | U7: 17608614 | V7: 18499626 | W7: 19921005 | X7: =SUM(B7:E7) -> 75182106 | Y7: =SUM(F7:Q7) -> 1.9973731e+08 | Z7: =SUM(R7:W7) -> 1.0486521e+08
A8: Cost of Revenue | B8: 10373323 | C8: 9082730.4 | D8: 10180963 | E8: 10961322 | F8: 8729633.2 | G8: 9172927.8 | H8: 9879354.8 | I8: 8190207.8 | J8: 9180521.3 | K8: 9884197.6 | L8: 7863005.9 | M8: 8263668.6 | N8: 8901516.2 | O8: 8734691.8 | P8: 9176674.9 | Q8: 9881744.9 | R8: 9155554.9 | S8: 9622079.9 | T8: 7780816.5 | U8: 9508651.8 | V8: 9989798 | W8: 10757343 | X8: =SUM(B8:E8) -> 40598337 | Y8: =SUM(F8:Q8) -> 1.0785814e+08 | Z8: =SUM(R8:W8) -> 56814244
A9: Gross Profit (derived) | B9: =B7-B8 -> 8836534 | C9: =C7-C8 -> 7737140.7 | D9: =D7-D8 -> 8672672 | E9: =E7-E8 -> 9337422.2 | F9: =F7-F8 -> 7436354.2 | G9: =G7-G8 -> 7813975.5 | H9: =H7-H8 -> 8415746.7 | I9: =I7-I8 -> 6976843.7 | ... W9: =W7-W8 -> 9163662.2 | X9: =SUM(B9:E9) -> 34583769 | Y9: =SUM(F9:Q9) -> 91879160 | Z9: =SUM(R9:W9) -> 48050963
A10: Operating Expenses | B10: 5820586.5 | C10: 5062781.2 | D10: 5825773.1 | E10: 6231714.4 | F10: 4962958.2 | G10: 5181005.5 | H10: 5543415.7 | I10: 4565282.5 | J10: 5253298.3 | K10: 5619349.4 | L10: 4441142.2 | M10: 4636836.3 | N10: 4961771 | O10: 4998184.8 | P10: 5217109.6 | Q10: 5581355.9 | R10: 5171193 | S10: 5399056 | T10: 3229895.6 | U10: 5441061.9 | V10: 5679385.2 | W10: 6075906.5 | X10: =SUM(B10:E10) -> 22940855 | Y10: =SUM(F10:Q10) -> 60961709 | Z10: =SUM(R10:W10) -> 30996498
A11: Reported EBITDA | B11: =B9-B10 -> 3015947.5 | C11: =C9-C10 -> 2674359.5 | D11: =D9-D10 -> 2846898.8 | E11: =E9-E10 -> 3105707.8 | F11: =F9-F10 -> 2473396.1 | G11: =G9-G10 -> 2632970 | H11: =H9-H10 -> 2872330.9 | I11: =I9-I10 -> 2411561.2 | ... W11: =W9-W10 -> 3087755.8 | X11: =SUM(B11:E11) -> 11642914 | Y11: =SUM(F11:Q11) -> 30917451 | Z11: =SUM(R11:W11) -> 17054465

Sheet Balance Sheet
A1: Veyrona Decision Systems, LLC | Detailed Balance Sheet
A2: Company-prepared monthly reporting package | USD, whole dollars (scale=1) | Unaudited | Source: Finance Reporting/<YYYY>/<MM>/<Month>_<Year>_Monthly_Package.xlsx, 'Balance Sheet' tab (Mar/Apr/May 2026: Quarterly_Package_2026-06-25_REVISED_MARCH-MAY.xlsx; Jun 2026: June_2026_Monthly_Package_2026-07-25.xlsx). No native Total Assets/Total Liabilities/Total Equity or Balance-Check row exists anywhere in this borrower's reporting -- disclosed gap, see Sources & Notes. Contract Asset/Accrued Cost/Retained Earnings Effect for Mar-May 2026 are RESTATED.
A6: Account | B6: Sep 2024 | C6: Oct 2024 | D6: Nov 2024 | E6: Dec 2024 | F6: Jan 2025 | G6: Feb 2025 | H6: Mar 2025 | I6: Apr 2025 | J6: May 2025 | K6: Jun 2025 | L6: Jul 2025 | M6: Aug 2025 | N6: Sep 2025 | O6: Oct 2025 | P6: Nov 2025 | Q6: Dec 2025 | R6: Jan 2026 | S6: Feb 2026 | T6: Mar 2026 | U6: Apr 2026 | V6: May 2026 | W6: Jun 2026 | X6: FY2024 (Sep-Dec, spot) | Y6: FY2025 (spot) | Z6: 2026 YTD (Jun, spot)
A7: Cash | B7: 9566562.3 | C7: 9629465.3 | D7: 9669412.9 | E7: 9712376.3 | F7: 9992464.9 | G7: 10051903 | H7: 9998329.8 | I7: 10047591 | J7: 10122568 | K7: 10063231 | L7: 10140761 | M7: 10184295 | N7: 10128133 | O7: 10204871 | P7: 10230604 | Q7: 10193034 | R7: 10211821 | S7: 10287328 | T7: 10257936 | U7: 10311450 | V7: 10316981 | W7: 10322838 | X7: =E7 -> 9712376.3 | Y7: =Q7 -> 10193034 | Z7: =W7 -> 10322838
A8: Accounts Receivable | B8: 25357011 | C8: 22622727 | D8: 23944116 | E8: 26286873 | F8: 21339103 | G8: 22847385 | H8: 23234779 | I8: 19641332 | J8: 22441274 | K8: 24618974 | L8: 18492625 | M8: 19817502 | N8: 21759262 | O8: 21755853 | P8: 21582180 | Q8: 23697888 | R8: 22380245 | S8: 23966107 | T8: 17234375 | U8: 22803156 | V8: 24419506 | W8: 26793752 | X8: =E8 -> 26286873 | Y8: =Q8 -> 23697888 | Z8: =W8 -> 26793752
A9: Contract Asset | B9: 5000000 | C9: 5000000 | D9: 5000000 | E9: 5000000 | F9: 5000000 | G9: 5000000 | H9: 5000000 | I9: 5000000 | J9: 5000000 | K9: 5000000 | L9: 5000000 | M9: 5000000 | N9: 5000000 | O9: 5000000 | P9: 5000000 | Q9: 5000000 | R9: 5000000 | S9: 5000000 | T9: 5492189.7 | U9: 5492189.7 | V9: 5492189.7 | W9: 5492189.7 | X9: =E9 -> 5000000 | Y9: =Q9 -> 5000000 | Z9: =W9 -> 5492189.7
A10: Accounts Payable | B10: 10373323 | C10: 9385488.1 | D10: 10859694 | E10: 10961322 | F10: 9020621 | G10: 9784456.3 | H10: 9879354.8 | I10: 8463214.7 | J10: 9792556.1 | K10: 9884197.6 | L10: 8125106.1 | M10: 8814579.9 | N10: 8901516.2 | O10: 9025848.2 | P10: 9788453.3 | Q10: 9881744.9 | R10: 9460740 | S10: 10263552 | T10: 7328002 | U10: 9825606.9 | V10: 10655785 | W10: 10757343 | X10: =E10 -> 10961322 | Y10: =Q10 -> 9881744.9 | Z10: =W10 -> 10757343
A11: Accrued Cost | B11: 2000000 | C11: 2000000 | D11: 2000000 | E11: 2000000 | F11: 2000000 | G11: 2000000 | H11: 2000000 | I11: 2000000 | J11: 2000000 | K11: 2000000 | L11: 2000000 | M11: 2000000 | N11: 2000000 | O11: 2000000 | P11: 2000000 | Q11: 2000000 | R11: 2000000 | S11: 2000000 | T11: 2452814.5 | U11: 2452814.5 | V11: 2452814.5 | W11: 2452814.5 | X11: =E11 -> 2000000 | Y11: =Q11 -> 2000000 | Z11: =W11 -> 2452814.5
A12: Funded Debt | B12: 181000000 | C12: 1.8041667e+08 | D12: 1.7983333e+08 | E12: 179250000 | F12: 1.8615128e+08 | G12: 1.8503437e+08 | H12: 1.8392417e+08 | I12: 1.8282062e+08 | J12: 1.817237e+08 | K12: 1.8063336e+08 | L12: 1.7954956e+08 | M12: 1.7847226e+08 | N12: 1.7740142e+08 | O12: 1.7633702e+08 | P12: 1.7527899e+08 | Q12: 1.7422732e+08 | R12: 1.7318196e+08 | S12: 1.7214286e+08 | T12: 171110007 | U12: 1.7008335e+08 | V12: 1.6906285e+08 | W12: 1.6804847e+08 | X12: =E12 -> 179250000 | Y12: =Q12 -> 1.7422732e+08 | Z12: =W12 -> 1.6804847e+08
A13: Retained Earnings Effect | B13: 0 | C13: 0 | D13: 0 | E13: 0 | F13: 0 | G13: 0 | H13: 0 | I13: 0 | J13: 0 | K13: 0 | L13: 0 | M13: 0 | N13: 0 | O13: 0 | P13: 0 | Q13: 0 | R13: 0 | S13: 0 | T13: 39375.18 | U13: 39375.18 | V13: 39375.18 | W13: 39375.18 | X13: =E13 -> 0 | Y13: =Q13 -> 0 | Z13: =W13 -> 39375.18
A15: Net Debt (derived: Funded Debt - Cash) | B15: =B12-B7 -> 1.7143344e+08 | C15: =C12-C7 -> 1.707872e+08 | D15: =D12-D7 -> 1.7016392e+08 | E15: =E12-E7 -> 1.6953762e+08 | F15: =F12-F7 -> 1.7615882e+08 | G15: =G12-G7 -> 1.7498247e+08 | H15: =H12-H7 -> 1.7392584e+08 | I15: =I12-I7 -> 1.7277303e+08 | ... W15: =W12-W7 -> 1.5772563e+08 | X15: =E15 -> 1.6953762e+08 | Y15: =Q15 -> 1.6403429e+08 | Z15: =W15 -> 1.5772563e+08
A17: DEBT & LIQUIDITY (borrower-certified roll-forward; source: Debt & Liquidity tab)
A18: Beginning Debt | B18: 1.8158333e+08 | C18: 181000000 | D18: 1.8041667e+08 | E18: 1.7983333e+08 | F18: 179250000 | G18: 1.8615128e+08 | H18: 1.8503437e+08 | I18: 1.8392417e+08 | J18: 1.8282062e+08 | K18: 1.817237e+08 | L18: 1.8063336e+08 | M18: 1.7954956e+08 | N18: 1.7847226e+08 | O18: 1.7740142e+08 | P18: 1.7633702e+08 | Q18: 1.7527899e+08 | R18: 1.7422732e+08 | S18: 1.7318196e+08 | T18: 1.7214286e+08 | U18: 171110007 | V18: 1.7008335e+08 | W18: 1.6906285e+08 | X18: =B18 -> 1.8158333e+08 | Y18: =F18 -> 179250000 | Z18: =R18 -> 1.7422732e+08
A19: Legacy Debt Payoff | B19: 0 | C19: 0 | D19: 0 | E19: 0 | F19: 179250000 | G19: 0 | H19: 0 | I19: 0 | J19: 0 | K19: 0 | L19: 0 | M19: 0 | N19: 0 | O19: 0 | P19: 0 | Q19: 0 | R19: 0 | S19: 0 | T19: 0 | U19: 0 | V19: 0 | W19: 0 | X19: =SUM(B19:E19) -> 0 | Y19: =SUM(F19:Q19) -> 179250000 | Z19: =SUM(R19:W19) -> 0
A20: New Facility Funding | B20: 0 | C20: 0 | D20: 0 | E20: 0 | F20: 1.8727493e+08 | G20: 0 | H20: 0 | I20: 0 | J20: 0 | K20: 0 | L20: 0 | M20: 0 | N20: 0 | O20: 0 | P20: 0 | Q20: 0 | R20: 0 | S20: 0 | T20: 0 | U20: 0 | V20: 0 | W20: 0 | X20: =SUM(B20:E20) -> 0 | Y20: =SUM(F20:Q20) -> 1.8727493e+08 | Z20: =SUM(R20:W20) -> 0
A21: Scheduled Principal | B21: 583333.33 | C21: 583333.33 | D21: 583333.34 | E21: 583333.33 | F21: 1123649.6 | G21: 1116907.7 | H21: 1110206.2 | I21: 1103545 | J21: 1096923.7 | K21: 1090342.2 | L21: 1083800.1 | M21: 1077297.3 | N21: 1070833.6 | O21: 1064408.6 | P21: 1058022.1 | Q21: 1051674 | R21: 1045363.9 | S21: 1039091.7 | T21: 1032857.2 | U21: 1026660 | V21: 1020500.1 | W21: 1014377.1 | X21: =SUM(B21:E21) -> 2333333.3 | Y21: =SUM(F21:Q21) -> 13047610 | Z21: =SUM(R21:W21) -> 6178850
A22: Ending Debt | B22: =B18-B19+B20-B21 -> 181000000 | C22: =C18-C19+C20-C21 -> 1.8041667e+08 | D22: =D18-D19+D20-D21 -> 1.7983333e+08 | E22: =E18-E19+E20-E21 -> 179250000 | F22: =F18-F19+F20-F21 -> 1.8615128e+08 | G22: =G18-G19+G20-G21 -> 1.8503437e+08 | H22: =H18-H19+H20-H21 -> 1.8392417e+08 | I22: =I18-I19+I20-I21 -> 1.8282062e+08 | ... W22: =W18-W19+W20-W21 -> 1.6804847e+08 | X22: =E22 -> 179250000 | Y22: =Q22 -> 1.7422732e+08 | Z22: =W22 -> 1.6804847e+08
A23: PIK | B23: 0 | C23: 0 | D23: 0 | E23: 0 | F23: 0 | G23: 0 | H23: 0 | I23: 0 | J23: 0 | K23: 0 | L23: 0 | M23: 0 | N23: 0 | O23: 0 | P23: 0 | Q23: 0 | R23: 0 | S23: 0 | T23: 0 | U23: 0 | V23: 0 | W23: 0 | X23: =SUM(B23:E23) -> 0 | Y23: =SUM(F23:Q23) -> 0 | Z23: =SUM(R23:W23) -> 0
A25: Memo: Debt tie across schedules (Funded Debt - Ending Debt, diff should be 0) | B25: =B12-B22 -> 0 | C25: =C12-C22 -> 0 | D25: =D12-D22 -> 0 | E25: =E12-E22 -> 0 | F25: =F12-F22 -> 0 | G25: =G12-G22 -> 0 | H25: =H12-H22 -> 0 | I25: =I12-I22 -> 0 | ... W25: =W12-W22 -> 0 | X25: =E25 -> 0 | Y25: =Q25 -> 0 | Z25: =W25 -> 0

Sheet Cash Flow Statement
A1: Veyrona Decision Systems, LLC | Detailed Cash Flow Statement (as reported; native Operating/Investing/Financing split)
A2: Company-prepared monthly reporting package | USD, whole dollars (scale=1) | Unaudited | Source: Finance Reporting/<YYYY>/<MM>/<Month>_<Year>_Monthly_Package.xlsx, 'Cash Flow' tab (Mar/Apr/May 2026: Quarterly_Package_2026-06-25_REVISED_MARCH-MAY.xlsx; Jun 2026: June_2026_Monthly_Package_2026-07-25.xlsx). As-reported -- native Operating/Investing/Financing Change columns, no derivation needed.
A6: Account | B6: Sep 2024 | C6: Oct 2024 | D6: Nov 2024 | E6: Dec 2024 | F6: Jan 2025 | G6: Feb 2025 | H6: Mar 2025 | I6: Apr 2025 | J6: May 2025 | K6: Jun 2025 | L6: Jul 2025 | M6: Aug 2025 | N6: Sep 2025 | O6: Oct 2025 | P6: Nov 2025 | Q6: Dec 2025 | R6: Jan 2026 | S6: Feb 2026 | T6: Mar 2026 | U6: Apr 2026 | V6: May 2026 | W6: Jun 2026 | X6: FY2024 (Sep-Dec, partial) | Y6: FY2025 | Z6: 2026 YTD (Jan-Jun)
A7: Beginning Cash | B7: 9540000 | C7: 9566562.3 | D7: 9629465.3 | E7: 9669412.9 | F7: 9712376.3 | G7: 9992464.9 | H7: 10051903 | I7: 9998329.8 | J7: 10047591 | K7: 10122568 | L7: 10063231 | M7: 10140761 | N7: 10184295 | O7: 10128133 | P7: 10204871 | Q7: 10230604 | R7: 10193034 | S7: 10211821 | T7: 10287328 | U7: 10257936 | V7: 10311450 | W7: 10316981 | X7: =B7 -> 9540000 | Y7: =F7 -> 9712376.3 | Z7: =R7 -> 10193034
A8: Operating Change | B8: 26562.26 | C8: 62903.03 | D8: 39947.63 | E8: 42963.41 | F8: 59036.68 | G8: 59438.26 | H8: -53573.37 | I8: 49261.49 | J8: 74977.07 | K8: -59337 | L8: 77529.79 | M8: 43533.44 | N8: -56161.66 | O8: 76737.74 | P8: 25732.96 | Q8: -37569.14 | R8: 18786.96 | S8: 75506.18 | T8: -29391.57 | U8: 53514.01 | V8: 5531.08 | W8: 5856.47 | X8: =SUM(B8:E8) -> 172376.33 | Y8: =SUM(F8:Q8) -> 259606.26 | Z8: =SUM(R8:W8) -> 129803.13
A9: Investing Change | B9: 0 | C9: 0 | D9: 0 | E9: 0 | F9: 0 | G9: 0 | H9: 0 | I9: 0 | J9: 0 | K9: 0 | L9: 0 | M9: 0 | N9: 0 | O9: 0 | P9: 0 | Q9: 0 | R9: 0 | S9: 0 | T9: 0 | U9: 0 | V9: 0 | W9: 0 | X9: =SUM(B9:E9) -> 0 | Y9: =SUM(F9:Q9) -> 0 | Z9: =SUM(R9:W9) -> 0
A10: Financing Change | B10: 0 | C10: 0 | D10: 0 | E10: 0 | F10: 221051.9 | G10: 0 | H10: 0 | I10: 0 | J10: 0 | K10: 0 | L10: 0 | M10: 0 | N10: 0 | O10: 0 | P10: 0 | Q10: 0 | R10: 0 | S10: 0 | T10: 0 | U10: 0 | V10: 0 | W10: 0 | X10: =SUM(B10:E10) -> 0 | Y10: =SUM(F10:Q10) -> 221051.9 | Z10: =SUM(R10:W10) -> 0
A11: Ending Cash | B11: =B7+B8+B9+B10 -> 9566562.3 | C11: =C7+C8+C9+C10 -> 9629465.3 | D11: =D7+D8+D9+D10 -> 9669412.9 | E11: =E7+E8+E9+E10 -> 9712376.3 | F11: =F7+F8+F9+F10 -> 9992464.9 | G11: =G7+G8+G9+G10 -> 10051903 | H11: =H7+H8+H9+H10 -> 9998329.8 | I11: =I7+I8+I9+I10 -> 10047591 | ... W11: =W7+W8+W9+W10 -> 10322838 | X11: =E11 -> 9712376.3 | Y11: =Q11 -> 10193034 | Z11: =W11 -> 10322838
A13: Memo: Net Change in Cash (Ending - Beginning) | B13: =B11-B7 -> 26562.26 | C13: =C11-C7 -> 62903.03 | D13: =D11-D7 -> 39947.63 | E13: =E11-E7 -> 42963.41 | F13: =F11-F7 -> 280088.58 | G13: =G11-G7 -> 59438.26 | H13: =H11-H7 -> -53573.37 | I13: =I11-I7 -> 49261.49 | ... W13: =W11-W7 -> 5856.47 | X13: =SUM(B13:E13) -> 172376.33 | Y13: =SUM(F13:Q13) -> 480658.16 | Z13: =SUM(R13:W13) -> 129803.13
A14: Memo: Net Change in Cash (sum of Operating+Investing+Financing) | B14: =B8+B9+B10 -> 26562.26 | C14: =C8+C9+C10 -> 62903.03 | D14: =D8+D9+D10 -> 39947.63 | E14: =E8+E9+E10 -> 42963.41 | F14: =F8+F9+F10 -> 280088.58 | G14: =G8+G9+G10 -> 59438.26 | H14: =H8+H9+H10 -> -53573.37 | I14: =I8+I9+I10 -> 49261.49 | ... W14: =W8+W9+W10 -> 5856.47 | X14: =SUM(B14:E14) -> 172376.33 | Y14: =SUM(F14:Q14) -> 480658.16 | Z14: =SUM(R14:W14) -> 129803.13
A15: Memo: CF internal tie (diff, should be 0) | B15: =B13-B14 -> -2.2191671e-10 | C15: =C13-C14 -> -6.693881e-10 | D15: =D13-D14 -> 8.2218321e-10 | E15: =E13-E14 -> 0 | F15: =F13-F14 -> 0 | G15: =G13-G14 -> -2.2555469e-10 | H15: =H13-H14 -> 8.2218321e-10 | I15: =I13-I14 -> 2.2555469e-10 | ... W15: =W13-W14 -> 6.702976e-10 | X15: =SUM(B15:E15) -> -6.9121597e-11 | Y15: =SUM(F15:Q15) -> 0 | Z15: =SUM(R15:W15) -> 8.2491169e-10
A16: Memo: Cash per Balance Sheet | B16: ='Balance Sheet'!B7 -> 9566562.3 | C16: ='Balance Sheet'!C7 -> 9629465.3 | D16: ='Balance Sheet'!D7 -> 9669412.9 | E16: ='Balance Sheet'!E7 -> 9712376.3 | F16: ='Balance Sheet'!F7 -> 9992464.9 | G16: ='Balance Sheet'!G7 -> 10051903 | H16: ='Balance Sheet'!H7 -> 9998329.8 | I16: ='Balance Sheet'!I7 -> 10047591 | ... W16: ='Balance Sheet'!W7 -> 10322838 | X16: =E16 -> 9712376.3 | Y16: =Q16 -> 10193034 | Z16: =W16 -> 10322838
A17: Memo: CF-vs-BS Cash tie (Ending Cash - BS Cash, diff should be 0) | B17: =B11-B16 -> 0 | C17: =C11-C16 -> 0 | D17: =D11-D16 -> 0 | E17: =E11-E16 -> 0 | F17: =F11-F16 -> 0 | G17: =G11-G16 -> 0 | H17: =H11-H16 -> 0 | I17: =I11-I16 -> 0 | ... W17: =W11-W16 -> 0 | X17: =E17 -> 0 | Y17: =Q17 -> 0 | Z17: =W17 -> 0

Sheet Sources & Notes
A1: Entity | B1: Veyrona Decision Systems, LLC (consolidated) -- per borrower-config model.entity='consolidated'. No separate divisional/standalone consolidation level is offered in the reporting package.
A2: Units | B2: USD, whole dollars (model.scale = 1). Verified against June 2026 revenue ($19,921,004.84) and FY2024 annual revenue ($213,000,000.00, ~$17.75M/month average), same unit; no '$ in thousands' caption anywhere in the source workbooks.
A3: Basis | B3: Actuals only -- company-prepared monthly reporting packages (Finance Reporting), unaudited. No proforma/budget/forecast columns included. Each monthly package's 'Package Authority' tab states 'AS FILED' generically (a point-in-time filing label, not a restatement flag) except the two June-quarter-close files, whose Authority fields explicitly mark them as the revised/authoritative source for March-May 2026 and the authoritative June close respectively.
A4: Coverage | B4: Sep 2024 through Jun 2026 (22 months), continuous, no gaps. Sep 2024-Feb 2026 (18 months) from each month's own individual monthly package. Mar/Apr/May 2026 from the REVISED consolidated file (see restatement note below), NOT their individual monthly packages, which are confirmed stale. Jun 2026 from its own regular monthly package.
A5: Primary source files | B5: One <Month>_<Year>_Monthly_Package.xlsx (or ..._AS_FILED_Monthly_Package.xlsx -- both are point-in-time filing labels, not restatement flags, confirmed by monitor-setup's investigation) per month, Sep 2024 through Feb 2026 -- single-period snapshot, four statement tabs (Income Statement, Balance Sheet, Cash Flow, Debt & Liquidity), verified identical schema across Sep 2024, Jun 2025 and Jun 2026. Mar/Apr/May 2026 from Finance Reporting/2026/Q2/June Close/Quarterly_Package_2026-06-25_REVISED_MARCH-MAY.xlsx (issued 2026-06-25). Jun 2026 from Finance Reporting/2026/Q2/June Close/June_2026_Monthly_Package_2026-07-25.xlsx (filed 2026-07-25; its own March-May comparative columns independently verified identical to the REVISED file, confirming no second restatement occurred). Quarterly_Package_2026-06-18_ORIGINAL.xlsx in the same folder is the pre-restatement original and was NOT used anywhere in this build. See source-map.json for the exact file per statement per month.
A6: RESTATEMENT -- March 2026 (Atlas Acceptance milestone, non-cash) | B6: Per Restatement_Notice_2026-06-20.pdf: Veyrona's finance team found an OMITTED completed implementation milestone (customer Arcwell Transit, project 'Atlas Acceptance', accepted 2026-03-29 but not booked at the March close). Entry is NON-CASH (Dr. Contract asset / Cr. Implementation revenue $492,189.73; Dr. Direct implementation costs / Cr. Accrued implementation costs $452,814.55) -- cash flow and the debt schedule are untouched (verified: Mar/Apr/May Cash Flow and Debt & Liquidity figures are IDENTICAL between the stale individual packages and the REVISED file). March 2026 Income Statement: Revenue $13,570,373.98 -> $14,062,563.71 (+$492,189.73); Cost of Revenue $7,328,001.95 -> $7,780,816.50 (+$452,814.55); Operating Expenses UNCHANGED ($3,229,895.60); Reported EBITDA $3,012,476.43 -> $3,051,851.61 (+$39,375.18 net). March/April/May 2026 Balance Sheet: Contract Asset $5,000,000.00 -> $5,492,189.73; Accrued Cost $2,000,000.00 -> $2,452,814.55; Retained Earnings Effect $0.00 -> $39,375.18, in ALL THREE months (the correction is a cumulative snapshot carried forward on the balance sheet even though only March's income statement changed). April and May 2026 Income Statement figures are IDENTICAL in the stale individual packages and the REVISED file -- confirmed by direct comparison; only their Balance Sheet figures were stale. AUTHORITATIVE FILE FOR MARCH, APRIL AND MAY 2026: Quarterly_Package_2026-06-25_REVISED_MARCH-MAY.xlsx. CONFIRMED STALE, NEVER REISSUED: March_2026_AS_FILED_Monthly_Package.xlsx (wrong on BOTH income statement and balance sheet), April_2026_Monthly_Package.xlsx and May_2026_AS_FILED_Monthly_Package.xlsx (correct income statement, stale balance sheet). All twelve restated line values are logged old->new in restatements.json (material=true in every case: each exceeds the greater of $25k or 1% of the prior value).
A7: Restatement scan -- scope | B7: Full scan performed across all 22 months: each individual month's own package compared against the REVISED consolidated file (the only file whose range overlaps any individual month, covering Mar-May 2026) and against June_2026_Monthly_Package_2026-07-25.xlsx for its own Mar-May comparative columns (which matched the REVISED file exactly, confirming no further restatement). Result: March 2026 Income Statement + Balance Sheet, and April/May 2026 Balance Sheet only, differ (see above); no other month has a second source to compare against (each individual month is a single-period snapshot with no other overlapping file). No prior canonical model existed for this borrower (first build), so no prior-snapshot diff applies.
A8: Income Statement -- four-row native cadence (JUDGMENT CALL, per borrower-config.json model_lines._construction_note) | B8: The borrower's monthly Income Statement has EXACTLY four native rows -- Revenue, Cost of Revenue, Operating Expenses, Reported EBITDA -- with no native Gross Profit, Net Income, Interest Expense, Taxes, or D&A anywhere on the IS, Cash Flow, or Debt & Liquidity tabs. Veyrona is also a pass-through LLC with no entity-level income tax (FY2022-FY2024 Reviewed Financial Statements) -- taxes is a genuine N/A, not merely unreported. Per borrower-config's pre-defined construction, a DERIVED 'Gross Profit (derived)' row = Revenue - Cost of Revenue is inserted between Cost of Revenue and Operating Expenses/Reported EBITDA. VERIFIED exact against FY2024 annual audited figures: $213,000,000.00 - $115,020,000.00 = $97,980,000.00 Gross Profit; $97,980,000.00 - $64,519,339.31 Operating Expenses = $33,460,660.69, tying EXACTLY to disclosed Covenant EBITDA -- not a guess. net_income/interest_expense/taxes/depreciation_amortization are left BLANK/unmapped in model_lines rather than guessed -- there is no cash-basis proxy for any of them anywhere in this borrower's reporting; three-statement-analysis will report these in lines_not_found with dependent ratios suppressed.
A9: EBITDA bridge | B9: Per covenant-spec.json#/definitions/Covenant_EBITDA, compute.ebitda_bridge = 'Reported EBITDA' -- the model's own single pinned EBITDA row (Revenue - Cost of Revenue - Operating Expenses), bound directly with ZERO addback. Verified exact match to certified Covenant EBITDA in every one of six quarterly Covenant_Calculation workbooks filed 2025 Q1 through 2026 Q2 ('Permitted add-backs: $0' every quarter), and to the FY2024 Reviewed Financial Statements' own EBITDA of $33,460,660.69. This EBITDA bridge is NOT provisional -- it is the covenant-spec-directed definition, with a covenant-spec.json present.
A10: Balance Sheet -- NO native totals (JUDGMENT CALL, per borrower-config.json analysis_lines._omitted_note; same pattern as this portfolio's Selvara build) | B10: This borrower's monthly Balance Sheet carries NO Total Assets / Total Liabilities / Total Equity anywhere -- only Cash, Accounts Receivable, Contract Asset, Accounts Payable, Accrued Cost, Funded Debt, and Retained Earnings Effect, verified identical across every month checked (Sep 2024 through Jun 2026). Consequently NO Balance-Check row is written -- inventing Total Assets/Liabilities/Equity from data the borrower does not report would misstate the model; this is a disclosed, borrower-config-documented gap, not an omission (the same reading used for Selvara elsewhere in this batch, which also carries no native Balance Sheet totals). The closest native cross-check is the source package's own 'Balance-sheet bridge' control check (Contract Asset - Accrued Cost - Retained Earnings Effect - $3,000,000 = 0 every month, verified), which is a partial identity, not a full double-entry balance.
A11: Net Debt (derived row) | B11: Per covenant-spec.json#/definitions/Net_Debt engine-design note: the covenant engine's 'formula' compute supports only op:'sum', so it cannot express Funded Debt minus Unrestricted Cash directly. 'Net Debt (derived: Funded Debt - Cash)' is added as a real model row (Balance Sheet row 15) so the covenant engine can read it as a plain model_line rather than a formula. VERIFIED against all six Covenant_Calculation workbooks filed to date (2025 Q1 through 2026 Q2): Net Debt = Funded Debt - Unrestricted Cash exactly every quarter, with both 'Debt check' and 'Ratio check' residual lines equal to 0.00 in every filing.
A12: Funded Debt -- sourced from the certified Balance Sheet, NOT the generated debt-service schedule (JUDGMENT CALL, per covenant-spec.json step7_signoff decision 'amortization_mechanic_declining_balance') | B12: The facility's '0.60% of beginning principal monthly' amortization clause is ambiguous between flat-off-original-principal (what the debt-service engine's v1 schedule models) and declining balance (0.60% of each month's own opening balance). The borrower's own 18+ months of certified Debt & Liquidity figures resolve this as DECLINING BALANCE (e.g. Jan 2025 scheduled principal $1,123,649.58 shrinking to $1,032,857.19 by Mar 2026, tracking a declining base), and the generated debt-service-schedule.json is a known flat-base approximation, already ~5.2% too high cumulative by June 2026 per the analyst's own step-7 sign-off. 'Funded Debt' (Balance Sheet row 12) is therefore sourced directly from each month's own certified Balance Sheet / Debt & Liquidity 'Ending Debt' figure (the two tie exactly every month checked -- see row 25 memo tie, and independently against the Covenant_Calculation workbooks: e.g. Q1'25 $183,924,166.39, Q2'26 $168,048,469.80), NOT from debt-service-schedule.json's generated principal/balance figures.
... A19: Build tool / recalc | B19: Built with openpyxl; formula cells recalculated (cached values populated) via headless LibreOffice as the LAST write, per assembling-rules.md. Gated with references/validate_model.py before becoming canonical.
