Workbook

Sheet Income Statement
A1: Asteron Care Partners, LLC | Detailed Income Statement
A2: Company-prepared monthly reporting package | USD (whole dollars) | Unaudited, PROVISIONAL restructuring accounting through Jun 2026 -- see Sources & Notes | Source: monthly.xlsx, 'Income Statement' tab
A6: Account | B6: Sep 2024 | C6: Oct 2024 | D6: Nov 2024 | E6: Dec 2024 | F6: Jan 2025 | G6: Feb 2025 | H6: Mar 2025 | I6: Apr 2025 | J6: May 2025 | K6: Jun 2025 | L6: Jul 2025 | M6: Aug 2025 | N6: Sep 2025 | O6: Oct 2025 | P6: Nov 2025 | Q6: Dec 2025 | R6: Jan 2026 | S6: Feb 2026 | T6: Mar 2026 | U6: Apr 2026 | V6: May 2026 | W6: Jun 2026 | X6: FY2024 (Sep-Dec, partial) | Y6: FY2025 | Z6: 2026 YTD (Jan-Jun)
A7: Revenue | B7: 14643908 | C7: 15246154 | D7: 15656105 | E7: 13389545 | F7: 14164178 | G7: 14413745 | H7: 14924661 | I7: 15267517 | J7: 15610914 | K7: 15888032 | L7: 12283732 | M7: 11863595 | N7: 12125235 | O7: 12593894 | P7: 13021719 | Q7: 11093057 | R7: 10891583 | S7: 11060843 | T7: 11470546 | U7: 12654928 | V7: 12875350 | W7: 13164600 | X7: =SUM(B7:E7) -> 58935712 | Y7: =SUM(F7:Q7) -> 1.6325028e+08 | Z7: =SUM(R7:W7) -> 72117849
A8: Direct clinical labor | B8: -6098052.8 | C8: -6098052.8 | D8: -6098052.8 | E8: -6098052.8 | F8: -6079463.1 | G8: -6079463.1 | H8: -6079463.1 | I8: -6079463.1 | J8: -6079463.1 | K8: -6079463.1 | L8: -5717290.1 | M8: -5717290.1 | N8: -5717290.1 | O8: -5717290.1 | P8: -5717290.1 | Q8: -5717290.1 | R8: -5717290.1 | S8: -5717290.1 | T8: -5717290.1 | U8: -5758889.3 | V8: -5758889.3 | W8: -5758889.3 | X8: =SUM(B8:E8) -> -24392211 | Y8: =SUM(F8:Q8) -> -70780519 | Z8: =SUM(R8:W8) -> -34428538
A9: Contract labor | B9: -595107 | C9: -595107 | D9: -595107 | E9: -595107 | F9: -620217 | G9: -620217 | H9: -620217 | I9: -620217 | J9: -620217 | K9: -620217 | L9: -1949280 | M9: -1949280 | N9: -1949280 | O9: -1949280 | P9: -1949280 | Q9: -1949280 | R9: -1674930 | S9: -1674930 | T9: -1674930 | U9: -1403602.5 | V9: -1403602.5 | W9: -1319386.4 | X9: =SUM(B9:E9) -> -2380428 | Y9: =SUM(F9:Q9) -> -15416982 | Z9: =SUM(R9:W9) -> -9151381.3
A10: Medical supplies | B10: -1215411.9 | C10: -1265493.9 | D10: -1299620.3 | E10: -1111548.2 | F10: -1176352.3 | G10: -1197152.9 | H10: -1239683.6 | I10: -1268241.9 | J10: -1296835.2 | K10: -1319950.6 | L10: -972639.38 | M10: -939456.71 | N10: -960241.58 | O10: -997428.14 | P10: -1031377 | Q10: -878633.63 | R10: -841412.83 | S10: -854561.75 | T10: -886292.73 | U10: -1003530.7 | V10: -1021005.7 | W10: -1044127.9 | X10: =SUM(B10:E10) -> -4892074.3 | Y10: =SUM(F10:Q10) -> -13277993 | Z10: =SUM(R10:W10) -> -5650931.7
A11: Other patient service costs | B11: -702907.56 | C11: -731815.39 | D11: -751493.04 | E11: -642698.18 | F11: -679880.54 | G11: -691859.77 | H11: -716383.74 | I11: -732840.83 | J11: -749323.9 | K11: -762625.55 | L11: -589619.13 | M11: -569452.53 | N11: -582011.26 | O11: -604506.9 | P11: -625042.5 | Q11: -532466.74 | R11: -522795.97 | S11: -530920.45 | T11: -550586.21 | U11: -607436.55 | V11: -618016.81 | W11: -631900.8 | X11: =SUM(B11:E11) -> -2828914.2 | Y11: =SUM(F11:Q11) -> -7836013.4 | Z11: =SUM(R11:W11) -> -3461656.8
A12: Cost of Patient Services | B12: =SUM(B8:B11) -> -8611479.2 | C12: =SUM(C8:C11) -> -8690469.1 | D12: =SUM(D8:D11) -> -8744273.1 | E12: =SUM(E8:E11) -> -8447406.1 | F12: =SUM(F8:F11) -> -8555912.9 | G12: =SUM(G8:G11) -> -8588692.8 | H12: =SUM(H8:H11) -> -8655747.4 | I12: =SUM(I8:I11) -> -8700762.8 | ... W12: =SUM(W8:W11) -> -8754304.3 | X12: =SUM(B12:E12) -> -34493627 | Y12: =SUM(F12:Q12) -> -1.0731151e+08 | Z12: =SUM(R12:W12) -> -52692508
A13: Gross Profit | B13: =B7+B12 -> 6032428.4 | C13: =C7+C12 -> 6555684.7 | D13: =D7+D12 -> 6911831.9 | E13: =E7+E12 -> 4942139.2 | F13: =F7+F12 -> 5608265.2 | G13: =G7+G12 -> 5825052.3 | H13: =H7+H12 -> 6268914 | I13: =I7+I12 -> 6566754.6 | ... W13: =W7+W12 -> 4410295.4 | X13: =SUM(B13:E13) -> 24442084 | Y13: =SUM(F13:Q13) -> 55938773 | Z13: =SUM(R13:W13) -> 19425342
A14: Occupancy and site costs | B14: -1394836.4 | C14: -1426153.3 | D14: -1447470.7 | E14: -1329609.6 | F14: -1569890.5 | G14: -1582868 | H14: -1609435.6 | I14: -1627264.2 | J14: -1645120.8 | K14: -1659530.9 | L14: -2227107.3 | M14: -2205260.2 | N14: -2218865.5 | O14: -2243235.7 | P14: -2265482.6 | Q14: -2165192.2 | R14: -1659715.6 | S14: -1668517.1 | T14: -1689821.7 | U14: -1531409.5 | V14: -1542871.4 | W14: -1557912.4 | X14: =SUM(B14:E14) -> -5598070 | Y14: =SUM(F14:Q14) -> -23019254 | Z14: =SUM(R14:W14) -> -9650247.7
A15: Corporate and administrative costs | B15: -1450763.5 | C15: -1510423.8 | D15: -1551128.8 | E15: -1326468 | F15: -1403170.9 | G15: -1427958.7 | H15: -1478392.2 | I15: -1512332.2 | J15: -1546612.6 | K15: -1573898.1 | L15: -1216932.5 | M15: -1175116.5 | N15: -1201147.6 | O15: -1247598.6 | P15: -1289934.6 | Q15: -1099013.9 | R15: -1079010.4 | S15: -1095705.5 | T15: -1136360.9 | U15: -1254154 | V15: -1276089.9 | W15: -1304641.7 | X15: =SUM(B15:E15) -> -5838784 | Y15: =SUM(F15:Q15) -> -16172108 | Z15: =SUM(R15:W15) -> -7145962.3
A16: Reported EBITDA | B16: =B13+B14+B15 -> 3186828.4 | C16: =C13+C14+C15 -> 3619107.7 | D16: =D13+D14+D15 -> 3913232.4 | E16: =E13+E14+E15 -> 2286061.6 | F16: =F13+F14+F15 -> 2635203.8 | G16: =G13+G14+G15 -> 2814225.6 | H16: =H13+H14+H15 -> 3181086.2 | I16: =I13+I14+I15 -> 3427158.2 | ... W16: =W13+W14+W15 -> 1547741.3 | X16: =SUM(B16:E16) -> 13005230 | Y16: =SUM(F16:Q16) -> 16747411 | Z16: =SUM(R16:W16) -> 2629131.5
A17: Depreciation | B17: -1093236.6 | C17: -1116524.6 | D17: -1139348.8 | E17: -1158253.8 | F17: -872646.66 | G17: -894820.45 | H17: -916708.35 | I17: -938357.92 | J17: -961674.58 | K17: -986272.96 | L17: -988965.71 | M17: -991483.36 | N17: -994211.33 | O17: -997147.4 | P17: -1000023.4 | Q17: -1002391 | R17: -1004861 | S17: -1007464.7 | T17: -1010019.3 | U17: -1012736 | V17: -1015660.9 | W17: -1018780.2 | X17: =SUM(B17:E17) -> -4507363.8 | Y17: =SUM(F17:Q17) -> -11544703 | Z17: =SUM(R17:W17) -> -6069522
A18: Cash interest | B18: -574055.4 | C18: -570037.02 | D18: -566046.76 | E18: -562084.43 | F18: -558149.84 | G18: -554242.79 | H18: -550363.09 | I18: -546510.55 | J18: -542684.97 | K18: -538886.18 | L18: -535113.98 | M18: -531368.18 | N18: -527648.6 | O18: -523955.06 | P18: -520287.38 | Q18: -574784.25 | R18: -583728.7 | S18: -583728.7 | T18: -583728.7 | U18: -425000 | V18: -424575 | W18: -424150.43 | X18: =SUM(B18:E18) -> -2272223.6 | Y18: =SUM(F18:Q18) -> -6503994.9 | Z18: =SUM(R18:W18) -> -3024911.5
A19: Debt issuance cost amortization | B19: 0 | C19: 0 | D19: 0 | E19: 0 | F19: 0 | G19: 0 | H19: 0 | I19: 0 | J19: 0 | K19: 0 | L19: 0 | M19: 0 | N19: 0 | O19: 0 | P19: 0 | Q19: 0 | R19: 0 | S19: 0 | T19: 0 | U19: -20000 | V19: -20000 | W19: -20000 | X19: =SUM(B19:E19) -> 0 | Y19: =SUM(F19:Q19) -> 0 | Z19: =SUM(R19:W19) -> -60000
A20: Restructuring advisory expense | B20: 0 | C20: 0 | D20: 0 | E20: 0 | F20: 0 | G20: 0 | H20: 0 | I20: 0 | J20: 0 | K20: 0 | L20: 0 | M20: 0 | N20: 0 | O20: 0 | P20: 0 | Q20: 0 | R20: 0 | S20: 0 | T20: -1800000 | U20: 0 | V20: 0 | W20: 0 | X20: =SUM(B20:E20) -> 0 | Y20: =SUM(F20:Q20) -> 0 | Z20: =SUM(R20:W20) -> -1800000
A21: Income tax expense | B21: -384896.81 | C21: -460087.9 | D21: -509965.19 | E21: -207342.05 | F21: -254221.65 | G21: -281197.91 | H21: -342638.85 | I21: -382027.91 | J21: -421001.38 | K21: -451002.06 | L21: 360437.17 | M21: 440376.68 | N21: 391746.91 | O21: 304071.5 | P21: 235314.24 | Q21: 400143.26 | R21: 0 | S21: 0 | T21: 0 | U21: 0 | V21: 0 | W21: 0 | X21: =SUM(B21:E21) -> -1562291.9 | Y21: =SUM(F21:Q21) -> 2.910383e-11 | Z21: =SUM(R21:W21) -> 0
A22: Bridge upfront fee | B22: 0 | C22: 0 | D22: 0 | E22: 0 | F22: 0 | G22: 0 | H22: 0 | I22: 0 | J22: 0 | K22: 0 | L22: 0 | M22: 0 | N22: 0 | O22: 0 | P22: 0 | Q22: -140000 | R22: 0 | S22: 0 | T22: 0 | U22: 0 | V22: 0 | W22: 0 | X22: =SUM(B22:E22) -> 0 | Y22: =SUM(F22:Q22) -> -140000 | Z22: =SUM(R22:W22) -> 0
A23: Goodwill impairment | B23: 0 | C23: 0 | D23: 0 | E23: 0 | F23: 0 | G23: 0 | H23: 0 | I23: 0 | J23: 0 | K23: 0 | L23: 0 | M23: 0 | N23: 0 | O23: 0 | P23: 0 | Q23: -1910453.2 | R23: 0 | S23: 0 | T23: 0 | U23: 0 | V23: 0 | W23: 0 | X23: =SUM(B23:E23) -> 0 | Y23: =SUM(F23:Q23) -> -1910453.2 | Z23: =SUM(R23:W23) -> 0
A24: Net income | B24: =B16+B17+B18+B19+B20+B21+B22+B23 -> 1134639.6 | C24: =C16+C17+C18+C19+C20+C21+C22+C23 -> 1472458.2 | D24: =D16+D17+D18+D19+D20+D21+D22+D23 -> 1697871.7 | E24: =E16+E17+E18+E19+E20+E21+E22+E23 -> 358381.33 | F24: =F16+F17+F18+F19+F20+F21+F22+F23 -> 950185.61 | G24: =G16+G17+G18+G19+G20+G21+G22+G23 -> 1083964.5 | H24: =H16+H17+H18+H19+H20+H21+H22+H23 -> 1371375.9 | I24: =I16+I17+I18+I19+I20+I21+I22+I23 -> 1560261.8 | ... W24: =W16+W17+W18+W19+W20+W21+W22+W23 -> 84810.69 | X24: =SUM(B24:E24) -> 4663350.8 | Y24: =SUM(F24:Q24) -> -3351740.5 | Z24: =SUM(R24:W24) -> -8325302

Sheet Balance Sheet
A1: Asteron Care Partners, LLC | Detailed Balance Sheet
A2: Company-prepared monthly reporting package | USD (whole dollars) | Unaudited, PROVISIONAL restructuring accounting through Jun 2026 (carryover/historical-cost basis, not fresh-start) -- see Sources & Notes | Source: monthly.xlsx, 'Balance Sheet' tab
A6: Account | B6: Sep 2024 | C6: Oct 2024 | D6: Nov 2024 | E6: Dec 2024 | F6: Jan 2025 | G6: Feb 2025 | H6: Mar 2025 | I6: Apr 2025 | J6: May 2025 | K6: Jun 2025 | L6: Jul 2025 | M6: Aug 2025 | N6: Sep 2025 | O6: Oct 2025 | P6: Nov 2025 | Q6: Dec 2025 | R6: Jan 2026 | S6: Feb 2026 | T6: Mar 2026 | U6: Apr 2026 | V6: May 2026 | W6: Jun 2026 | X6: FY2024 (Sep-Dec, spot) | Y6: FY2025 (spot) | Z6: 2026 YTD (Jun, spot)
A7: Cash | B7: 8238520.8 | C7: 8364065.5 | D7: 8968774.1 | E7: 10192084 | F7: 9490470.7 | G7: 9342106.6 | H7: 8319679.1 | I7: 8584491.8 | J7: 9061715.7 | K7: 8533476.1 | L7: 10150227 | M7: 8935807.8 | N7: 6951216.9 | O7: 5008900 | P7: 3431896.4 | Q7: 11012418 | R7: 9181041.2 | S7: 7684278.1 | T7: 18136709 | U7: 18140282 | V7: 18413087 | W7: 18817444 | X7: =E7 -> 10192084 | Y7: =Q7 -> 11012418 | Z7: =W7 -> 18817444
A8: Accounts receivable | B8: 21782240 | C8: 22678680 | D8: 23287870 | E8: 19916029 | F8: 21068710 | G8: 21439500 | H8: 22199860 | I8: 22710352 | J8: 23220660 | K8: 23633334 | L8: 21135146 | M8: 20413380 | N8: 20862648 | O8: 21669381 | P8: 22405507 | Q8: 19086623 | R8: 18739909 | S8: 19031161 | T8: 19735948 | U8: 20087028 | V8: 20436575 | W8: 20896429 | X8: =E8 -> 19916029 | Y8: =Q8 -> 19086623 | Z8: =W8 -> 20896429
A9: Other current assets | B9: 3000000 | C9: 3000000 | D9: 3000000 | E9: 3000000 | F9: 3000000 | G9: 3000000 | H9: 3000000 | I9: 3000000 | J9: 3000000 | K9: 3000000 | L9: 3000000 | M9: 3000000 | N9: 3000000 | O9: 3000000 | P9: 3000000 | Q9: 3000000 | R9: 3000000 | S9: 3000000 | T9: 3000000 | U9: 3000000 | V9: 3000000 | W9: 3000000 | X9: =E9 -> 3000000 | Y9: =Q9 -> 3000000 | Z9: =W9 -> 3000000
A10: Tax refund receivable | B10: 0 | C10: 0 | D10: 0 | E10: 0 | F10: 0 | G10: 0 | H10: 0 | I10: 0 | J10: 0 | K10: 0 | L10: 360437.17 | M10: 800813.85 | N10: 1192560.8 | O10: 1496632.3 | P10: 1731946.5 | Q10: 2132089.8 | R10: 2132089.8 | S10: 2132089.8 | T10: 2132089.8 | U10: 2132089.8 | V10: 2132089.8 | W10: 2132089.8 | X10: =E10 -> 0 | Y10: =Q10 -> 2132089.8 | Z10: =W10 -> 2132089.8
A11: PP&E, net | B11: 50820500 | C11: 51533514 | D11: 52272898 | E11: 52721389 | F11: 53548444 | G11: 54383273 | H11: 55257524 | I11: 56151268 | J11: 57062903 | K11: 57983194 | L11: 57215336 | M11: 56437397 | N11: 55661440 | O11: 54890983 | P11: 54125350 | Q11: 53322634 | R11: 52513822 | S11: 51705452 | T11: 50901903 | U11: 50116955 | V11: 49333051 | W11: 48551233 | X11: =E11 -> 52721389 | Y11: =Q11 -> 53322634 | Z11: =W11 -> 48551233
A12: Operating lease ROU assets | B12: 37829378 | C12: 37474185 | D12: 37117355 | E12: 36758881 | F12: 36398754 | G12: 36036906 | H12: 35673329 | I12: 35308014 | J12: 34940952 | K12: 34572134 | L12: 34201551 | M12: 33829195 | N12: 33455056 | O12: 33079126 | P12: 32701395 | Q12: 32321854 | R12: 31940494 | S12: 31557245 | T12: 31172098 | U12: 30785042 | V12: 30396068 | W12: 30005167 | X12: =E12 -> 36758881 | Y12: =Q12 -> 32321854 | Z12: =W12 -> 30005167
A13: Goodwill | B13: 80000000 | C13: 80000000 | D13: 80000000 | E13: 80000000 | F13: 80000000 | G13: 80000000 | H13: 80000000 | I13: 80000000 | J13: 80000000 | K13: 80000000 | L13: 80000000 | M13: 80000000 | N13: 80000000 | O13: 80000000 | P13: 80000000 | Q13: 78089547 | R13: 78089547 | S13: 78089547 | T13: 78089547 | U13: 78089547 | V13: 78089547 | W13: 78089547 | X13: =E13 -> 80000000 | Y13: =Q13 -> 78089547 | Z13: =W13 -> 78089547
A14: Total assets | B14: =SUM(B7:B13) -> 2.0167064e+08 | C14: =SUM(C7:C13) -> 2.0305044e+08 | D14: =SUM(D7:D13) -> 2.046469e+08 | E14: =SUM(E7:E13) -> 2.0258838e+08 | F14: =SUM(F7:F13) -> 2.0350638e+08 | G14: =SUM(G7:G13) -> 2.0420179e+08 | H14: =SUM(H7:H13) -> 2.0445039e+08 | I14: =SUM(I7:I13) -> 2.0575413e+08 | ... W14: =SUM(W7:W13) -> 2.0149191e+08 | X14: =E14 -> 2.0258838e+08 | Y14: =Q14 -> 1.9896517e+08 | Z14: =W14 -> 2.0149191e+08
A16: Accounts payable | B16: 5131727.1 | C16: 5320011.8 | D16: 5448374.5 | E16: 4740031.1 | F16: 5202692.5 | G16: 5280878.5 | H16: 5440364.6 | I16: 5547568.8 | J16: 5655403.9 | K16: 5741848.6 | L16: 6377890.8 | M16: 6248264.5 | N16: 6329113.4 | O16: 6473589.6 | P16: 6605368.6 | Q16: 6011540.2 | R16: 5210120 | S16: 5261836.7 | T16: 5387310 | U16: 5343168.4 | V16: 5411248.7 | W16: 5433050.7 | X16: =E16 -> 4740031.1 | Y16: =Q16 -> 6011540.2 | Z16: =W16 -> 5433050.7
A17: Current tax payable | B17: 0 | C17: 460087.9 | D17: 970053.09 | E17: 0 | F17: 254221.65 | G17: 535419.56 | H17: 0 | I17: 382027.91 | J17: 803029.29 | K17: 0 | L17: 0 | M17: 0 | N17: 0 | O17: 0 | P17: 0 | Q17: 0 | R17: 0 | S17: 0 | T17: 0 | U17: 0 | V17: 0 | W17: 0 | X17: =E17 -> 0 | Y17: =Q17 -> 0 | Z17: =W17 -> 0
A18: Operating lease liabilities | B18: 39249421 | C18: 38924770 | D18: 38598483 | E18: 38270551 | F18: 37929170 | G18: 37586067 | H18: 37241235 | I18: 36894665 | J18: 36546348 | K18: 36196275 | L18: 35844438 | M18: 35490827 | N18: 35135433 | O18: 34778248 | P18: 34419262 | Q18: 34058467 | R18: 33683785 | S18: 33307215 | T18: 32928745 | U18: 32548368 | V18: 32166072 | W18: 31781849 | X18: =E18 -> 38270551 | Y18: =Q18 -> 34058467 | Z18: =W18 -> 31781849
A19: Funded debt, carrying amount | B19: 59482123 | C19: 59065749 | D19: 58652288 | E19: 58241722 | F19: 57834030 | G19: 57429192 | H19: 57027188 | I19: 56627997 | J19: 56231601 | K19: 55837980 | L19: 55447114 | M19: 55058985 | N19: 54673572 | O19: 54290857 | P19: 53910821 | Q19: 60910821 | R19: 60910821 | S19: 60910821 | T19: 49800000 | U19: 49769000 | V19: 49738051 | W19: 49707153 | X19: =E19 -> 58241722 | Y19: =Q19 -> 60910821 | Z19: =W19 -> 49707153
A20: Other accrued liabilities | B20: 5000000 | C20: 5000000 | D20: 5000000 | E20: 5000000 | F20: 5000000 | G20: 5000000 | H20: 5000000 | I20: 5000000 | J20: 5000000 | K20: 5000000 | L20: 5000000 | M20: 5000000 | N20: 5000000 | O20: 5000000 | P20: 5000000 | Q20: 5000000 | R20: 5000000 | S20: 5000000 | T20: 5000000 | U20: 5000000 | V20: 5000000 | W20: 5000000 | X20: =E20 -> 5000000 | Y20: =Q20 -> 5000000 | Z20: =W20 -> 5000000
A21: Total liabilities | B21: =SUM(B16:B20) -> 1.0886327e+08 | C21: =SUM(C16:C20) -> 1.0877062e+08 | D21: =SUM(D16:D20) -> 1.086692e+08 | E21: =SUM(E16:E20) -> 1.062523e+08 | F21: =SUM(F16:F20) -> 1.0622011e+08 | G21: =SUM(G16:G20) -> 1.0583156e+08 | H21: =SUM(H16:H20) -> 1.0470879e+08 | I21: =SUM(I16:I20) -> 1.0445226e+08 | ... W21: =SUM(W16:W20) -> 91922053 | X21: =E21 -> 1.062523e+08 | Y21: =Q21 -> 1.0598083e+08 | Z21: =W21 -> 91922053
A23: Common equity | B23: 92807368 | C23: 94279826 | D23: 95977697 | E23: 96336079 | F23: 97286264 | G23: 98370229 | H23: 99741605 | I23: 1.0130187e+08 | J23: 1.0304985e+08 | K23: 1.0494603e+08 | L23: 1.0339325e+08 | M23: 1.0161852e+08 | N23: 99984804 | O23: 98602327 | P23: 97460643 | Q23: 92984338 | R23: 90792177 | S23: 88719901 | T23: 93141418 | U23: 92779587 | V23: 92574226 | W23: 92659036 | X23: =E23 -> 96336079 | Y23: =Q23 -> 92984338 | Z23: =W23 -> 92659036
A24: Preferred equity | B24: 0 | C24: 0 | D24: 0 | E24: 0 | F24: 0 | G24: 0 | H24: 0 | I24: 0 | J24: 0 | K24: 0 | L24: 0 | M24: 0 | N24: 0 | O24: 0 | P24: 0 | Q24: 0 | R24: 0 | S24: 0 | T24: 16910821 | U24: 16910821 | V24: 16910821 | W24: 16910821 | X24: =E24 -> 0 | Y24: =Q24 -> 0 | Z24: =W24 -> 16910821
A25: Total equity | B25: =SUM(B23:B24) -> 92807368 | C25: =SUM(C23:C24) -> 94279826 | D25: =SUM(D23:D24) -> 95977697 | E25: =SUM(E23:E24) -> 96336079 | F25: =SUM(F23:F24) -> 97286264 | G25: =SUM(G23:G24) -> 98370229 | H25: =SUM(H23:H24) -> 99741605 | I25: =SUM(I23:I24) -> 1.0130187e+08 | ... W25: =SUM(W23:W24) -> 1.0956986e+08 | X25: =E25 -> 96336079 | Y25: =Q25 -> 92984338 | Z25: =W25 -> 1.0956986e+08
A26: Liabilities and equity | B26: =B21+B25 -> 2.0167064e+08 | C26: =C21+C25 -> 2.0305044e+08 | D26: =D21+D25 -> 2.046469e+08 | E26: =E21+E25 -> 2.0258838e+08 | F26: =F21+F25 -> 2.0350638e+08 | G26: =G21+G25 -> 2.0420179e+08 | H26: =H21+H25 -> 2.0445039e+08 | I26: =I21+I25 -> 2.0575413e+08 | ... W26: =W21+W25 -> 2.0149191e+08 | X26: =E26 -> 2.0258838e+08 | Y26: =Q26 -> 1.9896517e+08 | Z26: =W26 -> 2.0149191e+08
A27: Balance Check (Total assets - Liabilities and equity) | B27: =B14-B26 -> 0 | C27: =C14-C26 -> 0 | D27: =D14-D26 -> 0 | E27: =E14-E26 -> 0 | F27: =F14-F26 -> 0 | G27: =G14-G26 -> 0 | H27: =H14-H26 -> 0 | I27: =I14-I26 -> 0 | ... W27: =W14-W26 -> 0 | X27: =E27 -> 0 | Y27: =Q27 -> 0 | Z27: =W27 -> 0
A29: DEBT & EQUITY ROLL-FORWARD (borrower-certified; source: monthly.xlsx 'Debt and Equity' tab)
A30: Beginning gross debt | B30: 59901433 | C30: 59482123 | D30: 59065749 | E30: 58652288 | F30: 58241722 | G30: 57834030 | H30: 57429192 | I30: 57027188 | J30: 56627997 | K30: 56231601 | L30: 55837980 | M30: 55447114 | N30: 55058985 | O30: 54673572 | P30: 54290857 | Q30: 53910821 | R30: 60910821 | S30: 60910821 | T30: 60910821 | U30: 51000000 | V30: 50949000 | W30: 50898051 | X30: =B30 -> 59901433 | Y30: =F30 -> 58241722 | Z30: =R30 -> 60910821
A31: Draws | B31: 0 | C31: 0 | D31: 0 | E31: 0 | F31: 0 | G31: 0 | H31: 0 | I31: 0 | J31: 0 | K31: 0 | L31: 0 | M31: 0 | N31: 0 | O31: 0 | P31: 0 | Q31: 7000000 | R31: 0 | S31: 0 | T31: 7000000 | U31: 0 | V31: 0 | W31: 0 | X31: =SUM(B31:E31) -> 0 | Y31: =SUM(F31:Q31) -> 7000000 | Z31: =SUM(R31:W31) -> 7000000
A32: Scheduled principal | B32: -419310.03 | C32: -416374.86 | D32: -413460.24 | E32: -410566.02 | F32: -407692.06 | G32: -404838.21 | H32: -402004.34 | I32: -399190.31 | J32: -396395.98 | K32: -393621.21 | L32: -390865.86 | M32: -388129.8 | N32: -385412.89 | O32: -382715 | P32: -380036 | Q32: 0 | R32: 0 | S32: 0 | T32: 0 | U32: -51000 | V32: -50949 | W32: -50898.05 | X32: =SUM(B32:E32) -> -1659711.1 | Y32: =SUM(F32:Q32) -> -4330901.7 | Z32: =SUM(R32:W32) -> -152847.05
A33: Predecessor payoff | B33: 0 | C33: 0 | D33: 0 | E33: 0 | F33: -57834030 | G33: 0 | H33: 0 | I33: 0 | J33: 0 | K33: 0 | L33: 0 | M33: 0 | N33: 0 | O33: 0 | P33: 0 | Q33: 0 | R33: 0 | S33: 0 | T33: 0 | U33: 0 | V33: 0 | W33: 0 | X33: =SUM(B33:E33) -> 0 | Y33: =SUM(F33:Q33) -> -57834030 | Z33: =SUM(R33:W33) -> 0
A34: Legacy facility funding | B34: 0 | C34: 0 | D34: 0 | E34: 0 | F34: 57834030 | G34: 0 | H34: 0 | I34: 0 | J34: 0 | K34: 0 | L34: 0 | M34: 0 | N34: 0 | O34: 0 | P34: 0 | Q34: 0 | R34: 0 | S34: 0 | T34: 0 | U34: 0 | V34: 0 | W34: 0 | X34: =SUM(B34:E34) -> 0 | Y34: =SUM(F34:Q34) -> 57834030 | Z34: =SUM(R34:W34) -> 0
A35: Debt converted to preferred | B35: 0 | C35: 0 | D35: 0 | E35: 0 | F35: 0 | G35: 0 | H35: 0 | I35: 0 | J35: 0 | K35: 0 | L35: 0 | M35: 0 | N35: 0 | O35: 0 | P35: 0 | Q35: 0 | R35: 0 | S35: 0 | T35: -16910821 | U35: 0 | V35: 0 | W35: 0 | X35: =SUM(B35:E35) -> 0 | Y35: =SUM(F35:Q35) -> 0 | Z35: =SUM(R35:W35) -> -16910821
A36: Ending gross debt | B36: =SUM(B30:B35) -> 59482123 | C36: =SUM(C30:C35) -> 59065749 | D36: =SUM(D30:D35) -> 58652288 | E36: =SUM(E30:E35) -> 58241722 | F36: =SUM(F30:F35) -> 57834030 | G36: =SUM(G30:G35) -> 57429192 | H36: =SUM(H30:H35) -> 57027188 | I36: =SUM(I30:I35) -> 56627997 | ... W36: =SUM(W30:W35) -> 50847153 | X36: =E36 -> 58241722 | Y36: =Q36 -> 60910821 | Z36: =W36 -> 50847153
A37: Unamortized debt issuance costs | B37: 0 | C37: 0 | D37: 0 | E37: 0 | F37: 0 | G37: 0 | H37: 0 | I37: 0 | J37: 0 | K37: 0 | L37: 0 | M37: 0 | N37: 0 | O37: 0 | P37: 0 | Q37: 0 | R37: 0 | S37: 0 | T37: -1200000 | U37: -1180000 | V37: -1160000 | W37: -1140000 | X37: =E37 -> 0 | Y37: =Q37 -> 0 | Z37: =W37 -> -1140000
A38: Carrying debt | B38: =B36+B37 -> 59482123 | C38: =C36+C37 -> 59065749 | D38: =D36+D37 -> 58652288 | E38: =E36+E37 -> 58241722 | F38: =F36+F37 -> 57834030 | G38: =G36+G37 -> 57429192 | H38: =H36+H37 -> 57027188 | I38: =I36+I37 -> 56627997 | ... W38: =W36+W37 -> 49707153 | X38: =E38 -> 58241722 | Y38: =Q38 -> 60910821 | Z38: =W38 -> 49707153
A40: COVENANT-SUPPORT ROWS (Fixed Charges inputs; certified Covenant Calculation exhibits -- see Sources & Notes)
A41: Facility Cash Interest Expense | B41: 574055.4 | C41: 570037.02 | D41: 566046.76 | E41: 562084.43 | F41: 558149.84 | G41: 554242.79 | H41: 550363.09 | I41: 546510.55 | J41: 542684.97 | K41: 538886.18 | L41: 535113.98 | M41: 531368.18 | N41: 527648.6 | O41: 523955.06 | P41: 520287.38 | Q41: 574784.25 | R41: 583728.7 | S41: 583728.7 | T41: 583728.7 | U41: 425000 | V41: 424575 | W41: 424150.43 | X41: =SUM(B41:E41) -> 2272223.6 | Y41: =SUM(F41:Q41) -> 6503994.9 | Z41: =SUM(R41:W41) -> 3024911.5
A42: Facility Scheduled Debt Principal Payments | B42: 419310.03 | C42: 416374.86 | D42: 413460.24 | E42: 410566.02 | F42: 407692.06 | G42: 404838.21 | H42: 402004.34 | I42: 399190.31 | J42: 396395.98 | K42: 393621.21 | L42: 390865.86 | M42: 388129.8 | N42: 385412.89 | O42: 382715 | P42: 380036 | Q42: 0 | R42: 0 | S42: 0 | T42: 0 | U42: 51000 | V42: 50949 | W42: 50898.05 | X42: =SUM(B42:E42) -> 1659711.1 | Y42: =SUM(F42:Q42) -> 4330901.7 | Z42: =SUM(R42:W42) -> 152847.05

Sheet Cash Flow Statement
A1: Asteron Care Partners, LLC | Detailed Cash Flow Statement (as reported)
A2: Company-prepared monthly reporting package | USD (whole dollars) | Unaudited, PROVISIONAL restructuring accounting through Jun 2026 -- see Sources & Notes | Source: monthly.xlsx, 'Cash Flow' tab
A6: Account | B6: Sep 2024 | C6: Oct 2024 | D6: Nov 2024 | E6: Dec 2024 | F6: Jan 2025 | G6: Feb 2025 | H6: Mar 2025 | I6: Apr 2025 | J6: May 2025 | K6: Jun 2025 | L6: Jul 2025 | M6: Aug 2025 | N6: Sep 2025 | O6: Oct 2025 | P6: Nov 2025 | Q6: Dec 2025 | R6: Jan 2026 | S6: Feb 2026 | T6: Mar 2026 | U6: Apr 2026 | V6: May 2026 | W6: Jun 2026 | X6: FY2024 (Sep-Dec, partial) | Y6: FY2025 | Z6: 2026 YTD (Jan-Jun)
A7: Beginning cash | B7: 9352790.8 | C7: 8238520.8 | D7: 8364065.5 | E7: 8968774.1 | F7: 10192084 | G7: 9490470.7 | H7: 9342106.6 | I7: 8319679.1 | J7: 8584491.8 | K7: 9061715.7 | L7: 8533476.1 | M7: 10150227 | N7: 8935807.8 | O7: 6951216.9 | P7: 5008900 | Q7: 3431896.4 | R7: 11012418 | S7: 9181041.2 | T7: 7684278.1 | U7: 18136709 | V7: 18140282 | W7: 18413087 | X7: =B7 -> 9352790.8 | Y7: =F7 -> 10192084 | Z7: =R7 -> 11012418
A8: Cash from operations | B8: 1062309 | C8: 2371458 | D8: 2896901.3 | E8: 3240621.6 | F8: 1405779.9 | G8: 1986123.5 | H8: 1170536.2 | I8: 2496105.1 | J8: 2746929.5 | K8: 1771945.5 | L8: 2228724.3 | M8: -612745.08 | N8: -1380923.7 | O8: -1332911.8 | P8: -962576.69 | Q8: 920196.69 | R8: -1635328.3 | S8: -1297667.9 | T8: -3141099.4 | U8: 282362.15 | V8: 555510.27 | W8: 692217.27 | X8: =SUM(B8:E8) -> 9571289.9 | Y8: =SUM(F8:Q8) -> 10437184 | Z8: =SUM(R8:W8) -> -4544005.9
A9: Cash from investing | B9: -1757268.9 | C9: -1829538.5 | D9: -1878732.6 | E9: -1606745.4 | F9: -1699701.4 | G9: -1729649.4 | H9: -1790959.4 | I9: -1832102.1 | J9: -1873309.7 | K9: -1906563.9 | L9: -221107.17 | M9: -213544.7 | N9: -218254.22 | O9: -226690.09 | P9: -234390.94 | Q9: -199675.03 | R9: -196048.49 | S9: -199095.17 | T9: -206469.83 | U9: -227788.7 | V9: -231756.3 | W9: -236962.8 | X9: =SUM(B9:E9) -> -7072285.4 | Y9: =SUM(F9:Q9) -> -12145948 | Z9: =SUM(R9:W9) -> -1298121.3
A10: Cash from financing | B10: -419310.03 | C10: -416374.86 | D10: -413460.24 | E10: -410566.02 | F10: -407692.06 | G10: -404838.21 | H10: -402004.34 | I10: -399190.31 | J10: -396395.98 | K10: -393621.21 | L10: -390865.86 | M10: -388129.8 | N10: -385412.89 | O10: -382715 | P10: -380036 | Q10: 6860000 | R10: 0 | S10: 0 | T10: 13800000 | U10: -51000 | V10: -50949 | W10: -50898.05 | X10: =SUM(B10:E10) -> -1659711.1 | Y10: =SUM(F10:Q10) -> 2529098.3 | Z10: =SUM(R10:W10) -> 13647153
A11: Ending cash | B11: =B7+B8+B9+B10 -> 8238520.8 | C11: =C7+C8+C9+C10 -> 8364065.5 | D11: =D7+D8+D9+D10 -> 8968774.1 | E11: =E7+E8+E9+E10 -> 10192084 | F11: =F7+F8+F9+F10 -> 9490470.7 | G11: =G7+G8+G9+G10 -> 9342106.6 | H11: =H7+H8+H9+H10 -> 8319679.1 | I11: =I7+I8+I9+I10 -> 8584491.8 | ... W11: =W7+W8+W9+W10 -> 18817444 | X11: =E11 -> 10192084 | Y11: =Q11 -> 11012418 | Z11: =W11 -> 18817444
A13: Memo: Cash per Balance Sheet | B13: ='Balance Sheet'!B7 -> 8238520.8 | C13: ='Balance Sheet'!C7 -> 8364065.5 | D13: ='Balance Sheet'!D7 -> 8968774.1 | E13: ='Balance Sheet'!E7 -> 10192084 | F13: ='Balance Sheet'!F7 -> 9490470.7 | G13: ='Balance Sheet'!G7 -> 9342106.6 | H13: ='Balance Sheet'!H7 -> 8319679.1 | I13: ='Balance Sheet'!I7 -> 8584491.8 | ... W13: ='Balance Sheet'!W7 -> 18817444 | X13: =E13 -> 10192084 | Y13: =Q13 -> 11012418 | Z13: =W13 -> 18817444
A14: Memo: CF-vs-BS cash tie (diff, should be 0) | B14: =B11-B13 -> 0 | C14: =C11-C13 -> 0 | D14: =D11-D13 -> 0 | E14: =E11-E13 -> 0 | F14: =F11-F13 -> 0 | G14: =G11-G13 -> 0 | H14: =H11-H13 -> 0 | I14: =I11-I13 -> 0 | ... W14: =W11-W13 -> 0 | X14: =E14 -> 0 | Y14: =Q14 -> 0 | Z14: =W14 -> 0
A15: Memo: Net income (per Income Statement) | B15: ='Income Statement'!B24 -> 1134639.6 | C15: ='Income Statement'!C24 -> 1472458.2 | D15: ='Income Statement'!D24 -> 1697871.7 | E15: ='Income Statement'!E24 -> 358381.33 | F15: ='Income Statement'!F24 -> 950185.61 | G15: ='Income Statement'!G24 -> 1083964.5 | H15: ='Income Statement'!H24 -> 1371375.9 | I15: ='Income Statement'!I24 -> 1560261.8 | ... W15: ='Income Statement'!W24 -> 84810.69 | X15: =SUM(B15:E15) -> 4663350.8 | Y15: =SUM(F15:Q15) -> -3351740.5 | Z15: =SUM(R15:W15) -> -8325302

Sheet Sources & Notes
A1: Entity | B1: Asteron Care Partners, LLC (consolidated) -- per borrower-config model.entity='consolidated'. No separate divisional/standalone consolidation level is offered in the reporting package.
A2: Units | B2: USD, whole dollars (model.scale = 1). Verified against June 2026 revenue ($13,164,599.73) and the Approved Stabilization Budget's own June 2026 figure, same unit; no '$ in thousands' caption anywhere in the source workbooks.
A3: Basis | B3: Actuals only -- company-prepared monthly reporting packages (Successor Reporting), unaudited. No proforma/budget/forecast columns included. Every monthly package's own 'Status' tab through June 2026 marks the P&L/BS/CF as PROVISIONAL (TDR framework, instrument-level 10% modification test, CODI, Section 382, and goodwill interim reassessment all remain open) -- successor Balance Sheet, gain/loss, and debt carrying-value figures could still restate once those workpapers conclude.
A4: Coverage | B4: Sep 2024 through Jun 2026 (22 months), matching every monthly subfolder present in Successor Reporting (Archive/<YYYY-MM>/ for Sep 2024-May 2026; <YYYY>/<MM>/ for Jun 2026), continuous, no gaps.
A5: Primary source files | B5: One monthly.xlsx package per reporting period (Successor Reporting is a continuously-used MONTHLY folder despite its name, spanning both the predecessor/legacy and successor eras). Each month's own package is a single-period snapshot (no hidden multi-month columns, no separate consolidated by-month/YTD file exists anywhere in the deal folder) -- so each ISO month's figures are sourced to that month's own monthly.xlsx (see source-map.json for the exact file per statement per month).
A6: Restatement scan | B6: Full scan performed: compared every month's own package against (a) any other package claiming to cover the same period and (b) any consolidated/by-month/YTD file -- neither exists anywhere in Successor Reporting or the wider Asteron deal folder for this borrower (unlike the Nemeris original/corrected-pair pattern). Each of the 22 months is reported exactly once, by exactly one file. Result: ZERO restatements found. restatements.json is written empty (schema present, zero entries).
A7: Income Statement -- two derived rows | B7: 'Cost of Patient Services' and 'Gross Profit' do NOT exist verbatim on the borrower's own Income Statement (it goes straight from Revenue and four direct-cost lines to 'Reported EBITDA'). Per borrower-config.json paths._model_lines_construction_note, these two rows are INSERTED as live formulas: Cost of Patient Services = SUM(Direct clinical labor, Contract labor, Medical supplies, Other patient service costs) [already-negative lines]; Gross Profit = Revenue + Cost of Patient Services. Independently re-verified against June 2026 to the penny: Revenue 13,164,599.73 + Cost of Patient Services (8,754,304.34) = Gross Profit 4,410,295.39; Gross Profit - Occupancy and site costs 1,557,912.45 - Corporate and administrative costs 1,304,641.66 = 1,547,741.28 = Reported EBITDA, tying exactly. The same two formulas were checked to foot for all 22 months with zero exceptions (see validation notes below).
A8: Income Statement -- subtotals as formulas | B8: Per build convention, 'Reported EBITDA' and 'Net income' are live formulas (Reported EBITDA = Gross Profit + Occupancy and site costs + Corporate and administrative costs; Net income = Reported EBITDA + Depreciation + Cash interest + Debt issuance cost amortization + Restructuring advisory expense + Income tax expense + Bridge upfront fee + Goodwill impairment), not hardcoded copies of the source subtotal -- both tie to the source's own printed subtotal in all 22 months to the penny, confirming the source data foots throughout the predecessor / legacy / exit-amendment / A&R eras alike.
A9: EBITDA bridge | B9: Per covenant-spec.json#/definitions/EBITDA, compute.ebitda_bridge = 'Reported EBITDA' -- the model's own single pinned EBITDA row, taken AS PARSED (no add-back folded in). covenant-spec.json's step7_signoff explicitly EXCLUDES the constant $553,353.26/month gap between this Reported EBITDA and the borrower's own certified 'Covenant EBITDA' (Covenant Calculation.xlsx TTM Detail), because no executed document supports that add-back in words. This EBITDA bridge is therefore NOT provisional in the sense of 'no covenant spec' -- it is the spec-directed definition -- but the reader should know the FCCR covenant (the only covenant that reads this EBITDA) runs materially below the borrower's own certified figure as a structural, documented, and currently-immaterial-because-suspended gap.
A10: Covenant-support rows -- CERTIFICATE OVERRIDE (per covenant-spec.json step7_signoff 'amortization_day_count_approximation') | B10: 'Facility Cash Interest Expense' and 'Facility Scheduled Debt Principal Payments' are the two rows debt-service-spec.json's covenant_support_rows names for Fixed_Charges. debt-service-schedule.json (generated engine output) only models the CURRENT A&R facility from its 2026-03-31 funding forward, and is known to use a flat/approximate day-count and amortization-base convention that does NOT reproduce the borrower's certified figures even within its own modeled range (documented in debt-service-spec.json's day_count.ambiguities: e.g. generated June 2026 cash interest 423,725.00 vs. certified 424,150.43). Per the covenant-spec's step7_signoff decision, BOTH rows are instead populated for ALL 22 months directly from the borrower's own CERTIFIED Portfolio Monitoring/<quarter>/Covenant Calculation.xlsx 'TTM Detail' exhibits (Cash interest / Principal columns), which -- because six overlapping quarterly certificates (2025-Q1 through 2026-Q2) together span 2024-04 through 2026-06 continuously -- cover every one of this model's 22 months with ZERO gaps and ZERO cross-quarter conflicts (every month that appears in more than one quarter's TTM Detail carries an identical figure to the penny). The generated debt-service-schedule.json was therefore NOT used as a fallback source for any month in this build -- certified figures alone were sufficient for the model's full Sep 2024-Jun 2026 range. Note the certified figures span the predecessor (11.50%/0.70%-month), legacy (same economics), Exit Amendment bridge (11.50% interest-only, hence Principal = 0.00 for Dec 2025-Mar 2026), and A&R (10.00%/0.10%-month, effective Apr 2026) facilities in turn -- each period's own contractual debt service, not a single facility's figure held constant. No non-facility scheduled debt (vehicle loans, SBA notes, etc.) is disclosed anywhere in the deal folder for this borrower, so nothing is added to the principal row beyond the certified facility figure.
A11: Balance Sheet -- carryover accounting | B11: Per covenant-spec.json accounting_basis and borrower-config.json paths._restructuring_timeline_note, the successor balance sheet (Apr 2026 forward per borrower-config.json analysis.basis_breaks) uses CARRYOVER (historical-cost) accounting, NOT a fresh-start/revalued basis -- confirmed against the IC Memo's 'ACCOUNTING STATUS' section. TDR framework selection, the instrument-level 10% modification test, CODI, and Section 382 conclusions all remain PENDING as of the June 2026 package; successor Balance Sheet figures could still restate.
A12: Balance Sheet -- no current/non-current subtotal, no inventory | B12: Per borrower-config.json analysis_lines._omitted_note: the Balance Sheet carries a flat asset/liability list with no Total Current Assets/Total Current Liabilities subtotal and no inventory line (healthcare-services business); neither is invented here. current_ratio/working-capital/DIO ratios will be suppressed downstream with a disclosed reason.
... A18: Build tool / recalc | B18: Built with openpyxl; formula cells recalculated (cached values populated) via headless LibreOffice as the LAST write, per assembling-rules.md. Gated with references/validate_model.py before becoming canonical.
