Workbook

Sheet Income Statement
A1: Nemeris Field Systems, LLC | Detailed Income Statement
A2: Management accounts | USD (whole dollars) | Unaudited | Source: borrower Monthly Financial Package, Income Statement tab
A6: Account | B6: Apr 2024 | C6: May 2024 | D6: Jun 2024 | E6: Jul 2024 | F6: Aug 2024 | G6: Sep 2024 | H6: Oct 2024 | I6: Nov 2024 | J6: Dec 2024 | K6: Jan 2025 | L6: Feb 2025 | M6: Mar 2025 | N6: Apr 2025 | O6: May 2025 | P6: Jun 2025 | Q6: Jul 2025 | R6: Aug 2025 | S6: Sep 2025 | T6: Oct 2025 | U6: Nov 2025 | V6: Dec 2025 | W6: Jan 2026 | X6: Feb 2026 | Y6: Mar 2026 | Z6: Apr 2026 | AA6: May 2026 | AB6: Jun 2026 | AC6: FY2024 (Apr-Dec, partial) | AD6: FY2025 | AE6: 2026 YTD (Jan-Jun)
A7: NET REVENUE
A8: Ruggedized Tool Systems | B8: 2764275 | C8: 2823977.1 | D8: 2897349 | E8: 2765556.2 | F8: 2728776.1 | G8: 2706531.7 | H8: 2871565.2 | I8: 3031042.2 | J8: 2605567 | K8: 2654133.6 | L8: 2741863.1 | M8: 2823483.1 | N8: 2842555.7 | O8: 2957368 | P8: 2958488.3 | Q8: 2927990.5 | R8: 2886796.8 | S8: 2882796.7 | T8: 2986376.1 | U8: 3014047.9 | V8: 2561831.8 | W8: 2752090.7 | X8: 2801861.2 | Y8: 2841938 | Z8: 2899738.7 | AA8: 2965665.5 | AB8: 2966717.5 | AC8: =SUM(B8:J8) -> 25194640 | AD8: =SUM(K8:V8) -> 34237731 | AE8: =SUM(W8:AB8) -> 17228011
A9: Diagnostic Units | B9: 1783403.3 | C9: 1821920.7 | D9: 1869257.4 | E9: 1784229.8 | F9: 1760500.7 | G9: 1746149.5 | H9: 1852622.7 | I9: 1955511.1 | J9: 1681011 | K9: 1712344.2 | L9: 1768943.9 | M9: 1821602 | N9: 1833906.9 | O9: 1907979.3 | P9: 1908702.1 | Q9: 1889026.1 | R9: 1862449.5 | S9: 1859868.9 | T9: 1926694.3 | U9: 1944547 | V9: 1652794.7 | W9: 1775542.4 | X9: 1807652.4 | Y9: 1833508.4 | Z9: 1870799.1 | AA9: 1913332.6 | AB9: 1914011.3 | AC9: =SUM(B9:J9) -> 16254606 | AD9: =SUM(K9:V9) -> 22088859 | AE9: =SUM(W9:AB9) -> 11114846
A10: Replacement Components | B10: 1515892.8 | C10: 1548632.6 | D10: 1588868.8 | E10: 1516595.4 | F10: 1496425.6 | G10: 1484227.1 | H10: 1574729.3 | I10: 1662184.4 | J10: 1428859.3 | K10: 1455492.6 | L10: 1503602.3 | M10: 1548361.7 | N10: 1558820.9 | O10: 1621782.4 | P10: 1622396.8 | Q10: 1605672.2 | R10: 1583082.1 | S10: 1580888.5 | T10: 1637690.1 | U10: 1652865 | V10: 1404875.5 | W10: 1509211 | X10: 1536504.5 | Y10: 1558482.1 | Z10: 1590179.3 | AA10: 1626332.7 | AB10: 1626909.6 | AC10: =SUM(B10:J10) -> 13816415 | AD10: =SUM(K10:V10) -> 18775530 | AE10: =SUM(W10:AB10) -> 9447619.2
A11: Preventive Maintenance Plans | B11: 1337552.4 | C11: 1366440.6 | D11: 1401943.1 | E11: 1338172.4 | F11: 1320375.6 | G11: 1309612.1 | H11: 1389467.1 | I11: 1466633.3 | J11: 1260758.2 | K11: 1284258.2 | L11: 1326707.9 | M11: 1366201.5 | N11: 1375430.2 | O11: 1430984.5 | P11: 1431526.6 | Q11: 1416769.6 | R11: 1396837.1 | S11: 1394901.6 | T11: 1445020.7 | U11: 1458410.2 | V11: 1239596 | W11: 1331656.8 | X11: 1355739.3 | Y11: 1375131.3 | Z11: 1403099.4 | AA11: 1434999.4 | AB11: 1435508.4 | AC11: =SUM(B11:J11) -> 12190955 | AD11: =SUM(K11:V11) -> 16566644 | AE11: =SUM(W11:AB11) -> 8336134.6
A12: Calibration Services | B12: 891701.63 | C12: 910960.36 | D12: 934628.73 | E12: 892114.92 | F12: 880250.37 | G12: 873074.74 | H12: 926311.37 | I12: 977755.55 | J12: 840505.49 | K12: 856172.12 | L12: 884471.96 | M12: 910801 | N12: 916953.46 | O12: 953989.67 | P12: 954351.06 | Q12: 944513.06 | R12: 931224.77 | S12: 929934.43 | T12: 963347.13 | U12: 972273.5 | V12: 826397.35 | W12: 887771.18 | X12: 903826.18 | Y12: 916754.18 | Z12: 935399.57 | AA12: 956666.3 | AB12: 957005.64 | AC12: =SUM(B12:J12) -> 8127303.2 | AD12: =SUM(K12:V12) -> 11044430 | AE12: =SUM(W12:AB12) -> 5557423
A13: Field Support & Training | B13: 624191.14 | C13: 637672.25 | D13: 654240.11 | E13: 624480.44 | F13: 616175.25 | G13: 611152.33 | H13: 648417.96 | I13: 684428.89 | J13: 588353.84 | K13: 599320.48 | L13: 619130.36 | M13: 637560.7 | N13: 641867.41 | O13: 667792.77 | P13: 668045.74 | Q13: 661159.14 | R13: 651857.34 | S13: 650954.1 | T13: 674342.99 | U13: 680591.45 | V13: 578478.15 | W13: 621439.83 | X13: 632678.33 | Y13: 641727.92 | Z13: 654779.7 | AA13: 669666.41 | AB13: 669903.95 | AC13: =SUM(B13:J13) -> 5689112.2 | AD13: =SUM(K13:V13) -> 7731100.6 | AE13: =SUM(W13:AB13) -> 3890196.1
A14: Net Revenue | B14: =SUM(B8:B13) -> 8917016.3 | C14: =SUM(C8:C13) -> 9109603.6 | D14: =SUM(D8:D13) -> 9346287.3 | E14: =SUM(E8:E13) -> 8921149.2 | F14: =SUM(F8:F13) -> 8802503.7 | G14: =SUM(G8:G13) -> 8730747.4 | H14: =SUM(H8:H13) -> 9263113.7 | I14: =SUM(I8:I13) -> 9777555.5 | ... AB14: =SUM(AB8:AB13) -> 9570056.4 | AC14: =SUM(B14:J14) -> 81273032 | AD14: =SUM(K14:V14) -> 1.104443e+08 | AE14: =SUM(W14:AB14) -> 55574230
A16: COST OF REVENUE
A17: Equipment and component purchases | B17: 1870600.9 | C17: 1855166.2 | D17: 1898825.7 | E17: 1852463.1 | F17: 1760714.1 | G17: 1782906.8 | H17: 1901661.1 | I17: 2010927.1 | J17: 1761317.5 | K17: 1766949 | L17: 1800561.6 | M17: 1816716.8 | N17: 1883820.7 | O17: 1955987.2 | P17: 1892883 | Q17: 1922437.1 | R17: 1938894.6 | S17: 1886855.8 | T17: 1970492.5 | U17: 2031265.9 | V17: 1683262.9 | W17: 1826853.7 | X17: 1876781.4 | Y17: 1870391.5 | Z17: 1880115.4 | AA17: 1947531 | AB17: 1949652.5 | AC17: =SUM(B17:J17) -> 16694582 | AD17: =SUM(K17:V17) -> 22550127 | AE17: =SUM(W17:AB17) -> 11351325
A18: Direct field labor | B18: 1112249.2 | C18: 1103071.8 | D18: 1129031.5 | E18: 1101464.6 | F18: 1046911.1 | G18: 1060106.8 | H18: 1130717.4 | I18: 1195686.4 | J18: 1047269.8 | K18: 1050618.3 | L18: 1070604.2 | M18: 1080210 | N18: 1120109.6 | O18: 1163019.4 | P18: 1125498 | Q18: 1143070.7 | R18: 1152856.3 | S18: 1121914.2 | T18: 1171644.2 | U18: 1207779.8 | V18: 1000859 | W18: 1086237.4 | X18: 1115924.1 | Y18: 1112124.7 | Z18: 1117906.4 | AA18: 1157991.4 | AB18: 1159252.8 | AC18: =SUM(B18:J18) -> 9926508.5 | AD18: =SUM(K18:V18) -> 13408184 | AE18: =SUM(W18:AB18) -> 6749436.8
A19: Freight and logistics | B19: 530846.19 | C19: 526466.08 | D19: 538855.94 | E19: 525698.99 | F19: 499662.12 | G19: 505960.04 | H19: 539660.58 | I19: 570668.51 | J19: 499833.33 | K19: 501431.47 | L19: 510970.17 | M19: 515554.77 | N19: 534597.76 | O19: 555077.44 | P19: 537169.51 | Q19: 545556.47 | R19: 550226.85 | S19: 535459.06 | T19: 559193.82 | U19: 576440.34 | V19: 477682.71 | W19: 518431.47 | X19: 532600.12 | Y19: 530786.78 | Z19: 533546.25 | AA19: 552677.71 | AB19: 553279.76 | AC19: =SUM(B19:J19) -> 4737651.8 | AD19: =SUM(K19:V19) -> 6399360.4 | AE19: =SUM(W19:AB19) -> 3221322.1
A20: Warranty and refurbishment | B20: 429732.63 | C20: 426186.82 | D20: 436216.72 | E20: 425565.85 | F20: 404488.38 | G20: 409586.7 | H20: 436868.09 | I20: 461969.74 | J20: 404626.98 | K20: 405920.71 | L20: 413642.52 | M20: 417353.86 | N20: 432769.61 | O20: 449348.41 | P20: 434851.51 | Q20: 441640.95 | R20: 445421.74 | S20: 433466.86 | T20: 452680.71 | U20: 466642.18 | V20: 386695.53 | W20: 419682.62 | X20: 431152.48 | Y20: 429684.54 | Z20: 431918.39 | AA20: 447405.77 | AB20: 447893.14 | AC20: =SUM(B20:J20) -> 3835241.9 | AD20: =SUM(K20:V20) -> 5180434.6 | AE20: =SUM(W20:AB20) -> 2607736.9
A21: Service parts consumption | B21: 581402.97 | C21: 576605.7 | D21: 590175.56 | E21: 575765.56 | F21: 547248.99 | G21: 554146.71 | H21: 591056.83 | I21: 625017.89 | J21: 547436.51 | K21: 549186.85 | L21: 559634 | M21: 564655.22 | N21: 585511.83 | O21: 607941.96 | P21: 588328.51 | Q21: 597514.23 | R21: 602629.41 | S21: 586455.17 | T21: 612450.37 | U21: 631339.42 | V21: 523176.3 | W21: 567805.89 | X21: 583323.94 | Y21: 581337.9 | Z21: 584360.18 | AA21: 605313.69 | AB21: 605973.07 | AC21: =SUM(B21:J21) -> 5188856.7 | AD21: =SUM(K21:V21) -> 7008823.3 | AE21: =SUM(W21:AB21) -> 3528114.7
A22: Other direct costs | B22: 480289.42 | C22: 476326.46 | D22: 487536.33 | E22: 475632.43 | F22: 452075.25 | G22: 457773.37 | H22: 488264.33 | I22: 516319.13 | J22: 452230.16 | K22: 453676.1 | L22: 462306.34 | M22: 466454.31 | N22: 483683.69 | O22: 502212.92 | P22: 486010.49 | Q22: 493598.71 | R22: 497824.29 | S22: 484462.97 | T22: 505937.27 | U22: 521541.24 | V22: 432189.12 | W22: 469057.04 | X22: 481876.29 | Y22: 480235.66 | Z22: 482732.32 | AA22: 500041.75 | AB22: 500586.44 | AC22: =SUM(B22:J22) -> 4286446.9 | AD22: =SUM(K22:V22) -> 5789897.5 | AE22: =SUM(W22:AB22) -> 2914529.5
A23: Cost of Revenue | B23: =SUM(B17:B22) -> 5005121.2 | C23: =SUM(C17:C22) -> 4963823 | D23: =SUM(D17:D22) -> 5080641.8 | E23: =SUM(E17:E22) -> 4956590.5 | F23: =SUM(F17:F22) -> 4711100 | G23: =SUM(G17:G22) -> 4770480.4 | H23: =SUM(H17:H22) -> 5088228.3 | I23: =SUM(I17:I22) -> 5380588.8 | ... AB23: =SUM(AB17:AB22) -> 5216637.7 | AC23: =SUM(B23:J23) -> 44669288 | AD23: =SUM(K23:V23) -> 60336826 | AE23: =SUM(W23:AB23) -> 30372465
A24: Gross Profit | B24: =B14-B23 -> 3911895 | C24: =C14-C23 -> 4145780.6 | D24: =D14-D23 -> 4265645.5 | E24: =E14-E23 -> 3964558.7 | F24: =F14-F23 -> 4091403.7 | G24: =G14-G23 -> 3960267 | H24: =H14-H23 -> 4174885.3 | I24: =I14-I23 -> 4396966.7 | ... AB24: =AB14-AB23 -> 4353418.6 | AC24: =SUM(B24:J24) -> 36603743 | AD24: =SUM(K24:V24) -> 50107469 | AE24: =SUM(W24:AB24) -> 25201765
A25: Gross Margin | B25: =IF(B14=0,"",B24/B14) -> 0.4387 | C25: =IF(C14=0,"",C24/C14) -> 0.4551 | D25: =IF(D14=0,"",D24/D14) -> 0.4564 | E25: =IF(E14=0,"",E24/E14) -> 0.4444 | F25: =IF(F14=0,"",F24/F14) -> 0.4648 | G25: =IF(G14=0,"",G24/G14) -> 0.4536 | H25: =IF(H14=0,"",H24/H14) -> 0.4507 | I25: =IF(I14=0,"",I24/I14) -> 0.4497 | ... AB25: =IF(AB14=0,"",AB24/AB14) -> 0.4549 | AC25: =AC24/AC14 -> 0.45037994 | AD25: =AD24/AD14 -> 0.45368997 | AE25: =AE24/AE14 -> 0.45347934
A27: OPERATING EXPENSES
A28: Sales compensation | B28: 368547.78 | C28: 376605.6 | D28: 385435.09 | E28: 368620.11 | F28: 371231.35 | G28: 374663.14 | H28: 374604.49 | I28: 388294.75 | J28: 368963.52 | K28: 362330.12 | L28: 371970.12 | M28: 381265.24 | N28: 372966.86 | O28: 384135.72 | P28: 388886.5 | Q28: 377789.79 | R28: 380151.86 | S28: 384613.59 | T28: 381085.75 | U28: 387335.39 | V28: 366494.6 | W28: 367859.96 | X28: 375357.11 | Y28: 382307.04 | Z28: 376194.92 | AA28: 384604.13 | AB28: 389351.05 | AC28: =SUM(B28:J28) -> 3376965.8 | AD28: =SUM(K28:V28) -> 4539025.5 | AE28: =SUM(W28:AB28) -> 2275674.2
A29: Marketing programs | B29: 141522.35 | C29: 144616.55 | D29: 148007.07 | E29: 141550.12 | F29: 142552.84 | G29: 143870.65 | H29: 143848.12 | I29: 149105.18 | J29: 141681.99 | K29: 139134.77 | L29: 142836.53 | M29: 146405.85 | N29: 143219.27 | O29: 147508.12 | P29: 149332.42 | Q29: 145071.28 | R29: 145978.32 | S29: 147691.62 | T29: 146336.93 | U29: 148736.79 | V29: 140733.93 | W29: 141258.22 | X29: 144137.13 | Y29: 146805.9 | Z29: 144458.85 | AA29: 147687.99 | AB29: 149510.8 | AC29: =SUM(B29:J29) -> 1296754.9 | AD29: =SUM(K29:V29) -> 1742985.8 | AE29: =SUM(W29:AB29) -> 873858.89
A30: Operations payroll | B30: 551347.49 | C30: 563401.97 | D30: 576610.89 | E30: 551455.69 | F30: 555362.09 | G30: 560496.06 | H30: 560408.32 | I30: 580888.95 | J30: 551969.43 | K30: 542045.86 | L30: 556467.31 | M30: 570372.8 | N30: 557958.42 | O30: 574667.04 | P30: 581774.2 | Q30: 565173.52 | R30: 568707.19 | S30: 575381.93 | T30: 570104.28 | U30: 579453.75 | V30: 548275.92 | W30: 550318.49 | X30: 561534.24 | Y30: 571931.34 | Z30: 562787.61 | AA30: 575367.78 | AB30: 582469.17 | AC30: =SUM(B30:J30) -> 5051940.9 | AD30: =SUM(K30:V30) -> 6790382.2 | AE30: =SUM(W30:AB30) -> 3404408.6
A31: Product and engineering | B31: 333167.2 | C31: 340451.46 | D31: 348433.32 | E31: 333232.58 | F31: 335593.14 | G31: 338695.48 | H31: 338642.46 | I31: 351018.46 | J31: 333543.02 | K31: 327546.43 | L31: 336260.99 | M31: 344663.77 | N31: 337162.04 | O31: 347258.69 | P31: 351553.39 | Q31: 341521.97 | R31: 343657.29 | S31: 347690.68 | T31: 344501.52 | U31: 350151.2 | V31: 331311.12 | W31: 332545.4 | X31: 339322.83 | Y31: 345605.57 | Z31: 340080.21 | AA31: 347682.14 | AB31: 351973.35 | AC31: =SUM(B31:J31) -> 3052777.1 | AD31: =SUM(K31:V31) -> 4103279.1 | AE31: =SUM(W31:AB31) -> 2057209.5
A32: Corporate payroll | B32: 507121.75 | C32: 518209.3 | D32: 530358.68 | E32: 507221.27 | F32: 510814.33 | G32: 515536.48 | H32: 515455.78 | I32: 534293.58 | J32: 507693.81 | K32: 498566.25 | L32: 511830.89 | M32: 524620.97 | N32: 513202.39 | O32: 528570.75 | P32: 535107.82 | Q32: 519838.75 | R32: 523088.97 | S32: 529228.3 | T32: 524373.99 | U32: 532973.5 | V32: 504296.57 | W32: 506175.3 | X32: 516491.39 | Y32: 526054.49 | Z32: 517644.22 | AA32: 529215.29 | AB32: 535747.04 | AC32: =SUM(B32:J32) -> 4646705 | AD32: =SUM(K32:V32) -> 6245699.2 | AE32: =SUM(W32:AB32) -> 3131327.7
A33: Facilities and occupancy | B33: 241767.35 | C33: 247053.27 | D33: 252845.42 | E33: 241814.79 | F33: 243527.76 | G33: 245779.02 | H33: 245740.54 | I33: 254721.36 | J33: 242040.07 | K33: 237688.56 | L33: 244012.4 | M33: 250110 | N33: 244666.26 | O33: 251993.03 | P33: 255109.54 | Q33: 247830.1 | R33: 249379.62 | S33: 252306.51 | T33: 249992.25 | U33: 254092.02 | V33: 240420.46 | W33: 241316.13 | X33: 246234.27 | Y33: 250793.42 | Z33: 246783.87 | AA33: 252300.31 | AB33: 255414.29 | AC33: =SUM(B33:J33) -> 2215289.6 | AD33: =SUM(K33:V33) -> 2977600.8 | AE33: =SUM(W33:AB33) -> 1492842.3
A34: Technology and communications | B34: 203438.38 | C34: 207886.29 | D34: 212760.17 | E34: 203478.3 | F34: 204919.7 | G34: 206814.05 | H34: 206781.68 | I34: 214338.7 | J34: 203667.86 | K34: 200006.23 | L34: 205327.51 | M34: 210458.41 | N34: 205877.7 | O34: 212042.92 | P34: 214665.35 | Q34: 208539.96 | R34: 209843.83 | S34: 212306.7 | T34: 210359.33 | U34: 213809.14 | V34: 202305.02 | W34: 203058.7 | X34: 207197.13 | Y34: 211033.49 | Z34: 207659.6 | AA34: 212301.48 | AB34: 214921.78 | AC34: =SUM(B34:J34) -> 1864085.1 | AD34: =SUM(K34:V34) -> 2505542.1 | AE34: =SUM(W34:AB34) -> 1256172.2
A35: Insurance | B35: 109090.14 | C35: 111475.26 | D35: 114088.79 | E35: 109111.55 | F35: 109884.48 | G35: 110900.29 | H35: 110882.93 | I35: 114935.25 | J35: 109213.2 | K35: 107249.72 | L35: 110103.16 | M35: 112854.51 | N35: 110398.19 | O35: 113704.17 | P35: 115110.4 | Q35: 111825.78 | R35: 112524.95 | S35: 113845.62 | T35: 112801.38 | U35: 114651.28 | V35: 108482.4 | W35: 108886.55 | X35: 111105.71 | Y35: 113162.88 | Z35: 111353.7 | AA35: 113842.82 | AB35: 115247.91 | AC35: =SUM(B35:J35) -> 999581.89 | AD35: =SUM(K35:V35) -> 1343551.6 | AE35: =SUM(W35:AB35) -> 673599.57
A36: Professional fees | B36: 179851.32 | C36: 183783.53 | D36: 188092.32 | E36: 179886.61 | F36: 181160.9 | G36: 182835.61 | H36: 182806.99 | I36: 189487.84 | J36: 180054.2 | K36: 176817.1 | L36: 181521.42 | M36: 186057.44 | N36: 182007.83 | O36: 187458.23 | P36: 189776.61 | Q36: 184361.42 | R36: 185514.11 | S36: 187691.43 | T36: 185969.85 | U36: 189019.67 | V36: 178849.36 | W36: 179515.66 | X36: 183174.27 | Y36: 186565.84 | Z36: 183583.12 | AA36: 187686.82 | AB36: 190003.31 | AC36: =SUM(B36:J36) -> 1647959.3 | AD36: =SUM(K36:V36) -> 2215044.5 | AE36: =SUM(W36:AB36) -> 1110529
A37: Travel and training | B37: 120883.67 | C37: 123526.64 | D37: 126422.71 | E37: 120907.4 | F37: 121763.88 | G37: 122889.51 | H37: 122870.27 | I37: 127360.68 | J37: 121020.04 | K37: 118844.28 | L37: 122006.2 | M37: 125055 | N37: 122333.13 | O37: 125996.52 | P37: 127554.77 | Q37: 123915.05 | R37: 124689.81 | S37: 126153.26 | T37: 124996.13 | U37: 127046.01 | V37: 120210.23 | W37: 120658.07 | X37: 123117.13 | Y37: 125396.71 | Z37: 123391.94 | AA37: 126150.16 | AB37: 127707.14 | AC37: =SUM(B37:J37) -> 1107644.8 | AD37: =SUM(K37:V37) -> 1488800.4 | AE37: =SUM(W37:AB37) -> 746421.15
A38: Other operating expense | B38: 191644.85 | C38: 195834.89 | D38: 200426.26 | E38: 191682.47 | F38: 193040.3 | G38: 194824.85 | H38: 194794.33 | I38: 201913.27 | J38: 191861.04 | K38: 188411.65 | L38: 193424.46 | M38: 198257.91 | N38: 193942.75 | O38: 199750.59 | P38: 202220.98 | Q38: 196450.67 | R38: 197678.97 | S38: 199999.07 | T38: 198164.58 | U38: 201414.4 | V38: 190577.18 | W38: 191287.17 | X38: 195185.69 | Y38: 198799.67 | Z38: 195621.36 | AA38: 199994.14 | AB38: 202462.55 | AC38: =SUM(B38:J38) -> 1756022.3 | AD38: =SUM(K38:V38) -> 2360293.2 | AE38: =SUM(W38:AB38) -> 1183350.6
A39: Operating Expenses | B39: =SUM(B28:B38) -> 2948382.3 | C39: =SUM(C28:C38) -> 3012844.8 | D39: =SUM(D28:D38) -> 3083480.7 | E39: =SUM(E28:E38) -> 2948960.9 | F39: =SUM(F28:F38) -> 2969850.8 | G39: =SUM(G28:G38) -> 2997305.1 | H39: =SUM(H28:H38) -> 2996835.9 | I39: =SUM(I28:I38) -> 3106358 | ... AB39: =SUM(AB28:AB38) -> 3114808.4 | AC39: =SUM(B39:J39) -> 27015727 | AD39: =SUM(K39:V39) -> 36312204 | AE39: =SUM(W39:AB39) -> 18205394
A40: Reported EBITDA | B40: =B24-B39 -> 963512.77 | C40: =C24-C39 -> 1132935.9 | D40: =D24-D39 -> 1182164.8 | E40: =E24-E39 -> 1015597.8 | F40: =F24-F39 -> 1121552.9 | G40: =G24-G39 -> 962961.89 | H40: =H24-H39 -> 1178049.4 | I40: =I24-I39 -> 1290608.7 | ... AB40: =AB24-AB39 -> 1238610.2 | AC40: =SUM(B40:J40) -> 9588016.6 | AD40: =SUM(K40:V40) -> 13795264 | AE40: =SUM(W40:AB40) -> 6996371.3
A41: EBITDA Margin | B41: =IF(B14=0,"",B40/B14) -> 0.10805327 | C41: =IF(C14=0,"",C40/C14) -> 0.1243672 | D41: =IF(D14=0,"",D40/D14) -> 0.12648496 | E41: =IF(E14=0,"",E40/E14) -> 0.11384159 | F41: =IF(F14=0,"",F40/F14) -> 0.12741295 | G41: =IF(G14=0,"",G40/G14) -> 0.11029547 | H41: =IF(H14=0,"",H40/H14) -> 0.1271764 | I41: =IF(I14=0,"",I40/I14) -> 0.13199707 | ... AB41: =IF(AB14=0,"",AB40/AB14) -> 0.1294256 | AC41: =AC40/AC14 -> 0.11797292 | AD41: =AD40/AD14 -> 0.12490699 | AE41: =AE40/AE14 -> 0.12589237

Sheet Balance Sheet
A1: Nemeris Field Systems, LLC | Detailed Balance Sheet
A2: Management accounts | USD (whole dollars) | Unaudited | Source: borrower Monthly Financial Package, Balance Sheet tab
A6: Account | B6: Apr 2024 | C6: May 2024 | D6: Jun 2024 | E6: Jul 2024 | F6: Aug 2024 | G6: Sep 2024 | H6: Oct 2024 | I6: Nov 2024 | J6: Dec 2024 | K6: Jan 2025 | L6: Feb 2025 | M6: Mar 2025 | N6: Apr 2025 | O6: May 2025 | P6: Jun 2025 | Q6: Jul 2025 | R6: Aug 2025 | S6: Sep 2025 | T6: Oct 2025 | U6: Nov 2025 | V6: Dec 2025 | W6: Jan 2026 | X6: Feb 2026 | Y6: Mar 2026 | Z6: Apr 2026 | AA6: May 2026 | AB6: Jun 2026 | AC6: FY2024 (Apr-Dec, partial) | AD6: FY2025 | AE6: 2026 YTD (Jan-Jun)
A7: CURRENT ASSETS
A8: Cash and cash equivalents | B8: 2964886 | C8: 3055520.9 | D8: 3150094 | E8: 3231341.9 | F8: 3321066.1 | G8: 3398103.1 | H8: 3492347 | I8: 3595595.7 | J8: 3654846.3 | K8: 3729670.1 | L8: 3813769.3 | M8: 3909524.8 | N8: 4001149.3 | O8: 4099807.2 | P8: 4209221.4 | Q8: 4311540.9 | R8: 4398195.3 | S8: 4492101 | T8: 4597091.9 | U8: 4692215.4 | V8: 4758467.5 | W8: 4842208.6 | X8: 4923308.3 | Y8: 5011670.3 | Z8: 5116778.8 | AA8: 5219088.3 | AB8: 5318177.2 | AC8: =SUM(B8:J8) -> 29863801 | AD8: =SUM(K8:V8) -> 51012754 | AE8: =SUM(W8:AB8) -> 30431232
A9: Accounts receivable | B9: 12372657 | C9: 12625911 | D9: 12969531 | E9: 12248738 | F9: 12221396 | G9: 11930275 | H9: 12757160 | I9: 13610357 | J9: 11739060 | K9: 11851705 | L9: 12288853 | M9: 12620666 | N9: 12598329 | O9: 13210849 | P9: 13068247 | Q9: 13026724 | R9: 12983136 | S9: 12802097 | T9: 13210700 | U9: 13183381 | V9: 11180605 | W9: 12218691 | X9: 12396277 | Y9: 12448299 | Z9: 12677782 | AA9: 12959002 | AB9: 12821962 | AC9: =SUM(B9:J9) -> 112475086 | AD9: =SUM(K9:V9) -> 1.5202529e+08 | AE9: =SUM(W9:AB9) -> 75522013
A10: Inventory | B10: 6756913.7 | C10: 6701161.1 | D10: 6858866.4 | E10: 6691397.2 | F10: 6359985 | G10: 6440148.5 | H10: 6869108.3 | I10: 7263794.9 | J10: 6362164.3 | K10: 6382506.3 | L10: 6503920.3 | M10: 6562275.7 | N10: 6804665.8 | O10: 7065342.9 | P10: 6837400.4 | Q10: 6944154.5 | R10: 7003601.8 | S10: 6815629 | T10: 7117738.5 | U10: 7337262 | V10: 6080218.5 | W10: 6598892 | X10: 6779238.7 | Y10: 6756157.4 | Z10: 6791281.5 | AA10: 7034797.8 | AB10: 7042460.9 | AC10: =SUM(B10:J10) -> 60303539 | AD10: =SUM(K10:V10) -> 81454716 | AE10: =SUM(W10:AB10) -> 41002828
A11: Prepaid and other current assets | B11: 998705.82 | C11: 1020275.6 | D11: 1046784.2 | E11: 999168.71 | F11: 985880.41 | G11: 977843.71 | H11: 1037468.7 | I11: 1095086.2 | J11: 941366.15 | K11: 958912.77 | L11: 990608.59 | M11: 1020097.1 | N11: 1026987.9 | O11: 1068468.4 | P11: 1068873.2 | Q11: 1057854.6 | R11: 1042971.7 | S11: 1041526.6 | T11: 1078948.8 | U11: 1088946.3 | V11: 925565.03 | W11: 994303.72 | X11: 1012285.3 | Y11: 1026764.7 | Z11: 1047647.5 | AA11: 1071466.3 | AB11: 1071846.3 | AC11: =SUM(B11:J11) -> 9102579.5 | AD11: =SUM(K11:V11) -> 12369761 | AE11: =SUM(W11:AB11) -> 6224313.8
A13: NON-CURRENT ASSETS
A14: Property and field equipment, net | B14: 8988352.4 | C14: 9182480.5 | D14: 9421057.6 | E14: 8992518.4 | F14: 8872923.7 | G14: 8800593.4 | H14: 9337218.6 | I14: 9855775.9 | J14: 8472295.3 | K14: 8630215 | L14: 8915477.3 | M14: 9180874.1 | N14: 9242890.9 | O14: 9616215.8 | P14: 9619858.7 | Q14: 9520691.7 | R14: 9386745.6 | S14: 9373739.1 | T14: 9710539.1 | U14: 9800516.9 | V14: 8330085.3 | W14: 8948733.5 | X14: 9110567.9 | Y14: 9240882.1 | Z14: 9428827.7 | AA14: 9643196.3 | AB14: 9646616.8 | AC14: =SUM(B14:J14) -> 81923216 | AD14: =SUM(K14:V14) -> 1.1132785e+08 | AE14: =SUM(W14:AB14) -> 56018824
A15: Capitalized software and other assets | B15: 2496764.6 | C15: 2550689 | D15: 2616960.4 | E15: 2497921.8 | F15: 2464701 | G15: 2444609.3 | H15: 2593671.8 | I15: 2737715.5 | J15: 2353415.4 | K15: 2397281.9 | L15: 2476521.5 | M15: 2550242.8 | N15: 2567469.7 | O15: 2671171.1 | P15: 2672183 | Q15: 2644636.6 | R15: 2607429.3 | S15: 2603816.4 | T15: 2697372 | U15: 2722365.8 | V15: 2313912.6 | W15: 2485759.3 | X15: 2530713.3 | Y15: 2566911.7 | Z15: 2619118.8 | AA15: 2678665.6 | AB15: 2679615.8 | AC15: =SUM(B15:J15) -> 22756449 | AD15: =SUM(K15:V15) -> 30924403 | AE15: =SUM(W15:AB15) -> 15560785
A16: Total Assets | B16: =B8+B9+B10+B11+B14+B15 -> 34578280 | C16: =C8+C9+C10+C11+C14+C15 -> 35136038 | D16: =D8+D9+D10+D11+D14+D15 -> 36063294 | E16: =E8+E9+E10+E11+E14+E15 -> 34661086 | F16: =F8+F9+F10+F11+F14+F15 -> 34225952 | G16: =G8+G9+G10+G11+G14+G15 -> 33991573 | H16: =H8+H9+H10+H11+H14+H15 -> 36086975 | I16: =I8+I9+I10+I11+I14+I15 -> 38158326 | ... AB16: =AB8+AB9+AB10+AB11+AB14+AB15 -> 38580678 | AC16: =J16 -> 33523147 | AD16: =V16 -> 33588854 | AE16: =AB16 -> 38580678
A18: LIABILITIES AND EQUITY
A19: Trade accounts payable | B19: 4925039.3 | C19: 4884401.8 | D19: 4999351.5 | E19: 4877285 | F19: 4635722.4 | G19: 4694152.7 | H19: 5006816.7 | I19: 5294499.4 | J19: 4637310.9 | K19: 4652137.9 | L19: 4740635.2 | M19: 4783169.8 | N19: 4959845.3 | O19: 5149849.9 | P19: 4983705.2 | Q19: 5061517.1 | R19: 5104847.5 | S19: 4967836.2 | T19: 5188040.5 | U19: 5348048.7 | V19: 4431803.7 | W19: 4809859 | X19: 4941311.7 | Y19: 4924488.1 | Z19: 4950089.6 | AA19: 5127585.9 | AB19: 5133171.5 | AC19: =SUM(B19:J19) -> 43954580 | AD19: =SUM(K19:V19) -> 59371437 | AE19: =SUM(W19:AB19) -> 29886506
A20: Accrued field and vendor costs | B20: 1081106.2 | C20: 1072185.8 | D20: 1097418.6 | E20: 1070623.5 | F20: 1017597.6 | G20: 1030423.8 | H20: 1099057.3 | I20: 1162207.2 | J20: 1017946.3 | K20: 1021201 | L20: 1040627.2 | M20: 1049964.1 | N20: 1088746.5 | O20: 1130454.9 | P20: 1093984.1 | Q20: 1111064.7 | R20: 1120576.3 | S20: 1090500.6 | T20: 1138838.2 | U20: 1173961.9 | V20: 972834.96 | W20: 1055822.7 | X20: 1084678.2 | Y20: 1080985.2 | Z20: 1086605 | AA20: 1125567.6 | AB20: 1126793.7 | AC20: =SUM(B20:J20) -> 9648566.3 | AD20: =SUM(K20:V20) -> 13032754 | AE20: =SUM(W20:AB20) -> 6560452.5
A21: Senior secured term loan | B21: 27600097 | C21: 27434497 | D21: 27269890 | E21: 27106271 | F21: 26943633 | G21: 26781971 | H21: 26621279 | I21: 26461552 | J21: 26302782 | K21: 26144966 | L21: 25988096 | M21: 25832167 | N21: 25677174 | O21: 25523111 | P21: 25369973 | Q21: 25217753 | R21: 25066446 | S21: 24916048 | T21: 24766551 | U21: 24617952 | V21: 24470244 | W21: 24323423 | X21: 24177482 | Y21: 24032417 | Z21: 23888223 | AA21: 23744893 | AB21: 23602424 | AC21: =SUM(B21:J21) -> 2.4252197e+08 | AD21: =SUM(K21:V21) -> 3.0359048e+08 | AE21: =SUM(W21:AB21) -> 1.4376886e+08
A22: Total Liabilities | B22: =B19+B20+B21 -> 33606243 | C22: =C19+C20+C21 -> 33391085 | D22: =D19+D20+D21 -> 33366660 | E22: =E19+E20+E21 -> 33054179 | F22: =F19+F20+F21 -> 32596953 | G22: =G19+G20+G21 -> 32506548 | H22: =H19+H20+H21 -> 32727153 | I22: =I19+I20+I21 -> 32918258 | ... AB22: =AB19+AB20+AB21 -> 29862389 | AC22: =J22 -> 31958039 | AD22: =V22 -> 29874883 | AE22: =AB22 -> 29862389
A23: Members' equity | B23: 972036.85 | C23: 1744953.2 | D23: 2696633.9 | E23: 1606906.6 | F23: 1628999.5 | G23: 1485025.7 | H23: 3359821.2 | I23: 5240067.3 | J23: 1565107.9 | K23: 2131986.7 | L23: 3219792 | M23: 4178379.1 | N23: 4515726.6 | O23: 5928438.3 | P23: 6028122 | Q23: 6115268 | R23: 6130209.5 | S23: 6154525 | T23: 7318960.7 | U23: 7684724.3 | V23: 3713971.3 | W23: 5899483.3 | X23: 6548918.7 | Y23: 7012795.1 | Z23: 7756519.2 | AA23: 8608168.9 | AB23: 8718289.1 | AC23: =SUM(B23:J23) -> 20299552 | AD23: =SUM(K23:V23) -> 63120104 | AE23: =SUM(W23:AB23) -> 44544174
A24: Total Liabilities and Equity | B24: =B22+B23 -> 34578280 | C24: =C22+C23 -> 35136038 | D24: =D22+D23 -> 36063294 | E24: =E22+E23 -> 34661086 | F24: =F22+F23 -> 34225952 | G24: =G22+G23 -> 33991573 | H24: =H22+H23 -> 36086975 | I24: =I22+I23 -> 38158326 | ... AB24: =AB22+AB23 -> 38580678 | AC24: =J24 -> 33523147 | AD24: =V24 -> 33588854 | AE24: =AB24 -> 38580678
A26: Balance Check (Total Assets - Total Liabilities and Equity) | B26: =B16-B24 -> 0 | C26: =C16-C24 -> 0 | D26: =D16-D24 -> 0 | E26: =E16-E24 -> 0 | F26: =F16-F24 -> 0 | G26: =G16-G24 -> 0 | H26: =H16-H24 -> 0 | I26: =I16-I24 -> 0 | ... AB26: =AB16-AB24 -> 0 | AC26: =J26 -> 0 | AD26: =V26 -> 0 | AE26: =AB26 -> 0
A28: DEBT & LIQUIDITY (borrower-certified roll-forward; source: Debt & Liquidity tab)
A29: Beginning Debt | B29: 27766698 | C29: =B33 -> 27600097 | D29: =C33 -> 27434497 | E29: =D33 -> 27269890 | F29: =E33 -> 27106271 | G29: =F33 -> 26943633 | H29: =G33 -> 26781971 | I29: =H33 -> 26621279 | J29: =I33 -> 26461552 | ... AB29: =AA33 -> 23744893 | AC29: =B29 -> 27766698 | AD29: =K29 -> 26302782 | AE29: =W29 -> 24470244
A30: Draws | B30: 0 | C30: 0 | D30: 0 | E30: 0 | F30: 0 | G30: 0 | H30: 0 | I30: 0 | J30: 0 | K30: 0 | L30: 0 | M30: 0 | N30: 0 | O30: 0 | P30: 0 | Q30: 0 | R30: 0 | S30: 0 | T30: 0 | U30: 0 | V30: 0 | W30: 0 | X30: 0 | Y30: 0 | Z30: 0 | AA30: 0 | AB30: 0 | AC30: =SUM(B30:J30) -> 0 | AD30: =SUM(K30:V30) -> 0 | AE30: =SUM(W30:AB30) -> 0
A31: PIK | B31: 0 | C31: 0 | D31: 0 | E31: 0 | F31: 0 | G31: 0 | H31: 0 | I31: 0 | J31: 0 | K31: 0 | L31: 0 | M31: 0 | N31: 0 | O31: 0 | P31: 0 | Q31: 0 | R31: 0 | S31: 0 | T31: 0 | U31: 0 | V31: 0 | W31: 0 | X31: 0 | Y31: 0 | Z31: 0 | AA31: 0 | AB31: 0 | AC31: =SUM(B31:J31) -> 0 | AD31: =SUM(K31:V31) -> 0 | AE31: =SUM(W31:AB31) -> 0
A32: Scheduled Principal | B32: -166600.19 | C32: -165600.58 | D32: -164606.98 | E32: -163619.34 | F32: -162637.62 | G32: -161661.8 | H32: -160691.83 | I32: -159727.68 | J32: -158769.31 | K32: -157816.69 | L32: -156869.79 | M32: -155928.58 | N32: -154993 | O32: -154063.05 | P32: -153138.67 | Q32: -152219.84 | R32: -151306.52 | S32: -150398.68 | T32: -149496.29 | U32: -148599.31 | V32: -147707.71 | W32: -146821.47 | X32: -145940.54 | Y32: -145064.89 | Z32: -144194.5 | AA32: -143329.34 | AB32: -142469.36 | AC32: =SUM(B32:J32) -> -1463915.3 | AD32: =SUM(K32:V32) -> -1832538.1 | AE32: =SUM(W32:AB32) -> -867820.1
A33: Ending Debt | B33: =B29+B30+B31+B32 -> 27600097 | C33: =C29+C30+C31+C32 -> 27434497 | D33: =D29+D30+D31+D32 -> 27269890 | E33: =E29+E30+E31+E32 -> 27106271 | F33: =F29+F30+F31+F32 -> 26943633 | G33: =G29+G30+G31+G32 -> 26781971 | H33: =H29+H30+H31+H32 -> 26621279 | I33: =I29+I30+I31+I32 -> 26461552 | ... AB33: =AB29+AB30+AB31+AB32 -> 23602424 | AC33: =J33 -> 26302782 | AD33: =V33 -> 24470244 | AE33: =AB33 -> 23602424
A34: Cash | B34: =B8 -> 2964886 | C34: =C8 -> 3055520.9 | D34: =D8 -> 3150094 | E34: =E8 -> 3231341.9 | F34: =F8 -> 3321066.1 | G34: =G8 -> 3398103.1 | H34: =H8 -> 3492347 | I34: =I8 -> 3595595.7 | ... AB34: =AB8 -> 5318177.2 | AC34: =J34 -> 3654846.3 | AD34: =V34 -> 4758467.5 | AE34: =AB34 -> 5318177.2
A35: Net Debt | B35: =B33-B34 -> 24635211 | C35: =C33-C34 -> 24378976 | D35: =D33-D34 -> 24119796 | E35: =E33-E34 -> 23874929 | F35: =F33-F34 -> 23622567 | G35: =G33-G34 -> 23383868 | H35: =H33-H34 -> 23128932 | I35: =I33-I34 -> 22865956 | ... AB35: =AB33-AB34 -> 18284247 | AC35: =J35 -> 22647936 | AD35: =V35 -> 19711777 | AE35: =AB35 -> 18284247
A36: TTM Covenant EBITDA | B36: 10844336 | C36: 11003184 | D36: 11152546 | E36: 11085286 | F36: 11410216 | G36: 11549787 | H36: 11759302 | I36: 12047872 | J36: 12228609 | K36: 12394317 | L36: 12500341 | M36: =SUM('Income Statement'!B40:M40) -> 12771497 | N36: =SUM('Income Statement'!C40:N40) -> 12953291 | O36: =SUM('Income Statement'!D40:O40) -> 13053579 | P36: =SUM('Income Statement'!E40:P40) -> 13239092 | Q36: =SUM('Income Statement'!F40:Q40) -> 13502488 | R36: =SUM('Income Statement'!G40:R40) -> 13464115 | S36: =SUM('Income Statement'!H40:S40) -> 13674974 | T36: =SUM('Income Statement'!I40:T40) -> 13809311 | ... AB36: =SUM('Income Statement'!Q40:AB40) -> 13861947 | AC36: =J36 -> 12228609 | AD36: =V36 -> 13795264 | AE36: =AB36 -> 13861947
A37: Net Leverage Ratio | B37: =IF(B36=0,"",B35/B36) -> 2.2717122 | C37: =IF(C36=0,"",C35/C36) -> 2.2156292 | D37: =IF(D36=0,"",D35/D36) -> 2.1627165 | E37: =IF(E36=0,"",E35/E36) -> 2.1537495 | F37: =IF(F36=0,"",F35/F36) -> 2.0702997 | G37: =IF(G36=0,"",G35/G36) -> 2.0246147 | H37: =IF(H36=0,"",H35/H36) -> 1.9668627 | I37: =IF(I36=0,"",I35/I36) -> 1.8979248 | ... AB37: =IF(AB36=0,"",AB35/AB36) -> 1.3190244 | AC37: =J37 -> 1.8520452 | AD37: =V37 -> 1.4288799 | AE37: =AB37 -> 1.3190244
A38: Maximum Covenant (Net Leverage Ratio) | B38: 5 | C38: 5 | D38: 5 | E38: 5 | F38: 5 | G38: 5 | H38: 5 | I38: 5 | J38: 5 | K38: 5 | L38: 5 | M38: 5 | N38: 5 | O38: 5 | P38: 5 | Q38: 5 | R38: 5 | S38: 5 | T38: 5 | U38: 5 | V38: 5 | W38: 5 | X38: 5 | Y38: 5 | Z38: 5 | AA38: 5 | AB38: 5 | AC38: =J38 -> 5 | AD38: =V38 -> 5 | AE38: =AB38 -> 5
A40: COVENANT-SUPPORT ROWS (facility Fixed-Charges inputs; source noted per row below)
A41: Cash Interest Expense | B41: 0 | C41: 0 | D41: 0 | E41: 0 | F41: 0 | G41: 0 | H41: 0 | I41: 0 | J41: 0 | K41: 131411.62 | L41: 215144.02 | M41: 236757.36 | N41: 227728.61 | O41: 233881.77 | P41: 224945.78 | Q41: 231006.17 | R41: 229568.38 | S41: 220771.53 | T41: 226692.78 | U41: 217988.69 | V41: 223817.18 | W41: 222379.39 | X41: 199560.15 | Y41: 219503.79 | Z41: 211031.61 | AA41: 216628.2 | AB41: 208248.77 | AC41: =SUM(B41:J41) -> 0 | AD41: =SUM(K41:V41) -> 2619713.9 | AE41: =SUM(W41:AB41) -> 1277351.9
A42: Scheduled Debt Principal Payments | B42: 0 | C42: 0 | D42: 0 | E42: 0 | F42: 0 | G42: 0 | H42: 0 | I42: 0 | J42: 0 | K42: =-K32 -> 157816.69 | L42: =-L32 -> 156869.79 | M42: =-M32 -> 155928.58 | N42: =-N32 -> 154993 | O42: =-O32 -> 154063.05 | P42: =-P32 -> 153138.67 | Q42: =-Q32 -> 152219.84 | R42: =-R32 -> 151306.52 | ... AB42: =-AB32 -> 142469.36 | AC42: =SUM(B42:J42) -> 0 | AD42: =SUM(K42:V42) -> 1832538.1 | AE42: =SUM(W42:AB42) -> 867820.1

Sheet Cash Flow Statement
A1: Nemeris Field Systems, LLC | Detailed Cash Flow Statement (as reported)
A2: Management accounts | USD (whole dollars) | Unaudited | Source: borrower Monthly Financial Package, Cash Flow tab
A6: Account | B6: Apr 2024 | C6: May 2024 | D6: Jun 2024 | E6: Jul 2024 | F6: Aug 2024 | G6: Sep 2024 | H6: Oct 2024 | I6: Nov 2024 | J6: Dec 2024 | K6: Jan 2025 | L6: Feb 2025 | M6: Mar 2025 | N6: Apr 2025 | O6: May 2025 | P6: Jun 2025 | Q6: Jul 2025 | R6: Aug 2025 | S6: Sep 2025 | T6: Oct 2025 | U6: Nov 2025 | V6: Dec 2025 | W6: Jan 2026 | X6: Feb 2026 | Y6: Mar 2026 | Z6: Apr 2026 | AA6: May 2026 | AB6: Jun 2026 | AC6: FY2024 (Apr-Dec, partial) | AD6: FY2025 | AE6: 2026 YTD (Jan-Jun)
A7: OPERATING ACTIVITIES
A8: Reported EBITDA | B8: 963512.77 | C8: 1132935.9 | D8: 1182164.8 | E8: 1015597.8 | F8: 1121552.9 | G8: 962961.89 | H8: 1178049.4 | I8: 1290608.7 | J8: 740632.43 | K8: 935297.78 | L8: 1051239.8 | M8: 1196943.2 | N8: 1145306.6 | O8: 1233223.6 | P8: 1367677.5 | Q8: 1278994.2 | R8: 1083179.6 | S8: 1173821.6 | T8: 1312386.5 | U8: 1189043 | V8: 828151.16 | W8: 1046764 | X8: 1013746.7 | Y8: 1104524.4 | Z8: 1313857.4 | AA8: 1278868.6 | AB8: 1238610.2 | AC8: =SUM(B8:J8) -> 9588016.6 | AD8: =SUM(K8:V8) -> 13795264 | AE8: =SUM(W8:AB8) -> 6996371.3
A9: Working capital and other operating uses | B9: -681291.05 | C9: -831382.98 | D9: -875698.04 | E9: -730106.74 | F9: -824328.97 | G9: -685744.66 | H9: -875991.66 | I9: -976007.96 | J9: -492987.23 | K9: -665245.36 | L9: -768221.26 | M9: -897381.42 | N9: -852876.79 | O9: -931173.7 | P9: -1050417.6 | Q9: -973295.05 | R9: -801891.5 | S9: -882564.31 | T9: -1005403.8 | U9: -897758.53 | V9: -581065.31 | W9: -774330.89 | X9: -746156.51 | Y9: -826916.56 | Z9: -1012000 | AA9: -982075.02 | AB9: -947507.66 | AC9: =SUM(B9:J9) -> -6973539.3 | AD9: =SUM(K9:V9) -> -10307295 | AE9: =SUM(W9:AB9) -> -5288986.7
A10: Net cash from operating activities | B10: =B8+B9 -> 282221.72 | C10: =C8+C9 -> 301552.88 | D10: =D8+D9 -> 306466.75 | E10: =E8+E9 -> 285491.07 | F10: =F8+F9 -> 297223.98 | G10: =G8+G9 -> 277217.23 | H10: =H8+H9 -> 302057.76 | I10: =I8+I9 -> 314600.72 | ... AB10: =AB8+AB9 -> 291102.59 | AC10: =SUM(B10:J10) -> 2614477.3 | AD10: =SUM(K10:V10) -> 3487969.9 | AE10: =SUM(W10:AB10) -> 1707384.7
A12: INVESTING ACTIVITIES
A13: Capital expenditures | B13: -38540.511 | C13: -45317.434 | D13: -47286.592 | E13: -40623.912 | F13: -44862.118 | G13: -38518.476 | H13: -47121.977 | I13: -51624.347 | J13: -29625.297 | K13: -37411.911 | L13: -42049.593 | M13: -47877.727 | N13: -45812.263 | O13: -49328.943 | P13: -54707.102 | Q13: -51159.768 | R13: -43327.183 | S13: -46952.863 | T13: -52495.459 | U13: -47561.72 | V13: -33126.046 | W13: -41870.562 | X13: -40549.866 | Y13: -44180.975 | Z13: -52554.297 | AA13: -51154.744 | AB13: -49544.41 | AC13: =SUM(B13:J13) -> -383520.66 | AD13: =SUM(K13:V13) -> -551810.58 | AE13: =SUM(W13:AB13) -> -279854.85
A14: Net cash used in investing activities | B14: =B13 -> -38540.511 | C14: =C13 -> -45317.434 | D14: =D13 -> -47286.592 | E14: =E13 -> -40623.912 | F14: =F13 -> -44862.118 | G14: =G13 -> -38518.476 | H14: =H13 -> -47121.977 | I14: =I13 -> -51624.347 | ... AB14: =AB13 -> -49544.41 | AC14: =SUM(B14:J14) -> -383520.66 | AD14: =SUM(K14:V14) -> -551810.58 | AE14: =SUM(W14:AB14) -> -279854.85
A16: FINANCING ACTIVITIES
A17: Term loan draws | B17: 0 | C17: 0 | D17: 0 | E17: 0 | F17: 0 | G17: 0 | H17: 0 | I17: 0 | J17: 0 | K17: 0 | L17: 0 | M17: 0 | N17: 0 | O17: 0 | P17: 0 | Q17: 0 | R17: 0 | S17: 0 | T17: 0 | U17: 0 | V17: 0 | W17: 0 | X17: 0 | Y17: 0 | Z17: 0 | AA17: 0 | AB17: 0 | AC17: =SUM(B17:J17) -> 0 | AD17: =SUM(K17:V17) -> 0 | AE17: =SUM(W17:AB17) -> 0
A18: Scheduled principal payments | B18: -166600.19 | C18: -165600.58 | D18: -164606.98 | E18: -163619.34 | F18: -162637.62 | G18: -161661.8 | H18: -160691.83 | I18: -159727.68 | J18: -158769.31 | K18: -157816.69 | L18: -156869.79 | M18: -155928.58 | N18: -154993 | O18: -154063.05 | P18: -153138.67 | Q18: -152219.84 | R18: -151306.52 | S18: -150398.68 | T18: -149496.29 | U18: -148599.31 | V18: -147707.71 | W18: -146821.47 | X18: -145940.54 | Y18: -145064.89 | Z18: -144194.5 | AA18: -143329.34 | AB18: -142469.36 | AC18: =SUM(B18:J18) -> -1463915.3 | AD18: =SUM(K18:V18) -> -1832538.1 | AE18: =SUM(W18:AB18) -> -867820.1
A19: Net cash from financing activities | B19: =B17+B18 -> -166600.19 | C19: =C17+C18 -> -165600.58 | D19: =D17+D18 -> -164606.98 | E19: =E17+E18 -> -163619.34 | F19: =F17+F18 -> -162637.62 | G19: =G17+G18 -> -161661.8 | H19: =H17+H18 -> -160691.83 | I19: =I17+I18 -> -159727.68 | ... AB19: =AB17+AB18 -> -142469.36 | AC19: =SUM(B19:J19) -> -1463915.3 | AD19: =SUM(K19:V19) -> -1832538.1 | AE19: =SUM(W19:AB19) -> -867820.1
A20: Net change in cash | B20: =B10+B14+B19 -> 77081.02 | C20: =C10+C14+C19 -> 90634.87 | D20: =D10+D14+D19 -> 94573.18 | E20: =E10+E14+E19 -> 81247.82 | F20: =F10+F14+F19 -> 89724.24 | G20: =G10+G14+G19 -> 77036.95 | H20: =H10+H14+H19 -> 94243.95 | I20: =I10+I14+I19 -> 103248.69 | ... AB20: =AB10+AB14+AB19 -> 99088.82 | AC20: =SUM(B20:J20) -> 767041.31 | AD20: =SUM(K20:V20) -> 1103621.2 | AE20: =SUM(W20:AB20) -> 559709.7
A21: Ending cash | B21: 2964886 | C21: =B21+C20 -> 3055520.9 | D21: =C21+D20 -> 3150094 | E21: =D21+E20 -> 3231341.9 | F21: =E21+F20 -> 3321066.1 | G21: =F21+G20 -> 3398103.1 | H21: =G21+H20 -> 3492347 | I21: =H21+I20 -> 3595595.7 | J21: =I21+J20 -> 3654846.3 | ... AB21: =AA21+AB20 -> 5318177.2 | AC21: =J21 -> 3654846.3 | AD21: =V21 -> 4758467.5 | AE21: =AB21 -> 5318177.2
A23: Memo: Cash per Balance Sheet | B23: ='Balance Sheet'!B8 -> 2964886 | C23: ='Balance Sheet'!C8 -> 3055520.9 | D23: ='Balance Sheet'!D8 -> 3150094 | E23: ='Balance Sheet'!E8 -> 3231341.9 | F23: ='Balance Sheet'!F8 -> 3321066.1 | G23: ='Balance Sheet'!G8 -> 3398103.1 | H23: ='Balance Sheet'!H8 -> 3492347 | I23: ='Balance Sheet'!I8 -> 3595595.7 | ... AB23: ='Balance Sheet'!AB8 -> 5318177.2 | AC23: =J23 -> 3654846.3 | AD23: =V23 -> 4758467.5 | AE23: =AB23 -> 5318177.2
A24: Memo: CF-vs-BS cash tie (diff, should be 0) | B24: =B21-B23 -> 0 | C24: =C21-C23 -> 0 | D24: =D21-D23 -> 0 | E24: =E21-E23 -> 0 | F24: =F21-F23 -> 0 | G24: =G21-G23 -> 0 | H24: =H21-H23 -> 0 | I24: =I21-I23 -> 0 | ... AB24: =AB21-AB23 -> 0 | AC24: =J24 -> 0 | AD24: =V24 -> 0 | AE24: =AB24 -> 0
A25: Memo: CF EBITDA vs IS EBITDA tie (diff, should be 0) | B25: =B8-'Income Statement'!B40 -> 0 | C25: =C8-'Income Statement'!C40 -> 0 | D25: =D8-'Income Statement'!D40 -> 0 | E25: =E8-'Income Statement'!E40 -> 0 | F25: =F8-'Income Statement'!F40 -> 0 | G25: =G8-'Income Statement'!G40 -> 0 | H25: =H8-'Income Statement'!H40 -> 0 | I25: =I8-'Income Statement'!I40 -> 0 | ... AB25: =AB8-'Income Statement'!AB40 -> 0 | AC25: =J25 -> 0 | AD25: =V25 -> 0 | AE25: =AB25 -> 0

Sheet Sources & Notes
A1: Entity | B1: Nemeris Field Systems, LLC (consolidated) — the model does not identify separate divisional/subsidiary consolidation levels in the reporting package; single consolidated entity assumed per borrower-config model.entity='consolidated'.
A2: Units | B2: USD, whole dollars (model.scale = 1). Borrower's own package states 'Management accounts | USD | Unaudited'.
A3: Basis | B3: Actuals only — company-prepared monthly management accounts, unaudited. No proforma/budget/forecast figures are included.
A4: Coverage | B4: Apr 2024 through Jun 2026 (27 months), matching every monthly subfolder present in the reporting-packages folder (2024.04 through 2026.06, continuous, no gaps).
A5: Primary source file | B5: Every Income Statement / Balance Sheet / Cash Flow / Debt & Liquidity figure in this model is sourced from the LATEST, most-consolidated reporting package: Monthly_Financial_Package_2026-06.xlsx. That single package's rolling ~30-month window (2024-01 through 2026-06) already spans the entire model range, so per the 'latest/most-consolidated source wins' rule it is the winning source for every month in this model.
A6: Restatement scan | B6: Full restatement scan performed: every one of the 26 earlier monthly packages (Monthly_Financial_Package_2024-04.xlsx through Monthly_Financial_Package_2026-05.xlsx) was compared, line-by-line, against the 2026-06 consolidated package's value for that same package's own reported month, across all four source tabs (Income Statement, Balance Sheet, Cash Flow, Debt & Liquidity). Result: ZERO differences found at any line, any month (all diffs < $0.01). This is consistent with the borrower's own 2026-06 Close Notes: 'First-and-final 2026-06 package; no restatement or basis change.' restatements.json is written empty (schema present, zero entries).
A7: Cash Flow | B7: As-reported from the borrower's own 'Cash Flow' tab (not derived) — the borrower delivers a full Operating/Investing/Financing cash flow every month. Reported EBITDA is the CF tab's own starting line (ties exactly to the Income Statement's Reported EBITDA every month — see the CF sheet's memo tie-out row). Ending cash for the first model month (Apr 2024) is hardcoded from source; every subsequent month is a live formula (prior Ending Cash + this month's Net Change in Cash) and ties to the Balance Sheet's Cash and cash equivalents line every month (see memo tie-out rows on the Cash Flow Statement sheet; both diffs compute to 0).
A8: Balance Sheet — no current subtotal | B8: The borrower's own Balance Sheet carries only 'CURRENT ASSETS' / 'NON-CURRENT ASSETS' section headers with no Total Current Assets / Total Current Liabilities subtotal rows. None are invented here, consistent with borrower-config's analysis_lines._omitted_note; current_ratio/working-capital ratios will be suppressed downstream with a disclosed reason.
A9: Balance Sheet FY/YTD columns | B9: Balance Sheet FY2024/FY2025/2026-YTD columns are PERIOD-END (spot) snapshots — the last month's value in that period, not a sum — for every BALANCE/stock-type row (Cash and cash equivalents through Total Liabilities and Equity, Balance Check, and — in the Debt & Liquidity block below — Beginning Debt, Ending Debt, Cash, Net Debt, TTM Covenant EBITDA, Net Leverage Ratio, Maximum Covenant), consistent with balance-sheet convention. FLOW-type rows on the same Balance Sheet tab (Draws, PIK, Scheduled Principal in the Debt & Liquidity block, and both covenant-support rows — Cash Interest Expense, Scheduled Debt Principal Payments) instead SUM over the period, like the Income Statement and Cash Flow Statement FY/YTD columns do, since a period total is what a Fixed-Charges-style coverage figure needs.
A10: No net income / interest / tax / D&A line | B10: The borrower's monthly management accounts stop at 'Reported EBITDA' — no Net Income, Interest Expense, Tax, or Depreciation & Amortization line appears anywhere in the package (Income Statement, Balance Sheet, or Cash Flow). None are invented here, consistent with borrower-config.json model_lines (net_income/interest_expense/taxes/depreciation_amortization left blank).
A11: No customer-level AR aging | B11: No customer-level accounts-receivable aging is delivered for this borrower (2026-06 Close Notes states this explicitly); only Inventory_Aging files are delivered monthly. This model carries the Balance Sheet's single 'Accounts receivable' line only.
A12: Inventory_and_Deployment_Support (2026-06) | B12: The extra file in the 2026.06 folder (Inventory_and_Deployment_Support_June_2026.xlsx) was reviewed: it is a supplementary inventory/ops detail and reconciliation file (Inventory Detail, Reconciliation, Review Notes tabs), not a core IS/BS/CF statement source. Its 'Reconciliation' tab ties its detailed net carrying value ($7,042,460.92) exactly to the June 2026 Balance Sheet's Inventory line — confirms BS integrity but was NOT used as a build input beyond that confirmation.
... A20: Build tool / recalc | B20: Built with openpyxl; formula cells recalculated (cached values populated) via headless LibreOffice as the LAST write, per assembling-rules.md. Gated with references/validate_model.py before becoming canonical.
